Workbook

Sheet KAS
C1: 1. KAS dan SETARA KAS
C2: Uang Tunai/Tabungan/Giro/Deposito
C4: 3173015410840005 | D4: SILVIA LISTIANI LIMANTO
I5: =SUM(I8:I38) -> 704944815 | K5: =SUM(K8:K38) -> 616081918 | L5: =SUM(L8:L38) -> 473848217 | M5: =SUM(M8:M38) -> 435252011 | N5: =SUM(N8:N38) -> 352433986 | O5: =SUM(O8:O38) -> 0
A6: NO | B6: KODE | C6: DESKRIPSI | D6: NOMOR AKUN | E6: ATAS NAMA | F6: NAMA BANK/INSTITUSI | G6: LOKASI HARTA | H6: TAHUN PEROLEHAN | I6: NILAI SAAT INI (2025) | J6: (HARTA PPS/ HARTA INVESTASI PPS) | K6: NILAI TAHUN SEBELUMNYA
K7: 2024 | L7: 2023 | M7: 2022 | N7: 2021 | O7: 2020 | Q7: - | R7: - | S7: -
A8: 1 | B8: =VLOOKUP(C8,$R:$S,2,0) -> 0101 | C8: UANG TUNAI | D8: - | E8: SILVIA LISTIANI LIMANTO | F8: - | G8: Indonesia | H8: 2025 | I8: 165000000 | J8: - | K8: 97500000 | L8: 68500000 | M8: 60000000 | N8: 5000000 | O8: 0 | Q8: 0101 | R8: UANG TUNAI | S8: 0101
A9: =A8+1 -> 2 | B9: =VLOOKUP(C9,$R:$S,2,0) -> 0102 | C9: TABUNGAN | D9: 8740120558 | E9: SILVIA LISTIANI LIMANTO | F9: BANK CENTRAL ASIA | G9: Indonesia | H9: 2025 | I9: 16559317 | J9: - | K9: 11383813 | L9: 10771832 | M9: 14353267 | N9: 12278746 | O9: 0 | Q9: 0102 | R9: TABUNGAN | S9: 0102
A10: =A9+1 -> 3 | B10: =VLOOKUP(C10,$R:$S,2,0) -> 0102 | C10: TABUNGAN | D10: 0702021575 | E10: SILVIA LISTIANI LIMANTO | F10: BANK PAN INDONESIA | G10: Indonesia | H10: 2025 | I10: 58080066 | J10: - | K10: 42080336 | L10: 59218861 | M10: 41221947 | N10: 105442298 | O10: 0 | Q10: 0103 | R10: GIRO | S10: 0103
A11: =A10+1 -> 4 | B11: =VLOOKUP(C11,$R:$S,2,0) -> 0102 | C11: TABUNGAN | D11: 0702912212 | E11: SILVIA LISTIANI LIMANTO | F11: BANK PAN INDONESIA | G11: Indonesia | H11: 2025 | I11: 330305432 | J11: - | K11: 320117769 | L11: 310357524 | M11: 304676797 | N11: 229712942 | O11: 0 | Q11: 0104 | R11: DEPOSITO | S11: 0104
A12: =A11+1 -> 5 | B12: =VLOOKUP(C12,$R:$S,2,0) -> 0109 | C12: SETARA KAS LAINNYA | D12: - | E12: SILVIA LISTIANI LIMANTO | F12: - | G12: Indonesia | H12: 2025 | I12: 135000000 | J12: - | K12: 145000000 | L12: 25000000 | M12: 15000000 | N12: 0 | O12: 0 | Q12: 0105 | R12: UANG ELEKTRONIK | S12: 0105
Q13: 0106 | R13: CEK | S13: 0106
Q14: 0107 | R14: WESSEL | S14: 0107
Q15: 0108 | R15: KERTAS KOMERSIAL | S15: 0108
Q16: 0109 | R16: SETARA KAS | S16: 0109
Q17: 0101 | R17: UANG TUNAI/BANK NOTE/KOIN | S17: 0101
Q18: 0109 | R18: SETARA KAS LAINNYA | S18: 0109
R19: SGD
Q20: Kurs 2017 | R20: 10086.53 | S20: =I9/R20 -> 1641.7258
Q21: Kurs 2016 | R21: 9292.03 | S21: =I9/R21 -> 1782.099
R22: =I9/50000 -> 331.18634
Q23: Kurs 2025 | R23: 13054.96

Sheet PIUTANG
C1: 2. PIUTANG
C2: Uang Tunai/Tabungan/Giro/Deposito
C4: 3173015410840005 | D4: SILVIA LISTIANI LIMANTO
I5: =SUM(I8:I55) -> 0 | K5: =SUM(K8:K55) -> 0 | L5: =SUM(L8:L55) -> 0 | M5: =SUM(M8:M55) -> 0 | N5: =SUM(N8:N55) -> 0 | O5: =SUM(O8:O55) -> 0
A6: NO | B6: KODE | C6: DESKRIPSI | D6: LOKASI PENERIMA PINJAMAN | E6: PENERIMA PINJAMAN | G6: NILAI PIUTANG | H6: TAHUN DIMULAI | I6: NILAI PIUTANG SAAT INI (2025) | J6: (HARTA PPS/ HARTA INVESTASI PPS) | K6: NILAI TAHUN SEBELUMNYA
E7: NIK / NPWP | F7: NAMA | K7: 2024 | L7: 2023 | M7: 2022 | N7: 2021 | O7: 2020 | Q7: - | R7: - | S7: -
A8: 1 | B8: =VLOOKUP(C8,$R:$S,2,0) -> - | C8: - | Q8: 0201 | R8: PIUTANG USAHA | S8: 0201
A9: =A8+1 -> 2 | Q9: 0202 | R9: PIUTANG AFILIASI | S9: 0202
A10: =A9+1 -> 3 | Q10: 0209 | R10: PIUTANG LAINNYA | S10: 0209
A11: =A10+1 -> 4
A12: =A11+1 -> 5
A13: =A12+1 -> 6
A14: =A13+1 -> 7
A15: =A14+1 -> 8
A16: =A15+1 -> 9
A17: =A16+1 -> 10
A18: =A17+1 -> 11
A19: =A18+1 -> 12
A20: =A19+1 -> 13
A21: =A20+1 -> 14
A22: =A21+1 -> 15
... A55: =A54+1 -> 48

Sheet INVEST
C1: 3. INVESTASI/SEKURITAS
C2: Saham yang dibeli untuk dijual kembali/Saham Non Bursa/Saham Bursa/Obligasi Perusahaan/Obligasi Pemerintah IndonesiaSurat Utang Lainnya/Asuransi/Unit Link di Asuransi
C4: 3173015410840005 | D4: SILVIA LISTIANI LIMANTO
H5: =SUM(H8:H46) -> 145350343 | J5: =SUM(J8:J46) -> 145350343 | L5: =SUM(L8:L46) -> 118039674 | M5: =SUM(M8:M46) -> 103565143 | N5: =SUM(N8:N46) -> 83352249 | O5: =SUM(O8:O46) -> 64372632 | P5: =SUM(P8:P46) -> 0
A6: NO | B6: KODE | C6: DESKRIPSI | D6: LOKASI HARTA | E6: BANK / INSTITUSI / PENERIMA INVESTASI | G6: NOMOR AKUN | H6: HARGA PEROLEHAN | I6: TAHUN PEROLEHAN | J6: NILAI SAAT INI (2025) | K6: (HARTA PPS/ HARTA INVESTASI PPS) | L6: NILAI TAHUN SEBELUMNYA
E7: NPWP | F7: NAMA | L7: 2024 | M7: 2023 | N7: 2022 | O7: 2021 | P7: 2020 | R7: - | S7: - | T7: -
A8: 1 | B8: =VLOOKUP(C8,$S:$T,2,0) -> 0311 | C8: UNIT LINK DI ASURANSI | D8: Indonesia | E8: 0013439658073000 | F8: PT PRUDENTIAL LIFE ASSURANCE | G8: 74563396 | H8: 87795905 | I8: 2025 | J8: 87795905 | K8: - | L8: 73551227 | M8: 66472264 | N8: 56298541 | O8: 46133132 | P8: 0 | R8: 0301 | S8: SAHAM YANG DIBELI UNTUK DIJUAL KEMBALI | T8: 0301
A9: 2 | B9: =VLOOKUP(C9,$S:$T,2,0) -> 0311 | C9: UNIT LINK DI ASURANSI | D9: Indonesia | E9: 0013439658073000 | F9: PT PRUDENTIAL LIFE ASSURANCE | G9: 11668684 | H9: 35155634 | I9: 2025 | J9: 35155634 | K9: - | L9: 27454723 | M9: 22960976 | N9: 16986561 | O9: 11551803 | P9: 0 | R9: 0302 | S9: SAHAM NON BURSA | T9: 0302
A10: 3 | B10: =VLOOKUP(C10,$S:$T,2,0) -> 0311 | C10: UNIT LINK DI ASURANSI | D10: Indonesia | E10: 0013392519038000 | F10: PANIN DAI-ICHI LIFE | G10: 2019018429 | H10: 22398804 | I10: 2025 | J10: 22398804 | K10: - | L10: 17033724 | M10: 14131903 | N10: 10067147 | O10: 6687697 | P10: 0 | R10: 0303 | S10: SAHAM BURSA | T10: 0303
R11: 0304 | S11: OBLIGASI PERUSAHAAN | T11: 0304
R12: 0305 | S12: OBLIGASI PEMERINTAH | T12: 0305
R13: 0306 | S13: SURAT UTANG LAINNYA | T13: 0306
R14: 0307 | S14: REKSADANA | T14: 0307
R15: 0309 | S15: PENYERTAAN MODAL DALAM PERUSAHAAN LAIN YANG BUKAN ATAS SAHAM | T15: 0309
R16: 0310 | S16: ASURANSI | T16: 0310
R17: 0311 | S17: UNIT LINK DI ASURANSI | T17: 0311
R18: 0399 | S18: INVESTASI LAINNYA | T18: 0399
S22: Code Description
S23: Atas nama pihak lain
S24: Atas nama sendiri

Sheet HARTA BERGERAK
C1: 4. HARTA BERGERAK
C2: Motor/Mobil
C4: 3173015410840005 | D4: SILVIA LISTIANI LIMANTO | K4: CEK TYPE DI STNK (DIBAWAH TULISAN MERK)
J5: =SUM(J8:J55) -> 15575000 | K5: =SUM(K8:K55) -> 4800000 | M5: =SUM(M8:M55) -> 15575000 | N5: =SUM(N8:N55) -> 15575000 | O5: =SUM(O8:O55) -> 15575000 | P5: =SUM(P8:P55) -> 15575000 | Q5: =SUM(Q8:Q55) -> 0
A6: NO | B6: KODE | C6: DESKRIPSI | E6: NOMOR POLISI/REGISTRASI | F6: KEPEMILIKAN | I6: TAHUN PEROLEHAN | J6: HARGA PEROLEHAN | K6: NILAI SAAT INI (2025) | L6: (Harta PPS/ Harta Investasi PPS) | M6: NILAI TAHUN SEBELUMNYA
C7: TIPE | D7: MEREK/MODEL | F7: MILIK SENDIRI/ ORANG LAIN | G7: NIK / NPWP | H7: NAMA | M7: 2024 | N7: 2023 | O7: 2022 | P7: 2021 | Q7: 2020 | S7: - | T7: - | U7: -
A8: 1 | B8: =VLOOKUP($C8,$T:$U,2,0) -> 0402 | C8: SEPEDA MOTOR | D8: YAHAMA XEON | E8: B 3539 BCQ | F8: TAXPAYER | G8: 3173015410840005 | H8: SILVIA LISTIANI LIMANTO | I8: 2010 | J8: 15575000 | K8: 4800000 | L8: - | M8: 15575000 | N8: 15575000 | O8: 15575000 | P8: 15575000 | Q8: 0 | S8: 0401 | T8: SEPEDA | U8: 0401
A9: =A8+1 -> 2 | S9: 0402 | T9: SEPEDA MOTOR | U9: 0402
S10: 0403 | T10: MOBIL PENUMPANG | U10: 0403
S11: 0404 | T11: BUS | U11: 0404
S12: 0405 | T12: KENDARAAN ANGKUTAN JALAN | U12: 0405
S13: 0406 | T13: KENDARAAN TUJUAN KHUSUS | U13: 0406
S14: 0407 | T14: KERETA | U14: 0407
S15: 0408 | T15: PESAWAT TERBANG | U15: 0408
S16: 0409 | T16: KAPAL | U16: 0409
S17: 0410 | T17: MESIN | U17: 0410
S18: 0411 | T18: GEROBAK | U18: 0411
S19: 0412 | T19: KAPAL PESIAR | U19: 0412
S20: 0499 | T20: HARTA BERGERAK LAINNYA | U20: 0499
S22: OWNERSHIP MOVEABLE ASSET
S23: Code | T23: Code Description
S24: OTHER | T24: Atas nama pihak lain
S25: TAXPAYER | T25: Atas nama sendiri

Sheet HARTA TIDAK BERGERAK
C1: 5. HARTA TIDAK BERGERAK
C2: Tanah Kosong/Tanah Bangunan untuk Tempat Tinggal/Apartemen/Vessel/Tanah atau Lahan untuk Usaha/Tanah Bangunan untuk Usaha atau yang disewakan
C4: 3173015410840005 | D4: SILVIA LISTIANI LIMANTO | F4: CEK PBB 2025 | L4: CEK NJOP PBB 2025
K5: =SUM(K8:K55) -> 78500000 | L5: =SUM(L8:L55) -> 342530000 | N5: =SUM(N8:N55) -> 78500000 | O5: =SUM(O8:O55) -> 78500000 | P5: =SUM(P8:P55) -> 78500000 | Q5: =SUM(Q8:Q55) -> 78500000 | R5: =SUM(R8:R55) -> 0
A6: NO | B6: KODE | C6: DESKRIPSI | D6: LOKASI HARTA | E6: DETAIL | F6: UKURAN PROPERTI | H6: SUMBER KEPEMILIKAN | I6: NOMOR SERTIFIKAT | J6: TAHUN PEROLEHAN | K6: HARGA PEROLEHAN | L6: NILAI SAAT INI (2025) | M6: (Harta PPS/ Harta Investasi PPS) | N6: NILAI TAHUN SEBELUMNYA
F7: TANAH | G7: BANGUNAN | N7: 2024 | O7: 2023 | P7: 2022 | Q7: 2021 | R7: 2020 | T7: - | U7: - | V7: -
A8: 1 | B8: =VLOOKUP(C8,$U:$V,2,0) -> 0502 | C8: TANAH DAN/ATAU BANGUNAN UNTUK TEMPAT TINGGAL | D8: INDONESIA | E8: RUMAH, GG EMPANG NO 30, RT 014 RW 12, KAPUK, CENGKARENG, JAKARTA BARAT | F8: 86 M2 | G8: 66 M2 | H8: Grant | I8: 317402000400300330 | J8: 2012 | K8: 78500000 | L8: 342530000 | M8: - | N8: 78500000 | O8: 78500000 | P8: 78500000 | Q8: 78500000 | R8: 0 | T8: 0501 | U8: TANAH KOSONG | V8: 0501 | W8: NOP: 31.71.070.001.013-0028.0
A9: =A8+1 -> 2 | T9: 0502 | U9: TANAH DAN/ATAU BANGUNAN UNTUK TEMPAT TINGGAL | V9: 0502 | W9: NOP: 31.71.070.001.017-0141.0
A10: 3 | T10: 0503 | U10: APARTEMEN | V10: 0503
T11: 0504 | U11: VESSEL | V11: 0504
T12: 0505 | U12: TANAH ATAU LAHAN UNTUK USAHA (LAHAN PERTANIAN, PERKEBUNAN, DSB) | V12: 0505
T13: 0506 | U13: TANAH DAN/ATAU BANGUNAN UNTUK USAHA (TOKO, PABRIK, DSB) | V13: 0506
T14: 0507 | U14: TANAH DAN/ATAU BANGUNAN YANG DISEWAKAN | V14: 0507
T15: 0509 | U15: HARTA TIDAK BERGERAK LAINNYA | V15: 0509
T18: Source of Income
T19: Code Name | U19: Code Description
T20: Debt | U20: Utang
T21: Gift | U21: Hadiah
T22: Grant | U22: Hibah
T23: Inheritance | U23: Warisan
T24: Other sources | U24: Sumber lainnya
T25: Own Income | U25: Hasil Sendiri

Sheet HARTA LAINNYA
C1: 6. HARTA LAINNYA
C2: Emas Batangan/Emas Perhiasan/Permata/Barang Barang Seni dan Antik/Peralatan Elektronik/Perabot Rumah Tangga/Harta Tidak Berwujud Lainnya
C4: 3173015410840005 | D4: SILVIA LISTIANI LIMANTO
G5: =SUM(G8:G55) -> 27500000 | H5: =SUM(H8:H55) -> 27500000 | J5: =SUM(J8:J55) -> 0 | K5: =SUM(K8:K55) -> 0 | L5: =SUM(L8:L55) -> 0 | M5: =SUM(M8:M55) -> 0 | N5: =SUM(N8:N55) -> 0
A6: NO | B6: KODE | C6: DESKRIPSI | D6: TAHUN PEROLEHAN | E6: BUKTI KEPEMILIKAN/NOMOR AKUN | F6: INFORMASI TAMBAHAN | G6: HARGA PEROLEHAN | H6: NILAI SAAT INI (2025) | I6: (Harta PPS/ Harta Investasi PPS) | J6: NILAI TAHUN SEBELUMNYA
J7: 2024 | K7: 2023 | L7: 2022 | M7: 2021 | N7: 2020 | P7: - | Q7: - | R7: -
A8: 1 | B8: =VLOOKUP(C8,$Q:$R,2,0) -> 0712 | C8: PERSEDIAAN USAHA | D8: 2025 | E8: - | F8: - | G8: =H8 -> 27500000 | H8: 27500000 | I8: - | J8: 0 | K8: 0 | L8: 0 | M8: 0 | N8: 0 | P8: 0601 | Q8: PATEN | R8: 0601
A9: =A8+1 -> 2 | P9: 0602 | Q9: ROYALTI | R9: 0602
A10: =A9+1 -> 3 | P10: 0603 | Q10: MEREK DAGANG | R10: 0603
A11: =A10+1 -> 4 | P11: 0699 | Q11: HARTA TIDAK BERWUJUD LAINNYA | R11: 0699
A12: =A11+1 -> 5 | P12: 0701 | Q12: EMAS BATANGAN | R12: 0701
A13: =A12+1 -> 6 | P13: 0702 | Q13: EMAS PERHIASAN | R13: 0702
A14: =A13+1 -> 7 | P14: 0703 | Q14: BATANGAN NON EMAS | R14: 0703
A15: =A14+1 -> 8 | P15: 0704 | Q15: PERHIASAN NON EMAS | R15: 0704
A16: =A15+1 -> 9 | P16: 0705 | Q16: PERMATA | R16: 0705
A17: =A16+1 -> 10 | P17: 0706 | Q17: BARANG-BARANG SENI DAN ANTIK | R17: 0706
A18: =A17+1 -> 11 | P18: 0707 | Q18: PERALATAN OLAH RAGA KHUSUS | R18: 0707
A19: =A18+1 -> 12 | P19: 0708 | Q19: PERALATAN ELEKTRONIK | R19: 0708
A20: =A19+1 -> 13 | P20: 0709 | Q20: PERABOT RUMAH TANGGA | R20: 0709
... A24: =A23+1 -> 17 | P24: 0799 | Q24: HARTA LAINNYA | R24: 0799
A25: =A24+1 -> 18
A26: =A25+1 -> 19
A27: =A26+1 -> 20
A28: =A27+1 -> 21
A29: =A28+1 -> 22
A30: =A29+1 -> 23
A31: =A30+1 -> 24
A32: =A31+1 -> 25
A33: =A32+1 -> 26
A34: =A33+1 -> 27
A35: =A34+1 -> 28
A36: =A35+1 -> 29
... A55: =A54+1 -> 48

Sheet HUTANG
C1: B. UTANG PAJAK PADA AKHIR TAHUN
C4: 3173015410840005 | D4: SILVIA LISTIANI LIMANTO
H5: =SUM(H8:H55) -> 0 | J5: =SUM(J8:J55) -> 0 | K5: =SUM(K8:K55) -> 0 | L5: =SUM(L8:L55) -> 0 | M5: =SUM(M8:M55) -> 0 | N5: =SUM(N8:N55) -> 0
A6: NO | B6: KODE | C6: DESKRIPSI | D6: PEMBERI PINJAMAN | F6: NEGARA KREDITUR | G6: TAHUN PEMINJAMAN | H6: NILAI PIUTANG SAAT INI (2025) | I6: KETERANGAN | J6: NILAI TAHUN SEBELUMNYA
D7: NIK / NPWP | E7: NAMA | J7: 2024 | K7: 2023 | L7: 2022 | M7: 2021 | N7: 2020 | P7: - | Q7: - | R7: -
A8: 1 | B8: =VLOOKUP(C8,$Q:$R,2,0) -> - | C8: - | P8: 101 | Q8: UTANG BANK/LEMBAGA KEUANGAN BUKAN BANK | R8: 101
A9: =A8+1 -> 2 | P9: 102 | Q9: KARTU KREDIT | R9: 102
A10: =A9+1 -> 3 | P10: 103 | Q10: UTANG AFILIASI | R10: 103
A11: =A10+1 -> 4 | P11: 109 | Q11: UTANG LAINNYA | R11: 109
A12: =A11+1 -> 5
A13: =A12+1 -> 6
A14: =A13+1 -> 7
A15: =A14+1 -> 8
A16: =A15+1 -> 9
A17: =A16+1 -> 10
A18: =A17+1 -> 11
A19: =A18+1 -> 12
A20: =A19+1 -> 13
A21: =A20+1 -> 14
A22: =A21+1 -> 15
A23: =A22+1 -> 16
... A55: =A54+1 -> 48

Sheet RECAP
B1: POINT | C1: 2024 | D1: 2025 DJP | E1: 2025 CTX | J1: Penjualan Logam Mulia
B2: KAS | C2: =KAS!K$5 -> 616081918 | D2: =KAS!I$5 -> 704944815 | E2: =KAS!I$5 -> 704944815 | N2: Total Dibeli | O2: Hitungan/Gram
B3: PIUTANG | C3: =PIUTANG!K$5 -> 0 | D3: =PIUTANG!I$5 -> 0 | E3: =PIUTANG!I$5 -> 0 | J3: 2015 | K3: 479950 | L3: =K3*O3 -> 23997500 | N3: =K3*O3 -> 23997500 | O3: 50
B4: INVEST | C4: =INVEST!L$5 -> 118039674 | D4: =INVEST!H$5 -> 145350343 | E4: =INVEST!J$5 -> 145350343 | J4: 2025 | K4: =K3+1100000 -> 1579950 | L4: =K4*O3 -> 78997500
B5: HARTA BERGERAK | C5: ='HARTA BERGERAK'!M$5 -> 15575000 | D5: ='HARTA BERGERAK'!J$5 -> 15575000 | E5: ='HARTA BERGERAK'!K$5 -> 4800000 | J5: Naik Keuntungan | K5: =K4-K3 -> 1100000 | L5: =L4-L3 -> 55000000
B6: HARTA TIDAK BERGERAK | C6: ='HARTA TIDAK BERGERAK'!N$5 -> 78500000 | D6: ='HARTA TIDAK BERGERAK'!K$5 -> 78500000 | E6: ='HARTA TIDAK BERGERAK'!L$5 -> 342530000 | J6: Sisa | K6: 479950000 | L6: =K6-L3 -> 455952500
B7: HARTA LAINNYA | C7: ='HARTA LAINNYA'!J$5 -> 0 | D7: ='HARTA LAINNYA'!G$5 -> 27500000 | E7: ='HARTA LAINNYA'!H$5 -> 27500000
B8: TOTAL HARTA | C8: =SUM(C2:C7) -> 828196592 | D8: =SUM(D2:D7) -> 971870158 | E8: =SUM(E2:E7) -> 1225125158
B9: TOTAL HUTANG | C9: =HUTANG!J$5 -> 0 | D9: =HUTANG!H5 -> 0 | E9: =D9 -> 0
B10: NET | C10: =C8-C9 -> 828196592 | D10: =D8-D9 -> 971870158 | E10: =E8-E9 -> 1225125158
C11: =C8+C20 -> 976832692 | D11: =C11-D8 -> 4962534
B14: Omset UMKM | C14: =OMSET!B23 -> 927580000
A15: =MID(B15,19,3) -> 30% | B15: Est. Margin UMKM (30%) | C15: =A15*C14 -> 278274000
B16: Bayar Pajak | C16: =OMSET!F23 -> 2137900
B17: Bunga | C17: =BUNGA!J14 -> 0
B18: Pengeluaran 11 Juta Per Bulan | C18: =MID(B18,13,2)*12*1000000 -> 132000000 | D18: =(C15-C18)/C14 -> 0.15769422
B20: Perhitungan | C20: =C15-C16+C17-C18+C23 -> 148636100
B21: Hasil Investasi | C21: 0 | D21: <= JANGAN LUPA DIINPUT, CEK DATA BUNGA
B22: Penghasilan Lain | C22: 0 | D22: <= JANGAN LUPA DIINPUT
B23: Sewa | C23: =5000000*90% -> 4500000
B24: Keuntungan LM

Sheet OMSET
A1: Daftar Jumlah Peredaran Bruto dan Pembayaran PPh Final berdasarkan PP 55 Tahun 2022
A2: Per Masa Pajak Serta Dari Masing-Masing Tempat Usaha Tahun 2024
A5: NAMA | B5: =KAS!D4 -> SILVIA LISTIANI LIMANTO
A6: NPWP | B6: =KAS!C4 -> 3173015410840005
A7: ALAMAT | B7: JL.KAPUK RAYA NO.2 RT 003/012 KEL.KAPUK KEC.CENGKARENG JAK-BAR
A10: Masa | B10: Peredaran Bruto | C10: PPh Final | D10: Total Peredaran Bruto | E10: Perhitungan Pengurangan | F10: PPh Final Harus Dibayar | H10: Omset 2024 | I10: PPh Final 0,5% Dibayar
A11: Januari | B11: 85780000 | C11: =B11/200 -> 428900 | D11: =+B11 -> 85780000 | E11: =+D11-500000000 -> -414220000 | F11: =IF(D11<500000000,"FREE",IF(#REF!="FREE",E11/200,C11)) -> FREE | H11: 54060000 | I11: 0
A12: Februari | B12: 77220000 | C12: =B12/200 -> 386100 | D12: =+D11+B12 -> 163000000 | E12: =+D12-500000000 -> -337000000 | F12: =IF(D12<500000000,"FREE",IF(F11="FREE",E12/200,C12)) -> FREE | H12: 59780000 | I12: 0
A13: Maret | B13: 82320000 | C13: =B13/200 -> 411600 | D13: =+D12+B13 -> 245320000 | E13: =+D13-500000000 -> -254680000 | F13: =IF(D13<500000000,"FREE",IF(F12="FREE",E13/200,C13)) -> FREE | H13: 79100000 | I13: 0
A14: April | B14: 74080000 | C14: =B14/200 -> 370400 | D14: =+D13+B14 -> 319400000 | E14: =+D14-500000000 -> -180600000 | F14: =IF(D14<500000000,"FREE",IF(F13="FREE",E14/200,C14)) -> FREE | H14: 65220000 | I14: 0
A15: Mei | B15: 81560000 | C15: =B15/200 -> 407800 | D15: =+D14+B15 -> 400960000 | E15: =+D15-500000000 -> -99040000 | F15: =IF(D15<500000000,"FREE",IF(F14="FREE",E15/200,C15)) -> FREE | H15: 71940000 | I15: 0
A16: Juni | B16: 97440000 | C16: =B16/200 -> 487200 | D16: =+D15+B16 -> 498400000 | E16: =+D16-500000000 -> -1600000 | F16: =IF(D16<500000000,"FREE",IF(F15="FREE",E16/200,C16)) -> FREE | H16: 68280000 | I16: 0
A17: Juli | B17: 92700000 | C17: =B17/200 -> 463500 | D17: =+D16+B17 -> 591100000 | E17: =+D17-500000000 -> 91100000 | F17: =IF(D17<500000000,"FREE",IF(F16="FREE",E17/200,C17)) -> 455500 | H17: 75360000 | I17: 0
A18: Agustus | B18: 43460000 | C18: =B18/200 -> 217300 | D18: =+D17+B18 -> 634560000 | E18: =+D18-500000000 -> 134560000 | F18: =IF(D18<500000000,"FREE",IF(F17="FREE",E18/200,C18)) -> 217300 | H18: 70720000 | I18: 222300
A19: September | B19: 67940000 | C19: =B19/200 -> 339700 | D19: =+D18+B19 -> 702500000 | E19: =+D19-500000000 -> 202500000 | F19: =IF(D19<500000000,"FREE",IF(F18="FREE",E19/200,C19)) -> 339700 | H19: 76440000 | I19: 382200
A20: Oktober | B20: 61420000 | C20: =B20/200 -> 307100 | D20: =+D19+B20 -> 763920000 | E20: =+D20-500000000 -> 263920000 | F20: =IF(D20<500000000,"FREE",IF(F19="FREE",E20/200,C20)) -> 307100 | H20: 74900000 | I20: 374500
A21: November | B21: 83780000 | C21: =B21/200 -> 418900 | D21: =+D20+B21 -> 847700000 | E21: =+D21-500000000 -> 347700000 | F21: =IF(D21<500000000,"FREE",IF(F20="FREE",E21/200,C21)) -> 418900 | H21: 82420000 | I21: 412100
A22: Desember | B22: 79880000 | C22: =B22/200 -> 399400 | D22: =+D21+B22 -> 927580000 | E22: =+D22-500000000 -> 427580000 | F22: =IF(D22<500000000,"FREE",IF(F21="FREE",E22/200,C22)) -> 399400 | H22: 78540000 | I22: 392700
A23: Total | B23: =+SUM(B11:B22) -> 927580000 | C23: =+SUM(C11:C22) -> 4637900 | D23: =IF(D22=B23,"-","ERROR") -> - | E23: - | F23: =SUM(F11:F22) -> 2137900 | H23: =SUM(H11:H22) -> 856760000 | I23: =SUM(I11:I22) -> 1783800

Sheet BUNGA
B2: DESKRIPSI | C2: NOMOR AKUN | D2: ATAS NAMA | E2: NAMA BANK/INSTITUSI | F2: NILAI SAAT INI (2025) | G2: BUNGA 1 BULAN | H2: BUNGA 1 TAHUN | I2: PAJAK | J2: BUNGA-PAJAK
J4: =H4-I4 -> 0
J5: =H5-I5 -> 0
J6: =H6-I6 -> 0
J7: =H7-I7 -> 0
J14: =SUM(J4:J13) -> 0
B17: Cash Dividend | E17: 1000
B18: Akun | C18: Payment Date | D18: Symbol | E18: Quantity (shares) | F18: Dividend | G18: Amount | H18: Tax | I18: Tax (Rp) | J18: Net Dividend (Rp)
H19: 0.00% | I19: 0
J24: =SUM(J19:J23) -> 0
