Workbook

Sheet data cadangan
A1: 56 | B1: #N/A | C1: DEPOSITO | D1: 6290003714 | E1: HARYANTO DJOJOE BUNTORO | F1: BANK UOB INDONESIA | G1: Indonesia | H1: IDR | I1: 2023 | J1: 0 | L1: 1 | N1: 522954440 | O1: 423213224 | P1: 0 | Q1: 0 | R1: 0
A2: 57 | B2: #N/A | C2: DEPOSITO | D2: 6290003714 | E2: HARYANTO DJOJOE BUNTORO | F2: BANK UOB INDONESIA | G2: Indonesia | H2: IDR | I2: 2023 | J2: 0 | L2: 1 | N2: 519743666 | O2: 575000000 | P2: 0 | Q2: 0 | R2: 0
A3: 58 | B3: #N/A | C3: DEPOSITO | D3: 6290003714 | E3: HARYANTO DJOJOE BUNTORO | F3: BANK UOB INDONESIA | G3: Indonesia | H3: IDR | I3: 2023 | J3: 0 | L3: 1 | N3: 514030503 | O3: 848290027 | P3: 0 | Q3: 0 | R3: 0
A4: 59 | B4: #N/A | C4: DEPOSITO | D4: 629000374 | E4: HARYANTO DJOJOE BUNTORO | F4: BANK UOB INDONESIA | G4: Indonesia | H4: IDR | I4: 2024 | J4: 0 | L4: 1 | N4: 514030503 | O4: 0 | P4: 0 | Q4: 0 | R4: 0
A5: 60 | B5: #N/A | C5: DEPOSITO | D5: 629000374 | E5: HARYANTO DJOJOE BUNTORO | F5: BANK UOB INDONESIA | G5: Indonesia | H5: IDR | I5: 2024 | J5: 0 | L5: 1 | N5: 505847387 | O5: 0 | P5: 0 | Q5: 0 | R5: 0
A6: 61 | B6: #N/A | C6: DEPOSITO | D6: 629000374 | E6: HARYANTO DJOJOE BUNTORO | F6: BANK UOB INDONESIA | G6: Indonesia | H6: IDR | I6: 2024 | J6: 0 | L6: 1 | N6: 1011694773 | O6: 0 | P6: 0 | Q6: 0 | R6: 0

Sheet 1770 (2)
B2: *) Pengisian kolom-kolom yang berisi nilai rupiah harus tanpa nilai desimal (contoh penulisan lihat petunjuk pengisian halaman 3)
AF3: RUPIAH *)
B5: A. PENGHASILAN NETO | G5: 1. | I5: PENGHASILAN NETO DALAM NEGERI DARI USAHA DAN/ATAU PEKERJAAN BEBAS [Diisi dari Formulir 1770 - I Halaman 1 Jumlah Bagian A atau Formulir 1770 - I Halaman 2 Jumlah Bagian B Kolom 5] | AF5: 1 | AG5: =BUPOT!F10 -> 52925263
G7: 2. | I7: PENGHASILAN NETO DALAM NEGERI SEHUBUNGAN DENGAN PEKERJAAN [Diisi dari Formulir 1770 - I Halaman 2 Jumlah Bagian C Kolom 5] | AF7: 2 | AG7: =BUPOT!F15 -> 111150000
G9: 3. | I9: PENGHASILAN NETO DALAM NEGERI LAINNYA [Diisi dari Formulir 1770 - I Halaman 2 Jumlah Bagian D Kolom 3] | AF9: 3 | AG9: 0
A10: 4
G11: 4. | I11: PENGHASILAN NETO LUAR NEGERI [Apabila memiliki penghasilan dari luar negeri agar diisi dari Lampiran Tersendiri, lihat petunjuk pengisian] | AF11: 4 | AG11: 0
G13: 5. | I13: JUMLAH PENGHASILAN NETO (1 + 2 + 3 + 4) | AF13: 5 | AG13: =AG5+AG7+AG9+AG11 -> 164075263
U14: …………………………………………………………………………………………………………………………..
G15: 6. | I15: ZAKAT / SUMBANGAN KEAGAMAAN YANG BERSIFAT WAJIB | AF15: 6 | AG15: 0
G17: 7. | I17: JUMLAH PENGHASILAN NETO SETELAH PENGURANGAN ZAKAT /SUMBANGAN KEAGAMAAN YANG | AF17: 7 | AG17: =AG13-AG15 -> 164075263
I18: SIFATNYA WAJIB ( 5- 6)
B21: B. PENGHASILAN KENA PAJAK | G21: 8. | I21: KOMPENSASI KERUGIAN | AF21: 8 | AG21: 0
G23: 9. | I23: JUMLAH PENGHASILAN NETO SETELAH KOMPENSASI KERUGIAN (7 - 8) | AF23: 9 | AG23: =AG17-AG21 -> 164075263
G25: 10. | I25: PENGHASILAN TIDAK KENA PAJAK | Q25: TK / | T25: K / | U25: 1 | W25: K / I / | AF25: 10 | AG25: 63000000
G27: 11. | I27: PENGHASILAN KENA PAJAK (9 -10) | AF27: 11 | AG27: =AG23-AG25 -> 101075263
B30: C. PPh TERUTANG | G30: 12. | I30: PPh TERUTANG (TARIF PASAL 17 UU PPh X ANGKA 11) [Bagi Wajib Pajak dengan status PH / MT diisi dari Lampiran Perhitungan PPh Terutang sebagaimana dimaksud dalam bagian G: Lampiran huruf i] | AF30: 12 | AG30: {=MAX(({5;15;25;30}%*(ROUNDDOWN($AG$27,-3))-{0;6000000;31000000;56000000}))} -> 9161250
G32: 13. | I32: PENGEMBALIAN/PENGURANGAN PPh PASAL 24 YANG TELAH DIKREDITKAN | AF32: 13 | AG32: 0
G35: 14. | I35: JUMLAH PPh TERUTANG ( 12 + 13) | AF35: 14 | AG35: =AG30+AG32 -> 9161250
B38: D. KREDIT PAJAK | G38: 15. | I38: PPh YANG DIPOTONG / DIPUNGUT OLEH PIHAK LAIN, PPh YANG DIBAYAR / DIPOTONG DI LUAR NEGERI DAN PPh DITANGGUNG PEMERINTAH [Diisi dari formulir 1770 -II Jumlah Bagian A Kolom 7] | AF38: 15 | AG38: =BUPOT!G16 -> 7687526
G40: 16. | I40: X | K40: a. | L40: PPh YANG HARUS DIBAYAR SENDIRI | U40: (14-15) | AF40: 16 | AG40: =AG35-AG38 -> 1473724
K42: b. | L42: PPh YANG LEBIH DIPOTONG/DIPUNGUT
G44: 17. | I44: PPh YANG DIBAYAR SENDIRI | P44: a. | Q44: PPh PASAL 25 BULANAN | AF44: 17a | AG44: 0
P46: b. | Q46: STP PPh PASAL 25 (HANYA POKOK PAJAK) | AF46: 17b
G49: 18. | I49: JUMLAH KREDIT PAJAK (17a+17b) | AF49: 18 | AG49: =AG44+AG46 -> 0
B51: E. PPh KURANG/ LEBIH BAYAR
G52: 19. | I52: a. | J52: X | K52: PPh YANG KURANG DIBAYAR (PPh PASAL 29) | U52: (16-18) | W52: TGL LUNAS | Y52: 3 | Z52: 1 | AA52: 0 | AB52: 3 | AC52: 2 | AD52: 6 | AF52: 19 | AG52: =AG40-AG49 -> 1473724
J53: \
I54: b. | K54: PPh YANG LEBIH DIBAYAR (PPh PASAL 28 A) | Y54: tgl | AA54: bln | AC54: thn
G56: 20. | I56: PERMOHONAN : PPh Lebih Bayar pada 19.b mohon | V56: a. | X56: DIRESTITUSIKAN | AC56: c. | AF56: DIKEMBALIKAN DENGAN SKPPKP PASAL 17C (WP dengan Kriteria Tertentu)
V59: b. | X59: DIPERHITUNGKAN DENGAN | AC59: d. | AF59: DIKEMBALIKAN DENGAN SKPPKP PASAL 17D (WP yang Memenuhi Persyaratan Tertentu)
X60: UTANG PAJAK
B62: F. ANGSURAN PPh PASAL 25 TAHUN PAJAK BERIKUTNYA
G63: 21. | I63: ANGSURAN PPh PASAL 25 TAHUN PAJAK BERIKUTNYA DIHITUNG SEBESAR | AF63: 21
I65: DIHITUNG BERDASARKAN :
I67: a. | K67: 1/12 X JUMLAH PADA ANGKA 16 | Z67: c. | AB67: PERHITUNGAN DALAM LAMPIRAN TERSENDIRI
I69: b. | K69: PERHITUNGAN WAJIB PAJAK ORANG PRIBADI PENGUSAHA TERTENTU

Sheet Sheet2
A3: Sum of SALDO SAAT INI (2025) | B3: Column Labels
B4: DEPOSITO | C4: DEPOSITO Total | D4: SETARA KAS LAINNYA | E4: SETARA KAS LAINNYA Total | F4: TABUNGAN | H4: TABUNGAN Total | I4: UANG TUNAI | J4: UANG TUNAI Total | K4: (blank) | L4: (blank) Total | M4: Grand Total
A5: Row Labels | B5: IDR | D5: IDR | F5: IDR | G5: USD | I5: IDR | K5: (blank)
A6: - | D6: 1050000000 | E6: 1050000000 | I6: 375000000 | J6: 375000000 | M6: 1425000000
A7: BANK CENTRAL ASIA | F7: 1849939508 | G7: 448197555 | H7: 2298137063 | M7: 2298137063
A8: BANK CIMB NIAGA | F8: 703053335 | H8: 703053335 | M8: 703053335
A9: BANK DBS INDONESIA | F9: 86378401 | G9: 10603064 | H9: 96981465 | M9: 96981465
A10: BANK HSBC INDONESIA | F10: 150158590 | G10: 76972876 | H10: 227131466 | M10: 227131466
A11: BANK MANDIRI | F11: 69884414 | H11: 69884414 | M11: 69884414
A12: BANK MAYBANK INDONESIA | F12: 289120215 | H12: 289120215 | M12: 289120215
A13: BANK MEGA | B13: 2076324773 | C13: 2076324773 | F13: 2365099919 | G13: 38368999 | H13: 2403468918 | M13: 4479793691
A14: BANK OCBC NISP | F14: 282662537 | H14: 282662537 | M14: 282662537
A15: BANK PAN INDONESIA | F15: 239621964 | G15: 280679210 | H15: 520301174 | M15: 520301174
A16: BANK UOB INDONESIA | F16: 700631451 | G16: 429021444 | H16: 1129652895 | M16: 1129652895
A17: STANDARD CHARTERED BANK | F17: 471794907 | G17: 7314772 | H17: 479109679 | M17: 479109679
A18: VALAS US DOLAR | I18: 590000000 | J18: 590000000 | M18: 590000000
A19: (blank)
A20: Grand Total | B20: 2076324773 | C20: 2076324773 | D20: 1050000000 | E20: 1050000000 | F20: 7208345241 | G20: 1291157920 | H20: 8499503161 | I20: 965000000 | J20: 965000000 | M20: 12590827934

Sheet KAS
C1: 1. KAS dan SETARA KAS | J1: AMBIL HANYA SAMPAI KOLOM J SAJA
C2: Uang Tunai/Tabungan/Giro/Deposito
C4: 3173042409640005 | D4: SINDJAJA JONANY | J4: =ROUNDDOWN(K4*L4,0) -> 0
B5: =VLOOKUP(C5,U:V,2,) -> #N/A | J5: =SUM(J8:J292) -> 11475827934 | L5: =VLOOKUP(H5,BUNGA!$C$97:$D$97,2,0) -> #N/A | N5: =SUM(N8:N292) -> 14579487152 | O5: =SUM(O8:O292) -> 2418393230 | P5: =SUM(P8:P292) -> 1972372290 | Q5: =SUM(Q8:Q292) -> 9193154695 | R5: =SUM(R8:R292) -> 13233927881
A6: NO | B6: KODE | C6: DESKRIPSI | D6: NOMOR AKUN | E6: ATAS NAMA | F6: NAMA BANK/INSTITUSI | G6: LOKASI HARTA | H6: KURS | I6: TAHUN PEROLEHAN | J6: SALDO SAAT INI (2025) | K6: SALDO DALAM BENTUK AWAL (2025) | L6: KURS | M6: (HARTA PPS/ HARTA INVESTASI PPS) | N6: NILAI TAHUN SEBELUMNYA
N7: 2024 | O7: 2023 | P7: 2022 | Q7: 2021 | R7: 2020 | T7: - | U7: - | V7: -
A8: 1 | B8: =VLOOKUP(C8,U:V,2,) -> 0102 | C8: TABUNGAN | D8: 30610081702 | E8: SINDJAJA JONANY | F8: STANDARD CHARTERED BANK | G8: Indonesia | H8: IDR | I8: 2025 | J8: =ROUNDDOWN(K8*L8,0) -> 395266344 | K8: 395266344 | L8: =VLOOKUP(H8,BUNGA!$C$97:$D$98,2,0) -> 1 | M8: SJ | N8: 121941664 | O8: 481437 | P8: 12040351 | Q8: 0 | R8: 0 | T8: 0101 | U8: UANG TUNAI | V8: 0101
A9: =A8+1 -> 2 | B9: =VLOOKUP(C9,U:V,2,) -> 0102 | C9: TABUNGAN | D9: 30607686992 | E9: SINDJAJA JONANY | F9: STANDARD CHARTERED BANK | G9: Indonesia | H9: IDR | I9: 2025 | J9: =ROUNDDOWN(K9*L9,0) -> 76528563 | K9: 76528563 | L9: =VLOOKUP(H9,BUNGA!$C$97:$D$98,2,0) -> 1 | M9: SJ | N9: 92634637 | O9: 974723 | P9: 12561571 | Q9: 0 | R9: 0 | T9: 0102 | U9: TABUNGAN | V9: 0102
A10: =A9+1 -> 3 | B10: =VLOOKUP(C10,U:V,2,) -> 0102 | C10: TABUNGAN | D10: 306812112560 | E10: ROSALINA CHANDRA | F10: STANDARD CHARTERED BANK | G10: Indonesia | H10: USD | I10: 2025 | J10: =ROUNDDOWN(K10*L10,0) -> 7314772 | K10: 436 | L10: =VLOOKUP(H10,BUNGA!$C$97:$D$98,2,0) -> 16777 | M10: RC | N10: 56429070 | O10: 5004180 | P10: 0 | Q10: 0 | R10: 0 | T10: 0103 | U10: GIRO | V10: 0103
A11: =A10+1 -> 4 | B11: =VLOOKUP(C11,U:V,2,) -> 0102 | C11: TABUNGAN | D11: 010210020072665 | E11: SINDJAJA JONANY | F11: BANK MEGA | G11: Indonesia | H11: IDR | I11: 2025 | J11: =ROUNDDOWN(K11*L11,0) -> 129148067 | K11: 129148067 | L11: =VLOOKUP(H11,BUNGA!$C$97:$D$98,2,0) -> 1 | M11: SJ | N11: 84858925 | O11: 22058140 | P11: 71975639 | Q11: 181789681 | R11: 188528896 | T11: 0104 | U11: DEPOSITO | V11: 0104
A12: =A11+1 -> 5 | B12: =VLOOKUP(C12,U:V,2,) -> 0102 | C12: TABUNGAN | D12: 010210020079229 | E12: ROSALINA CHANDRA | F12: BANK MEGA | G12: Indonesia | H12: IDR | I12: 2025 | J12: =ROUNDDOWN(K12*L12,0) -> 121185719 | K12: 121185719 | L12: =VLOOKUP(H12,BUNGA!$C$97:$D$98,2,0) -> 1 | M12: RC | N12: 3776657 | O12: 134948 | P12: 21856286 | Q12: 28421979 | R12: 0 | T12: 0105 | U12: UANG ELEKTRONIK | V12: 0105
A13: =A12+1 -> 6 | B13: =VLOOKUP(C13,U:V,2,) -> 0102 | C13: TABUNGAN | D13: 010212029003270 | E13: SINDJAJA JONANY | F13: BANK MEGA | G13: Indonesia | H13: USD | I13: 2025 | J13: =ROUNDDOWN(K13*L13,0) -> 38368999 | K13: 2287 | L13: =VLOOKUP(H13,BUNGA!$C$97:$D$98,2,0) -> 16777 | M13: SJ | N13: 27281025 | O13: 26179275 | P13: 52731000 | Q13: 62064548 | R13: 120454248 | T13: 0106 | U13: CEK | V13: 0106
A14: =A13+1 -> 7 | B14: =VLOOKUP(C14,U:V,2,) -> 0102 | C14: TABUNGAN | D14: 010210036010740 | E14: SINDJAJA JONANY | F14: BANK MEGA | G14: Indonesia | H14: IDR | I14: 2025 | J14: =ROUNDDOWN(K14*L14,0) -> 2114766133 | K14: 2114766133 | L14: =VLOOKUP(H14,BUNGA!$C$97:$D$98,2,0) -> 1 | M14: SJ | N14: 0 | O14: 0 | P14: 0 | Q14: 0 | R14: 0 | T14: 0107 | U14: WESSEL | V14: 0107
A15: =A14+1 -> 8 | B15: =VLOOKUP(C15,U:V,2,) -> 0104 | C15: DEPOSITO | D15: 0102100200360006730 | E15: ROSALINA CHANDRA | F15: BANK MEGA | G15: Indonesia | H15: IDR | I15: 2025 | J15: =ROUNDDOWN(K15*L15,0) -> 1576324773 | K15: 1576324773 | L15: =VLOOKUP(H15,BUNGA!$C$97:$D$98,2,0) -> 1 | M15: RC | N15: 0 | O15: 0 | P15: 0 | Q15: 0 | R15: 0 | T15: 0108 | U15: KERTAS KOMERSIAL | V15: 0108
A16: =A15+1 -> 9 | B16: =VLOOKUP(C16,U:V,2,) -> 0104 | C16: DEPOSITO | D16: 010210036007967 | E16: ROSALINA CHANDRA | F16: BANK MEGA | G16: Indonesia | H16: IDR | I16: 2025 | J16: =ROUNDDOWN(K16*L16,0) -> 500000000 | K16: 500000000 | L16: =VLOOKUP(H16,BUNGA!$C$97:$D$98,2,0) -> 1 | M16: RC | N16: 0 | O16: 0 | P16: 0 | Q16: 0 | R16: 0 | T16: 0109 | U16: SETARA KAS | V16: 0109
A17: =A16+1 -> 10 | B17: =VLOOKUP(C17,U:V,2,) -> 0102 | C17: TABUNGAN | D17: 5910502699 | E17: SINDJAJA JONANY | F17: BANK CENTRAL ASIA | G17: Indonesia | H17: IDR | I17: 2025 | J17: =ROUNDDOWN(K17*L17,0) -> 623690638 | K17: 623690638 | L17: =VLOOKUP(H17,BUNGA!$C$97:$D$98,2,0) -> 1 | M17: SJ | N17: 395980369 | O17: 58844070 | P17: 84236265 | Q17: 73625229 | R17: 42296991 | T17: 0101 | U17: UANG TUNAI/BANK NOTE/KOIN | V17: 0101
A18: =A17+1 -> 11 | B18: =VLOOKUP(C18,U:V,2,) -> 0102 | C18: TABUNGAN | D18: 8740285689 | E18: SINDJAJA JONANY | F18: BANK CENTRAL ASIA | G18: Indonesia | H18: IDR | I18: 2025 | J18: =ROUNDDOWN(K18*L18,0) -> 298564906 | K18: 298564906 | L18: =VLOOKUP(H18,BUNGA!$C$97:$D$98,2,0) -> 1 | M18: SJ | N18: 431828577 | O18: 117767462 | P18: 127485150 | Q18: 24878970 | R18: 354451437 | T18: 0109 | U18: SETARA KAS LAINNYA | V18: 0109
A19: =A18+1 -> 12 | B19: =VLOOKUP(C19,U:V,2,) -> 0102 | C19: TABUNGAN | D19: 8740530683 | E19: SINDJAJA JONANY | F19: BANK CENTRAL ASIA | G19: Indonesia | H19: USD | I19: 2025 | J19: =ROUNDDOWN(K19*L19,0) -> 279018287 | K19: 16631 | L19: =VLOOKUP(H19,BUNGA!$C$97:$D$98,2,0) -> 16777 | M19: SJ | N19: 11604495 | O19: 0 | P19: 0 | Q19: 0 | R19: 0
A20: =A19+1 -> 13 | B20: =VLOOKUP(C20,U:V,2,) -> 0102 | C20: TABUNGAN | D20: 8740185668 | E20: ROSALINA CHANDRA | F20: BANK CENTRAL ASIA | G20: Indonesia | H20: IDR | I20: 2025 | J20: =ROUNDDOWN(K20*L20,0) -> 158216505 | K20: 158216505 | L20: =VLOOKUP(H20,BUNGA!$C$97:$D$98,2,0) -> 1 | M20: RC | N20: 508484117 | O20: 267041301 | P20: 36497755 | Q20: 173685791 | R20: 233518380
A21: =A20+1 -> 14 | B21: =VLOOKUP(C21,U:V,2,) -> 0102 | C21: TABUNGAN | D21: 8740351711 | E21: ROSALINA CHANDRA | F21: BANK CENTRAL ASIA | G21: Indonesia | H21: IDR | I21: 2025 | J21: =ROUNDDOWN(K21*L21,0) -> 769467459 | K21: 769467459 | L21: =VLOOKUP(H21,BUNGA!$C$97:$D$98,2,0) -> 1 | M21: RC | N21: 956098574 | O21: 48237792 | P21: 91749141 | Q21: 0 | R21: 0
A22: =A21+1 -> 15 | B22: =VLOOKUP(C22,U:V,2,) -> 0102 | C22: TABUNGAN | D22: 5910700598 | E22: ROSALINA CHANDRA | F22: BANK CENTRAL ASIA | G22: Indonesia | H22: USD | I22: 2025 | J22: =ROUNDDOWN(K22*L22,0) -> 169179268 | K22: 10084 | L22: =VLOOKUP(H22,BUNGA!$C$97:$D$98,2,0) -> 16777 | M22: RC | N22: 312452235 | O22: 125397955 | P22: 45539000 | Q22: 51687104 | R22: 100563504
A23: =A22+1 -> 16 | B23: =VLOOKUP(C23,U:V,2,) -> 0102 | C23: TABUNGAN | D23: 0702102299 | E23: SINDJAJA JONANY | F23: BANK PAN INDONESIA | G23: Indonesia | H23: IDR | I23: 2025 | J23: =ROUNDDOWN(K23*L23,0) -> 117449710 | K23: 117449710 | L23: =VLOOKUP(H23,BUNGA!$C$97:$D$98,2,0) -> 1 | M23: SJ | N23: 34224869 | O23: 7418816 | P23: 16621048 | Q23: 3082257 | R23: 0
A24: =A23+1 -> 17 | B24: =VLOOKUP(C24,U:V,2,) -> 0102 | C24: TABUNGAN | D24: 0704400221 | E24: SINDJAJA JONANY | F24: BANK PAN INDONESIA | G24: Indonesia | H24: USD | I24: 2025 | J24: =ROUNDDOWN(K24*L24,0) -> 280679210 | K24: 16730 | L24: =VLOOKUP(H24,BUNGA!$C$97:$D$98,2,0) -> 16777 | M24: SJ | N24: 100143090 | O24: 25623255 | P24: 26799500 | Q24: 503163094 | R24: 432460060
A25: =A24+1 -> 18 | B25: =VLOOKUP(C25,U:V,2,) -> 0102 | C25: TABUNGAN | D25: 0702013221 | E25: ROSALINA CHANDRA | F25: BANK PAN INDONESIA | G25: Indonesia | H25: IDR | I25: 2025 | J25: =ROUNDDOWN(K25*L25,0) -> 122172254 | K25: 122172254 | L25: =VLOOKUP(H25,BUNGA!$C$97:$D$98,2,0) -> 1 | M25: RC | N25: 45154004 | O25: 9618501 | P25: 18320983 | Q25: 6245711 | R25: 0
A26: =A25+1 -> 19 | B26: =VLOOKUP(C26,U:V,2,) -> 0102 | C26: TABUNGAN | D26: 702531238600 | E26: SINDJAJA JONANY | F26: BANK CIMB NIAGA | G26: Indonesia | H26: IDR | I26: 2025 | J26: =ROUNDDOWN(K26*L26,0) -> 629283803 | K26: 629283803 | L26: =VLOOKUP(H26,BUNGA!$C$97:$D$98,2,0) -> 1 | M26: SJ | N26: 174126066 | O26: 5647422 | P26: 5635819 | Q26: 1842731 | R26: 0
A27: =A26+1 -> 20 | B27: =VLOOKUP(C27,U:V,2,) -> 0102 | C27: TABUNGAN | D27: 700884870600 | E27: SINDJAJA JONANY | F27: BANK CIMB NIAGA | G27: Indonesia | H27: IDR | I27: 2025 | J27: =ROUNDDOWN(K27*L27,0) -> 53819698 | K27: 53819698 | L27: =VLOOKUP(H27,BUNGA!$C$97:$D$98,2,0) -> 1 | M27: SJ | N27: 149441785 | O27: 0 | P27: 0 | Q27: 0 | R27: 0
A28: =A27+1 -> 21 | B28: =VLOOKUP(C28,U:V,2,) -> 0102 | C28: TABUNGAN | D28: 701031763000 | E28: ROSALINA CHANDRA | F28: BANK CIMB NIAGA | G28: Indonesia | H28: IDR | I28: 2025 | J28: =ROUNDDOWN(K28*L28,0) -> 19949834 | K28: 19949834 | L28: =VLOOKUP(H28,BUNGA!$C$97:$D$98,2,0) -> 1 | M28: RC | N28: 4999856 | O28: 8874867 | P28: 97603432 | Q28: 14822490 | R28: 0
A29: =A28+1 -> 22 | B29: =VLOOKUP(C29,U:V,2,) -> 0102 | C29: TABUNGAN | D29: 27810193121 | E29: ROSALINA CHANDRA | F29: BANK OCBC NISP | G29: Indonesia | H29: IDR | I29: 2025 | J29: =ROUNDDOWN(K29*L29,0) -> 282662537 | K29: 282662537 | L29: =VLOOKUP(H29,BUNGA!$C$97:$D$98,2,0) -> 1 | M29: RC | N29: 225113597 | O29: 0 | P29: 0 | Q29: 0 | R29: 0
A30: =A29+1 -> 23 | B30: =VLOOKUP(C30,U:V,2,) -> 0102 | C30: TABUNGAN | D30: 1680011168885 | E30: ROSALINA CHANDRA | F30: BANK MANDIRI | G30: Indonesia | H30: IDR | I30: 2025 | J30: =ROUNDDOWN(K30*L30,0) -> 69884414 | K30: 69884414 | L30: =VLOOKUP(H30,BUNGA!$C$97:$D$98,2,0) -> 1 | M30: RC | N30: 131871464 | O30: 45421741 | P30: 88218785 | Q30: 103010634 | R30: 162755079
... A44: =A43+1 -> 37 | B44: =VLOOKUP(C44,U:V,2,) -> 0102 | C44: TABUNGAN | D44: 6419000709 | E44: SINDJAJA JONANY | F44: BANK UOB INDONESIA | G44: Indonesia | H44: USD | I44: 2025 | J44: =ROUNDDOWN(K44*L44,0) -> 15401286 | K44: 918 | L44: =VLOOKUP(H44,BUNGA!$C$97:$D$98,2,0) -> 16777 | M44: SJ | N44: 53660730 | O44: 0 | P44: 0 | Q44: 0 | R44: 0
A45: =A44+1 -> 38 | B45: =VLOOKUP(C45,U:V,2,) -> 0102 | C45: TABUNGAN | D45: 6309003261 | E45: SINDJAJA JONANY | F45: BANK UOB INDONESIA | G45: Indonesia | H45: IDR | I45: 2025 | J45: =ROUNDDOWN(K45*L45,0) -> 563263882 | K45: 563263882 | L45: =VLOOKUP(H45,BUNGA!$C$97:$D$98,2,0) -> 1 | M45: SJ | N45: 0 | O45: 0 | P45: 0 | Q45: 0 | R45: 0
A46: =A45+1 -> 39 | B46: =VLOOKUP(C46,U:V,2,) -> 0102 | C46: TABUNGAN | D46: 6419000059 | E46: SINDJAJA JONANY | F46: BANK UOB INDONESIA | G46: Indonesia | H46: USD | I46: 2025 | J46: =ROUNDDOWN(K46*L46,0) -> 73382598 | K46: 4374 | L46: =VLOOKUP(H46,BUNGA!$C$97:$D$98,2,0) -> 16777 | M46: SJ | N46: 0 | O46: 0 | P46: 0 | Q46: 0 | R46: 0
A47: =A46+1 -> 40 | B47: =VLOOKUP(C47,U:V,2,) -> 0102 | C47: TABUNGAN | D47: 6309003831 | E47: ROSALINA CHANDRA | F47: BANK UOB INDONESIA | G47: Indonesia | H47: IDR | I47: 2025 | J47: =ROUNDDOWN(K47*L47,0) -> 88959334 | K47: 88959334 | L47: =VLOOKUP(H47,BUNGA!$C$97:$D$98,2,0) -> 1 | M47: RC | N47: 0 | O47: 0 | P47: 0 | Q47: 0 | R47: 0
A48: =A47+1 -> 41 | B48: =VLOOKUP(C48,U:V,2,) -> 0102 | C48: TABUNGAN | D48: 6309001742 | E48: ROSALINA CHANDRA | F48: BANK UOB INDONESIA | G48: Indonesia | H48: USD | I48: 2025 | J48: =ROUNDDOWN(K48*L48,0) -> 83029373 | K48: 4949 | L48: =VLOOKUP(H48,BUNGA!$C$97:$D$98,2,0) -> 16777 | M48: RC | N48: 0 | O48: 0 | P48: 0 | Q48: 0 | R48: 0
A49: =A48+1 -> 42 | B49: =VLOOKUP(C49,U:V,2,) -> 0109 | C49: SETARA KAS LAINNYA | D49: - | E49: SINDJAJA JONANY | F49: - | G49: Indonesia | H49: IDR | I49: 2025 | J49: =ROUNDDOWN(K49*L49,0) -> 600000000 | K49: 600000000 | L49: =VLOOKUP(H49,BUNGA!$C$97:$D$98,2,0) -> 1 | M49: SJ | N49: 1050000000 | O49: 500000000 | P49: 0 | Q49: 0 | R49: 0
A50: =A49+1 -> 43 | B50: =VLOOKUP(C50,U:V,2,) -> 0101 | C50: UANG TUNAI | D50: - | E50: SINDJAJA JONANY | F50: VALAS US DOLAR (sebagian diinvestasikan) | G50: Indonesia | H50: IDR | I50: 2021 | J50: =ROUNDDOWN(K50*L50,0) -> 50000000 | K50: 50000000 | L50: =VLOOKUP(H50,BUNGA!$C$97:$D$98,2,0) -> 1 | M50: SJ | N50: 590000000 | O50: 590000000 | P50: 590000000 | Q50: 590000000 | R50: 590000000
A51: =A50+1 -> 44 | B51: =VLOOKUP(C51,U:V,2,) -> 0101 | C51: UANG TUNAI | D51: - | E51: SINDJAJA JONANY | F51: - | G51: Indonesia | H51: IDR | I51: 2025 | J51: =ROUNDDOWN(K51*L51,0) -> 250000000 | K51: 250000000 | L51: =VLOOKUP(H51,BUNGA!$C$97:$D$98,2,0) -> 1 | M51: SJ | N51: 375000000 | O51: 152575000 | P51: 102575000 | Q51: 325750000 | R51: 100000000
B71: =VLOOKUP(C71,U:V,2,) -> 0104 | C71: DEPOSITO | D71: Deposito 30152041 | F71: BANK MEGA | G71: Indonesia | H71: IDR | I71: 2020 | J71: CLOSE | K71: CLOSE | L71: CLOSE | M71: - | N71: 0 | O71: 0 | P71: 0 | Q71: 670000000 | R71: 670000000
B72: =VLOOKUP(C72,U:V,2,) -> 0104 | C72: DEPOSITO | D72: Deposito 6788 | F72: BANK MEGA | G72: Indonesia | H72: IDR | I72: 2024 | J72: CLOSE | K72: CLOSE | L72: CLOSE | M72: - | N72: 2000000000 | O72: 0 | P72: 0 | Q72: 0 | R72: 0
B73: =VLOOKUP(C73,U:V,2,) -> 0104 | C73: DEPOSITO | D73: Deposito 7374 | F73: BANK MEGA | G73: Indonesia | H73: IDR | I73: 2024 | J73: CLOSE | K73: CLOSE | L73: CLOSE | M73: - | N73: 2000000000 | O73: 0 | P73: 0 | Q73: 0 | R73: 0
B74: =VLOOKUP(C74,U:V,2,) -> 0104 | C74: DEPOSITO | D74: Deposito 6720 | F74: BANK MEGA | G74: Indonesia | H74: IDR | I74: 2024 | J74: CLOSE | K74: CLOSE | L74: CLOSE | M74: - | N74: 659399671 | O74: 0 | P74: 0 | Q74: 0 | R74: 0
B75: =VLOOKUP(C75,U:V,2,) -> 0102 | C75: TABUNGAN | D75: Tabungan 7263 | F75: STANDARD CHARTERED | G75: Indonesia | H75: IDR | I75: 2021 | J75: CLOSE | K75: CLOSE | L75: CLOSE | M75: - | N75: 0 | O75: 0 | P75: 0 | Q75: 540490682 | R75: 0
B76: =VLOOKUP(C76,U:V,2,) -> 0102 | C76: TABUNGAN | D76: Tabungan USD $5.367 | F76: STANDARD CHARTERED | G76: Indonesia | H76: IDR | I76: 2021 | J76: CLOSE | K76: CLOSE | L76: CLOSE | M76: - | N76: 0 | O76: 0 | P76: 0 | Q76: 76715898 | R76: 0
B77: =VLOOKUP(C77,U:V,2,) -> 0102 | C77: TABUNGAN | D77: Tabungan USD $7.841 | F77: STANDARD CHARTERED | G77: Indonesia | H77: IDR | I77: 2021 | J77: CLOSE | K77: CLOSE | L77: CLOSE | M77: - | N77: 0 | O77: 0 | P77: 0 | Q77: 112079254 | R77: 0
B78: =VLOOKUP(C78,U:V,2,) -> 0102 | C78: TABUNGAN | D78: Tabungan USD 1,686 | F78: STANDARD CHARTERED | G78: Indonesia | H78: IDR | I78: 2020 | J78: CLOSE | K78: CLOSE | L78: CLOSE | M78: - | N78: 0 | O78: 0 | P78: 0 | Q78: 0 | R78: 23988408
B79: =VLOOKUP(C79,U:V,2,) -> 0102 | C79: TABUNGAN | D79: Tabungan 8170 | F79: STANDARD CHARTERED | G79: Indonesia | H79: IDR | I79: 2021 | J79: CLOSE | K79: CLOSE | L79: CLOSE | M79: - | N79: 0 | O79: 0 | P79: 0 | Q79: 168535506 | R79: 0
B80: =VLOOKUP(C80,U:V,2,) -> 0104 | C80: DEPOSITO | D80: Deposito 122 | F80: BANK PAN INDONESIA | G80: Indonesia | H80: IDR | I80: 2025 | J80: CLOSE | K80: CLOSE | L80: CLOSE | M80: - | N80: 0 | O80: 0 | P80: 0 | Q80: 2125043811 | R80: 2065000000
B81: =VLOOKUP(C81,U:V,2,) -> 0104 | C81: DEPOSITO | D81: Deposito 122 | F81: BANK PAN INDONESIA | G81: Indonesia | H81: IDR | I81: 2025 | J81: CLOSE | K81: CLOSE | L81: CLOSE | M81: - | N81: 0 | O81: 0 | P81: 0 | Q81: 0 | R81: 1032000000
B82: =VLOOKUP(C82,U:V,2,) -> 0102 | C82: TABUNGAN | D82: Tabungan Investor 7060 | F82: BANK CIMB NIAGA | G82: Indonesia | H82: IDR | I82: 2021 | J82: CLOSE | K82: CLOSE | L82: CLOSE | N82: 0 | O82: 234686962 | P82: 159550956 | Q82: 753550358 | R82: 0
B83: =VLOOKUP(C83,U:V,2,) -> 0102 | C83: TABUNGAN | D83: Tabungan Investor 0126 | F83: BANK CIMB NIAGA | G83: Indonesia | H83: IDR | I83: 2020 | J83: CLOSE | K83: CLOSE | L83: CLOSE | N83: 0 | O83: 0 | P83: 0 | Q83: 0 | R83: 729975790
B84: =VLOOKUP(C84,U:V,2,) -> 0102 | C84: TABUNGAN | D84: Tabungan Goal Savers | F84: BANK CIMB NIAGA | G84: Indonesia | H84: IDR | I84: 2024 | J84: CLOSE | K84: CLOSE | L84: CLOSE | N84: 3505000000 | O84: 0 | P84: 0 | Q84: 0 | R84: 0
B85: =VLOOKUP(C85,U:V,2,) -> 0102 | C85: TABUNGAN | D85: HSBC - Tabungan USD 4,636 | F85: BANK HSBC INDONESIA | G85: Indonesia | H85: IDR | I85: 2021 | J85: CLOSE | K85: CLOSE | L85: CLOSE | M85: - | N85: 0 | O85: 0 | P85: 7626000 | Q85: 66266984 | R85: 119159500
B86: =VLOOKUP(C86,U:V,2,) -> 0102 | C86: TABUNGAN | D86: HSBC - Tabungan 7580 | F86: BANK HSBC INDONESIA | G86: Indonesia | H86: IDR | I86: 2022 | J86: CLOSE | K86: CLOSE | L86: CLOSE | M86: - | N86: 0 | O86: 0 | P86: 3677349 | Q86: 0 | R86: 0
B87: =VLOOKUP(C87,U:V,2,) -> 0102 | C87: TABUNGAN | D87: HSBC - Tabungan 0519 | F87: BANK HSBC INDONESIA | G87: Indonesia | H87: IDR | I87: 2022 | J87: CLOSE | K87: CLOSE | L87: CLOSE | M87: - | N87: 0 | O87: 0 | P87: 7962819 | Q87: 0 | R87: 0
B88: =VLOOKUP(C88,U:V,2,) -> 0102 | C88: TABUNGAN | D88: DBS - Tabungan 5150 | E88: DBS - Tabungan 5150 | F88: BANK DBS INDONESIA | G88: Indonesia | H88: IDR | I88: 2025 | J88: CLOSE | K88: CLOSE | L88: CLOSE | N88: 0 | O88: 0 | P88: 14521438 | Q88: 583464594 | R88: 0
B89: =VLOOKUP(C89,U:V,2,) -> 0102 | C89: TABUNGAN | D89: DBS - Tabungan 7554 | E89: DBS - Tabungan 7554 | F89: BANK DBS INDONESIA | G89: Indonesia | H89: IDR | I89: 2025 | J89: CLOSE | K89: CLOSE | L89: CLOSE | N89: 54239 | O89: 396407 | P89: 693082 | Q89: 749236815 | R89: 0
B90: =VLOOKUP(C90,U:V,2,) -> 0102 | C90: TABUNGAN | D90: DBS - Tabungan 6009 | E90: DBS - Tabungan 6009 | F90: BANK DBS INDONESIA | G90: Indonesia | H90: IDR | I90: 2025 | J90: CLOSE | K90: CLOSE | L90: CLOSE | N90: 168513 | O90: 141893 | P90: 235823 | Q90: 226103005 | R90: 0
B91: =VLOOKUP(C91,U:V,2,) -> 0102 | C91: TABUNGAN | D91: Citibank - Tabungan 2490 USD $15.764 | F91: BANK UOB INDONESIA | G91: Indonesia | H91: IDR | I91: 2025 | J91: CLOSE | K91: CLOSE | L91: CLOSE | N91: 0 | O91: 0 | P91: 244342000 | Q91: 225330616 | R91: 0
B92: =VLOOKUP(C92,U:V,2,) -> 0102 | C92: TABUNGAN | D92: Citibank - Tabungan 8553 USD $12.788 | F92: BANK UOB INDONESIA | G92: Indonesia | H92: IDR | I92: 2025 | J92: CLOSE | K92: CLOSE | L92: CLOSE | N92: 0 | O92: 0 | P92: 0 | Q92: 182791672 | R92: 0
B93: =VLOOKUP(C93,U:V,2,) -> 0102 | C93: TABUNGAN | D93: Citibank - Tabungan USD 9,489 | F93: BANK UOB INDONESIA | G93: Indonesia | H93: IDR | I93: 2025 | J93: CLOSE | K93: CLOSE | L93: CLOSE | N93: 0 | O93: 0 | P93: 0 | Q93: 0 | R93: 135009492
B94: =VLOOKUP(C94,U:V,2,) -> 0102 | C94: TABUNGAN | D94: Citibank - Tabungan USD 23,125 | F94: BANK UOB INDONESIA | G94: Indonesia | H94: IDR | I94: 2025 | J94: CLOSE | K94: CLOSE | L94: CLOSE | N94: 0 | O94: 0 | P94: 0 | Q94: 0 | R94: 329022500
B95: =VLOOKUP(C95,U:V,2,) -> 0102 | C95: TABUNGAN | D95: UOB - Tabungan 34622 | F95: BANK UOB INDONESIA | G95: Indonesia | H95: IDR | I95: 2025 | J95: CLOSE | K95: CLOSE | L95: CLOSE | N95: 42877269 | O95: 16754952 | P95: 0 | Q95: 0 | R95: 0
B96: =VLOOKUP(C96,U:V,2,) -> 0102 | C96: TABUNGAN | D96: UOB - Tabungan 8931 | F96: BANK UOB INDONESIA | G96: Indonesia | H96: IDR | I96: 2025 | J96: CLOSE | K96: CLOSE | L96: CLOSE | N96: 141422936 | O96: 0 | P96: 0 | Q96: 0 | R96: 0
B97: =VLOOKUP(C97,U:V,2,) -> 0104 | C97: DEPOSITO | D97: Deposito 7506755 | E97: 0013093232091000 | F97: BANK MAYBANK INDONESIA | G97: Indonesia | H97: IDR | I97: 2025 | J97: CLOSE | K97: CLOSE | L97: CLOSE | N97: 0 | O97: 0 | P97: 0 | Q97: 0 | R97: 4120232856
B98: =VLOOKUP(C98,U:V,2,) -> 0104 | C98: DEPOSITO | D98: Deposito 5100889 | E98: 0013093232091000 | F98: BANK MAYBANK INDONESIA | G98: Indonesia | H98: IDR | I98: 2025 | J98: CLOSE | K98: CLOSE | L98: CLOSE | N98: 0 | O98: 0 | P98: 0 | Q98: 0 | R98: 1523991149
B99: =VLOOKUP(C99,U:V,2,) -> 0102 | C99: TABUNGAN | D99: Tabungan 109987 | E99: 0013093232091000 | F99: BANK MAYBANK INDONESIA | G99: Indonesia | H99: IDR | I99: 2025 | J99: CLOSE | K99: CLOSE | L99: CLOSE | N99: 0 | O99: 0 | P99: 0 | Q99: 0 | R99: 80487091
B100: =VLOOKUP(C100,U:V,2,) -> 0102 | C100: TABUNGAN | D100: 1775037702 | E100: 0013093232091000 | F100: BANK MAYBANK INDONESIA | G100: Indonesia | H100: IDR | I100: 2025 | J100: CLOSE | K100: CLOSE | L100: CLOSE | N100: 0 | O100: 0 | P100: 145975 | Q100: 11243683 | R100: 0

Sheet INVEST
C1: 3. INVESTASI/SEKURITAS
C2: Saham yang dibeli untuk dijual kembali/Saham Non Bursa/Saham Bursa/Obligasi Perusahaan/Obligasi Pemerintah IndonesiaSurat Utang Lainnya/Asuransi/Unit Link di Asuransi
C4: 3173042409640005 | D4: SINDJAJA JONANY
J5: =SUM(J8:J215) -> 229892184504 | L5: =SUM(L8:L215) -> 230091984504 | P5: =SUM(P8:P215) -> 157557581602 | Q5: =SUM(Q8:Q215) -> 133490009839 | R5: =SUM(R8:R215) -> 124003495797 | S5: =SUM(S8:S215) -> 127567111319 | T5: =SUM(T8:T215) -> 133023244249
A6: NO | B6: KODE | C6: DESKRIPSI | D6: LOKASI HARTA | E6: BANK / INSTITUSI / PENERIMA INVESTASI | G6: NOMOR AKUN | H6: KODE BANK | I6: KURS | J6: HARGA PEROLEHAN | K6: TAHUN PEROLEHAN | L6: NILAI SAAT INI (2025) | M6: SALDO DALAM BENTUK AWAL (2025) | N6: KURS | O6: (HARTA PPS/ HARTA INVESTASI PPS) | P6: NILAI TAHUN SEBELUMNYA
E7: NPWP | F7: NAMA | P7: 2024 | Q7: 2023 | R7: 2022 | S7: 2021 | T7: 2020 | V7: - | W7: - | X7: -
A8: 1 | B8: =VLOOKUP(C8,$W:$X,2,0) -> 0305 | C8: OBLIGASI PEMERINTAH | D8: Indonesia | E8: 0010003358091000 | F8: STANDARD CHARTERED BANK | G8: OBLIGASI FR 75 | H8: SC | I8: IDR | J8: 1095750000 | K8: 2025 | L8: =ROUNDDOWN(M8*N8,0) -> 1095750000 | M8: 1095750000 | N8: =VLOOKUP(I8,BUNGA!$C$97:$D$98,2,0) -> 1 | O8: SJ | P8: 1000000000 | Q8: 1000000000 | R8: 1000000000 | S8: 1000000000 | T8: 1000000000 | V8: 0301 | W8: SAHAM YANG DIBELI UNTUK DIJUAL KEMBALI | X8: 0301
A9: =A8+1 -> 2 | B9: =VLOOKUP(C9,$W:$X,2,0) -> 0305 | C9: OBLIGASI PEMERINTAH | D9: Indonesia | E9: 0010003358091000 | F9: STANDARD CHARTERED BANK | G9: OBLIGASI FR 80 | H9: SC | I9: IDR | J9: 437628000 | K9: 2025 | L9: =ROUNDDOWN(M9*N9,0) -> 437628000 | M9: 437628000 | N9: =VLOOKUP(I9,BUNGA!$C$97:$D$98,2,0) -> 1 | O9: SJ | P9: 400000000 | Q9: 400000000 | R9: 400000000 | S9: 400000000 | T9: 400000000 | V9: 0302 | W9: SAHAM NON BURSA | X9: 0302
A10: =A9+1 -> 3 | B10: =VLOOKUP(C10,$W:$X,2,0) -> 0305 | C10: OBLIGASI PEMERINTAH | D10: Indonesia | E10: 0010003358091000 | F10: STANDARD CHARTERED BANK | G10: FR064 | H10: SC | I10: IDR | J10: 1850000000 | K10: 2025 | L10: =ROUNDDOWN(M10*N10,0) -> 1850000000 | M10: 1850000000 | N10: =VLOOKUP(I10,BUNGA!$C$97:$D$98,2,0) -> 1 | O10: - | P10: 1850000000 | Q10: 1850000000 | R10: 0 | S10: 0 | T10: 0 | V10: 0303 | W10: SAHAM BURSA | X10: 0303
A11: =A10+1 -> 4 | B11: =VLOOKUP(C11,$W:$X,2,0) -> 0305 | C11: OBLIGASI PEMERINTAH | D11: Indonesia | E11: 0010003358091000 | F11: STANDARD CHARTERED BANK | G11: ST011 | H11: SC | I11: IDR | J11: 2370000000 | K11: 2025 | L11: =ROUNDDOWN(M11*N11,0) -> 2370000000 | M11: 2370000000 | N11: =VLOOKUP(I11,BUNGA!$C$97:$D$98,2,0) -> 1 | O11: RC | P11: 2370000000 | Q11: 2370000000 | R11: 0 | S11: 0 | T11: 0 | V11: 0304 | W11: OBLIGASI PERUSAHAAN | X11: 0304
A12: =A11+1 -> 5 | B12: =VLOOKUP(C12,$W:$X,2,0) -> 0399 | C12: INVESTASI LAINNYA | D12: Indonesia | E12: 0010003358091000 | F12: STANDARD CHARTERED BANK | G12: ASURANSI PRUDENTIAL UMP | H12: SC | I12: IDR | J12: 901170423 | K12: 2025 | L12: =ROUNDDOWN(M12*N12,0) -> 901170423 | M12: 901170423 | N12: =VLOOKUP(I12,BUNGA!$C$97:$D$98,2,0) -> 1 | O12: SJ | P12: 109394265 | Q12: 0 | R12: 0 | S12: 0 | T12: 0 | V12: 0305 | W12: OBLIGASI PEMERINTAH | X12: 0305
A13: =A12+1 -> 6 | B13: =VLOOKUP(C13,$W:$X,2,0) -> 0399 | C13: INVESTASI LAINNYA | D13: Indonesia | E13: 0010003358091000 | F13: STANDARD CHARTERED BANK | G13: ASURANSI PRUDENTIAL VIA | H13: SC | I13: IDR | J13: 1280003810 | K13: 2025 | L13: =ROUNDDOWN(M13*N13,0) -> 1280003810 | M13: 1280003810 | N13: =VLOOKUP(I13,BUNGA!$C$97:$D$98,2,0) -> 1 | O13: SJ | P13: 197646600 | Q13: 0 | R13: 0 | S13: 0 | T13: 0 | V13: 0306 | W13: SURAT UTANG LAINNYA | X13: 0306
A14: =A13+1 -> 7 | B14: =VLOOKUP(C14,$W:$X,2,0) -> 0307 | C14: REKSADANA | D14: Indonesia | E14: 0013781138024000 | F14: Manulife Obligasi Negara Indonesia II | G14: - | H14: SC | I14: IDR | J14: =M14 -> 1406054056 | K14: 2025 | L14: =ROUNDDOWN(M14*N14,0) -> 1406054056 | M14: 1406054056 | N14: =VLOOKUP(I14,BUNGA!$C$97:$D$98,2,0) -> 1 | O14: SJ | P14: 0 | Q14: 0 | R14: 0 | S14: 0 | T14: 0 | V14: 0307 | W14: REKSADANA | X14: 0307
A15: =A14+1 -> 8 | B15: =VLOOKUP(C15,$W:$X,2,0) -> 0307 | C15: REKSADANA | D15: Indonesia | E15: 0013781138024000 | F15: Manulife Obligasi Negara Indonesia II | G15: - | H15: SC | I15: IDR | J15: =M15 -> 398528728 | K15: 2025 | L15: =ROUNDDOWN(M15*N15,0) -> 398528728 | M15: 398528728 | N15: =VLOOKUP(I15,BUNGA!$C$97:$D$98,2,0) -> 1 | O15: SJ | P15: 0 | Q15: 0 | R15: 0 | S15: 0 | T15: 0 | V15: 0309 | W15: PENYERTAAN MODAL DALAM PERUSAHAAN LAIN YANG BUKAN ATAS SAHAM | X15: 0309
A16: =A15+1 -> 9 | B16: =VLOOKUP(C16,$W:$X,2,0) -> 0307 | C16: REKSADANA | D16: Indonesia | E16: 0033154576063000 | F16: Manulife USD Fixed Income Kelas A2 | G16: - | H16: SC | I16: USD | J16: =L16 -> 374093546 | K16: 2025 | L16: =ROUNDDOWN(M16*N16,0) -> 374093546 | M16: 22298 | N16: =VLOOKUP(I16,BUNGA!$C$97:$D$98,2,0) -> 16777 | O16: SJ | P16: 0 | Q16: 0 | R16: 0 | S16: 0 | T16: 0 | V16: 0310 | W16: ASURANSI | X16: 0310
A17: =A16+1 -> 10 | B17: =VLOOKUP(C17,$W:$X,2,0) -> 0307 | C17: REKSADANA | D17: Indonesia | E17: 0013781138024000 | F17: Manulife Obligasi Negara Indonesia II | G17: - | H17: SC | I17: IDR | J17: =M17 -> 1287534772 | K17: 2025 | L17: =ROUNDDOWN(M17*N17,0) -> 1287534772 | M17: 1287534772 | N17: =VLOOKUP(I17,BUNGA!$C$97:$D$98,2,0) -> 1 | O17: RC | P17: 0 | Q17: 0 | R17: 0 | S17: 0 | T17: 0 | V17: 0311 | W17: UNIT LINK DI ASURANSI | X17: 0311
A18: =A17+1 -> 11 | B18: =VLOOKUP(C18,$W:$X,2,0) -> 0305 | C18: OBLIGASI PEMERINTAH | D18: Indonesia | E18: 0010003358091000 | F18: STANDARD CHARTERED BANK | G18: USD INDON 34 | H18: SC | I18: USD | J18: =L18 -> 2013240000 | K18: 2025 | L18: =ROUNDDOWN(M18*N18,0) -> 2013240000 | M18: 120000 | N18: =VLOOKUP(I18,BUNGA!$C$97:$D$98,2,0) -> 16777 | O18: SJ | P18: 0 | Q18: 0 | R18: 0 | S18: 0 | T18: 0 | V18: 0399 | W18: INVESTASI LAINNYA | X18: 0399
A19: =A18+1 -> 12 | B19: =VLOOKUP(C19,$W:$X,2,0) -> 0305 | C19: OBLIGASI PEMERINTAH | D19: Indonesia | E19: 0010003358091000 | F19: STANDARD CHARTERED BANK | G19: SR 021 | H19: SC | I19: IDR | J19: 1984096000 | K19: 2025 | L19: =ROUNDDOWN(M19*N19,0) -> 1984096000 | M19: 1984096000 | N19: =VLOOKUP(I19,BUNGA!$C$97:$D$98,2,0) -> 1 | O19: SJ | P19: 0 | Q19: 0 | R19: 0 | S19: 0 | T19: 0
A20: =A19+1 -> 13 | B20: =VLOOKUP(C20,$W:$X,2,0) -> 0305 | C20: OBLIGASI PEMERINTAH | D20: Indonesia | E20: 0010003358091000 | F20: STANDARD CHARTERED BANK | G20: SR022 T5 | H20: SC | I20: IDR | J20: 2000000000 | K20: 2025 | L20: =ROUNDDOWN(M20*N20,0) -> 2000000000 | M20: 2000000000 | N20: =VLOOKUP(I20,BUNGA!$C$97:$D$98,2,0) -> 1 | O20: SJ | P20: 0 | Q20: 0 | R20: 0 | S20: 0 | T20: 0
A21: =A20+1 -> 14 | B21: =VLOOKUP(C21,$W:$X,2,0) -> 0305 | C21: OBLIGASI PEMERINTAH | D21: Indonesia | E21: 0010003358091000 | F21: STANDARD CHARTERED BANK | G21: ST014 T4 | H21: SC | I21: IDR | J21: 1700000000 | K21: 2025 | L21: =ROUNDDOWN(M21*N21,0) -> 1700000000 | M21: 1700000000 | N21: =VLOOKUP(I21,BUNGA!$C$97:$D$98,2,0) -> 1 | O21: SJ | P21: 0 | Q21: 0 | R21: 0 | S21: 0 | T21: 0
A22: =A21+1 -> 15 | B22: =VLOOKUP(C22,$W:$X,2,0) -> 0305 | C22: OBLIGASI PEMERINTAH | D22: Indonesia | E22: 0010003358091000 | F22: STANDARD CHARTERED BANK | G22: FR 58 | H22: SC | I22: IDR | J22: 2500000000 | K22: 2025 | L22: =ROUNDDOWN(M22*N22,0) -> 2500000000 | M22: 2500000000 | N22: =VLOOKUP(I22,BUNGA!$C$97:$D$98,2,0) -> 1 | O22: SJ | P22: 0 | Q22: 0 | R22: 0 | S22: 0 | T22: 0 | V22: OWNERSHIP MOVEABLE ASSET
A23: =A22+1 -> 16 | B23: =VLOOKUP(C23,$W:$X,2,0) -> 0305 | C23: OBLIGASI PEMERINTAH | D23: Indonesia | E23: 0010003358091000 | F23: STANDARD CHARTERED BANK | G23: ORI27 T6 | H23: SC | I23: IDR | J23: 2180000000 | K23: 2025 | L23: =ROUNDDOWN(M23*N23,0) -> 2180000000 | M23: 2180000000 | N23: =VLOOKUP(I23,BUNGA!$C$97:$D$98,2,0) -> 1 | O23: SJ | P23: 0 | Q23: 0 | R23: 0 | S23: 0 | T23: 0 | V23: Code | W23: Code Description
A24: =A23+1 -> 17 | B24: =VLOOKUP(C24,$W:$X,2,0) -> 0305 | C24: OBLIGASI PEMERINTAH | D24: Indonesia | E24: 0010003358091000 | F24: STANDARD CHARTERED BANK | G24: FR 78 | H24: SC | I24: IDR | J24: 1220000000 | K24: 2025 | L24: =ROUNDDOWN(M24*N24,0) -> 1220000000 | M24: 1220000000 | N24: =VLOOKUP(I24,BUNGA!$C$97:$D$98,2,0) -> 1 | O24: SJ | P24: 0 | Q24: 0 | R24: 0 | S24: 0 | T24: 0 | V24: OTHER | W24: Atas nama pihak lain
A25: =A24+1 -> 18 | B25: =VLOOKUP(C25,$W:$X,2,0) -> 0305 | C25: OBLIGASI PEMERINTAH | D25: Indonesia | E25: 0010003358091000 | F25: STANDARD CHARTERED BANK | G25: ST015 T2 | H25: SC | I25: IDR | J25: 3000000000 | K25: 2025 | L25: =ROUNDDOWN(M25*N25,0) -> 3000000000 | M25: 3000000000 | N25: =VLOOKUP(I25,BUNGA!$C$97:$D$98,2,0) -> 1 | O25: SJ | P25: 0 | Q25: 0 | R25: 0 | S25: 0 | T25: 0 | V25: TAXPAYER | W25: Atas nama sendiri
A26: =A25+1 -> 19 | B26: =VLOOKUP(C26,$W:$X,2,0) -> 0305 | C26: OBLIGASI PEMERINTAH | D26: Indonesia | E26: 0010003358091000 | F26: STANDARD CHARTERED BANK | G26: SBR014 T2 | H26: SC | I26: IDR | J26: 620000000 | K26: 2025 | L26: =ROUNDDOWN(M26*N26,0) -> 620000000 | M26: 620000000 | N26: =VLOOKUP(I26,BUNGA!$C$97:$D$98,2,0) -> 1 | O26: RC | P26: 0 | Q26: 0 | R26: 0 | S26: 0 | T26: 0
A27: =A26+1 -> 20 | B27: =VLOOKUP(C27,$W:$X,2,0) -> 0305 | C27: OBLIGASI PEMERINTAH | D27: Indonesia | E27: 0010003358091000 | F27: STANDARD CHARTERED BANK | G27: SR021 T5 | H27: SC | I27: IDR | J27: 2150000000 | K27: 2025 | L27: =ROUNDDOWN(M27*N27,0) -> 2150000000 | M27: 2150000000 | N27: =VLOOKUP(I27,BUNGA!$C$97:$D$98,2,0) -> 1 | O27: RC | P27: 0 | Q27: 0 | R27: 0 | S27: 0 | T27: 0
A28: =A27+1 -> 21 | B28: =VLOOKUP(C28,$W:$X,2,0) -> 0305 | C28: OBLIGASI PEMERINTAH | D28: Indonesia | E28: 0011080454091000 | F28: BANK MEGA | G28: USD INDOIS 27 | H28: MG | I28: USD | J28: 3355400000 | K28: 2025 | L28: =ROUNDDOWN(M28*N28,0) -> 3355400000 | M28: 200000 | N28: =VLOOKUP(I28,BUNGA!$C$97:$D$98,2,0) -> 16777 | O28: SJ | P28: 0 | Q28: 0 | R28: 0 | S28: 0 | T28: 0
A29: =A28+1 -> 22 | B29: =VLOOKUP(C29,$W:$X,2,0) -> 0305 | C29: OBLIGASI PEMERINTAH | D29: Indonesia | E29: 0013084496091000 | F29: BANK CENTRAL ASIA | G29: OBLIGASI FR68 | H29: BCA | I29: IDR | J29: =L29 -> 1200000000 | K29: 2025 | L29: =ROUNDDOWN(M29*N29,0) -> 1200000000 | M29: 1200000000 | N29: =VLOOKUP(I29,BUNGA!$C$97:$D$98,2,0) -> 1 | O29: SJ | P29: 2000000000 | Q29: 2000000000 | R29: 2000000000 | S29: 2000000000 | T29: 2000000000
A30: =A29+1 -> 23 | B30: =VLOOKUP(C30,$W:$X,2,0) -> 0305 | C30: OBLIGASI PEMERINTAH | D30: Indonesia | E30: 0013084496091000 | F30: BANK CENTRAL ASIA | G30: OBLIGASI FR74 | H30: BCA | I30: IDR | J30: =L30 -> 1600000000 | K30: 2025 | L30: =ROUNDDOWN(M30*N30,0) -> 1600000000 | M30: 1600000000 | N30: =VLOOKUP(I30,BUNGA!$C$97:$D$98,2,0) -> 1 | O30: SJ | P30: 2000000000 | Q30: 2000000000 | R30: 2000000000 | S30: 2000000000 | T30: 2000000000
A31: =A30+1 -> 24 | B31: =VLOOKUP(C31,$W:$X,2,0) -> 0305 | C31: OBLIGASI PEMERINTAH | D31: Indonesia | E31: 0013084496091000 | F31: BANK CENTRAL ASIA | G31: OBLIGASI FR79 | H31: BCA | I31: IDR | J31: =L31 -> 4500000000 | K31: 2025 | L31: =ROUNDDOWN(M31*N31,0) -> 4500000000 | M31: 4500000000 | N31: =VLOOKUP(I31,BUNGA!$C$97:$D$98,2,0) -> 1 | O31: SJ | P31: 4500000000 | Q31: 4500000000 | R31: 4500000000 | S31: 4500000000 | T31: 4500000000
A32: =A31+1 -> 25 | B32: =VLOOKUP(C32,$W:$X,2,0) -> 0305 | C32: OBLIGASI PEMERINTAH | D32: Indonesia | E32: 0013084496091000 | F32: BANK CENTRAL ASIA | G32: OBLIGASI FR065 | H32: BCA | I32: IDR | J32: =L32 -> 700000000 | K32: 2025 | L32: =ROUNDDOWN(M32*N32,0) -> 700000000 | M32: 700000000 | N32: =VLOOKUP(I32,BUNGA!$C$97:$D$98,2,0) -> 1 | O32: RC | P32: 2000000000 | Q32: 2000000000 | R32: 2000000000 | S32: 2000000000 | T32: 0
A33: =A32+1 -> 26 | B33: =VLOOKUP(C33,$W:$X,2,0) -> 0305 | C33: OBLIGASI PEMERINTAH | D33: Indonesia | E33: 0013084496091000 | F33: BANK CENTRAL ASIA | G33: OBLIGASI FR068 | H33: BCA | I33: IDR | J33: =L33 -> 1200000000 | K33: 2025 | L33: =ROUNDDOWN(M33*N33,0) -> 1200000000 | M33: 1200000000 | N33: =VLOOKUP(I33,BUNGA!$C$97:$D$98,2,0) -> 1 | O33: RC | P33: 2000000000 | Q33: 2000000000 | R33: 2000000000 | S33: 2000000000 | T33: 2000000000
A34: =A33+1 -> 27 | B34: =VLOOKUP(C34,$W:$X,2,0) -> 0305 | C34: OBLIGASI PEMERINTAH | D34: Indonesia | E34: 0013084496091000 | F34: BANK CENTRAL ASIA | G34: OBLIGASI FR072 | H34: BCA | I34: IDR | J34: =L34 -> 1000000000 | K34: 2025 | L34: =ROUNDDOWN(M34*N34,0) -> 1000000000 | M34: 1000000000 | N34: =VLOOKUP(I34,BUNGA!$C$97:$D$98,2,0) -> 1 | O34: RC | P34: 2000000000 | Q34: 2000000000 | R34: 2000000000 | S34: 2000000000 | T34: 2000000000
A35: =A34+1 -> 28 | B35: =VLOOKUP(C35,$W:$X,2,0) -> 0305 | C35: OBLIGASI PEMERINTAH | D35: Indonesia | E35: 0013084496091000 | F35: BANK CENTRAL ASIA | G35: OBLIGASI FR074 | H35: BCA | I35: IDR | J35: =L35 -> 1200000000 | K35: 2025 | L35: =ROUNDDOWN(M35*N35,0) -> 1200000000 | M35: 1200000000 | N35: =VLOOKUP(I35,BUNGA!$C$97:$D$98,2,0) -> 1 | O35: RC | P35: 2000000000 | Q35: 2000000000 | R35: 2000000000 | S35: 2000000000 | T35: 2000000000
A36: =A35+1 -> 29 | B36: =VLOOKUP(C36,$W:$X,2,0) -> 0305 | C36: OBLIGASI PEMERINTAH | D36: Indonesia | E36: 0013084496091000 | F36: BANK CENTRAL ASIA | G36: OBLIGASI FR079 | H36: BCA | I36: IDR | J36: =L36 -> 450000000 | K36: 2025 | L36: =ROUNDDOWN(M36*N36,0) -> 450000000 | M36: 450000000 | N36: =VLOOKUP(I36,BUNGA!$C$97:$D$98,2,0) -> 1 | O36: RC | P36: 700000000 | Q36: 700000000 | R36: 700000000 | S36: 700000000 | T36: 700000000
A37: =A36+1 -> 30 | B37: =VLOOKUP(C37,$W:$X,2,0) -> 0305 | C37: OBLIGASI PEMERINTAH | D37: Indonesia | E37: 0013084496091000 | F37: BANK CENTRAL ASIA | G37: OBLIGASI FR080 | H37: BCA | I37: IDR | J37: =L37 -> 400000000 | K37: 2025 | L37: =ROUNDDOWN(M37*N37,0) -> 400000000 | M37: 400000000 | N37: =VLOOKUP(I37,BUNGA!$C$97:$D$98,2,0) -> 1 | O37: RC | P37: 1000000000 | Q37: 1000000000 | R37: 1000000000 | S37: 1000000000 | T37: 1000000000
A38: =A37+1 -> 31 | B38: =VLOOKUP(C38,$W:$X,2,0) -> 0305 | C38: OBLIGASI PEMERINTAH | D38: Indonesia | E38: 0013084496091000 | F38: BANK CENTRAL ASIA | G38: OBLIGASI FR082 | H38: BCA | I38: IDR | J38: =L38 -> 2000000000 | K38: 2025 | L38: =ROUNDDOWN(M38*N38,0) -> 2000000000 | M38: 2000000000 | N38: =VLOOKUP(I38,BUNGA!$C$97:$D$98,2,0) -> 1 | O38: RC | P38: 3800000000 | Q38: 3800000000 | R38: 3800000000 | S38: 3800000000 | T38: 3800000000
A39: =A38+1 -> 32 | B39: =VLOOKUP(C39,$W:$X,2,0) -> 0305 | C39: OBLIGASI PEMERINTAH | D39: Indonesia | E39: 0013084496091000 | F39: BANK CENTRAL ASIA | G39: OBLIGASI FR091 | H39: BCA | I39: IDR | J39: =L39 -> 1000000000 | K39: 2025 | L39: =ROUNDDOWN(M39*N39,0) -> 1000000000 | M39: 1000000000 | N39: =VLOOKUP(I39,BUNGA!$C$97:$D$98,2,0) -> 1 | O39: RC | P39: 2000000000 | Q39: 2000000000 | R39: 2000000000 | S39: 2000000000 | T39: 0
A40: =A39+1 -> 33 | B40: =VLOOKUP(C40,$W:$X,2,0) -> 0305 | C40: OBLIGASI PEMERINTAH | D40: Indonesia | E40: 0013084496091000 | F40: BANK CENTRAL ASIA | G40: OBLIGASI INDOIS 30 USD | H40: BCA | I40: USD | J40: =L40 -> 694383253 | K40: 2025 | L40: =ROUNDDOWN(M40*N40,0) -> 694383253 | M40: 41389 | N40: =VLOOKUP(I40,BUNGA!$C$97:$D$98,2,0) -> 16777 | O40: RC | P40: 667025085 | Q40: 3100000000 | R40: 3100000000 | S40: 2858800000 | T40: 0
... A133: =A132+1 -> 126 | B133: =VLOOKUP(C133,$W:$X,2,0) -> 0307 | C133: REKSADANA | D133: Indonesia | E133: 0013084439091000 | F133: BANK UOB INDONESIA | G133: REKSADANA SCHRODER DANA MANTAP PLUS LL | H133: UOB | I133: IDR | J133: =L133 -> 2017035138 | K133: 2025 | L133: =ROUNDDOWN(M133*N133,0) -> 2017035138 | M133: 2017035138 | N133: =VLOOKUP(I133,BUNGA!$C$97:$D$98,2,0) -> 1 | O133: RC | P133: 0 | Q133: 0 | R133: 0 | S133: 0 | T133: 0
A134: =A133+1 -> 127 | B134: =VLOOKUP(C134,$W:$X,2,0) -> 0307 | C134: REKSADANA | D134: Indonesia | E134: - | F134: CITIBANK SINGAPORE | G134: CITIBANK SINGAPORE - INVESMENT FUND 841879901 | H134: CBS | I134: USD | J134: 2316750000 | K134: 2025 | L134: =ROUNDDOWN(M134*N134,0) -> 2516550000 | M134: 150000 | N134: =VLOOKUP(I134,BUNGA!$C$97:$D$98,2,0) -> 16777 | O134: RC | P134: 2316750000 | Q134: 2316750000 | R134: 2325000000 | S134: 2144100000 | T134: 2134200000
A135: =A134+1 -> 128 | B135: =VLOOKUP(C135,$W:$X,2,0) -> 0302 | C135: SAHAM NON BURSA | D135: Indonesia | E135: - | F135: PT BORNEO JAYA SEJATI | G135: PT BORNEO JAYA SEJATI | H135: - | I135: IDR | J135: =L135 -> 40000000 | K135: 2016 | L135: =ROUNDDOWN(M135*N135,0) -> 40000000 | M135: 40000000 | N135: =VLOOKUP(I135,BUNGA!$C$97:$D$98,2,0) -> 1 | O135: SJ | P135: 40000000 | Q135: 40000000 | R135: 40000000 | S135: 40000000 | T135: 40000000
A136: =A135+1 -> 129 | B136: =VLOOKUP(C136,$W:$X,2,0) -> 0302 | C136: SAHAM NON BURSA | D136: Indonesia | E136: 0027473420047000 | F136: PT.MG DUA JAYA | G136: AHU-0034772.AH.01.02. TAHUN 2025 | H136: - | I136: IDR | J136: =L136 -> 1680000000 | K136: 2014 | L136: =ROUNDDOWN(M136*N136,0) -> 1680000000 | M136: 1680000000 | N136: =VLOOKUP(I136,BUNGA!$C$97:$D$98,2,0) -> 1 | O136: SJ | P136: 1680000000 | Q136: 1680000000 | R136: 1680000000 | S136: 1680000000 | T136: 1680000000
A137: =A136+1 -> 130 | B137: =VLOOKUP(C137,$W:$X,2,0) -> 0302 | C137: SAHAM NON BURSA | D137: Indonesia | E137: - | F137: PT.KARUNIA RAHMAT INTI SEJAHTERA | G137: PT.KARUNIA RAHMAT INTI SEJAHTERA | H137: - | I137: IDR | J137: =L137 -> 250000000 | K137: 2014 | L137: =ROUNDDOWN(M137*N137,0) -> 250000000 | M137: 250000000 | N137: =VLOOKUP(I137,BUNGA!$C$97:$D$98,2,0) -> 1 | O137: SJ | P137: 250000000 | Q137: 250000000 | R137: 250000000 | S137: 250000000 | T137: 250000000
A138: =A137+1 -> 131 | B138: =VLOOKUP(C138,$W:$X,2,0) -> 0302 | C138: SAHAM NON BURSA | D138: Indonesia | E138: - | F138: PT.HEPI JAYA BERSAMA | G138: PT.HEPI JAYA BERSAMA | H138: - | I138: IDR | J138: =L138 -> 236000000 | K138: 2017 | L138: =ROUNDDOWN(M138*N138,0) -> 236000000 | M138: 236000000 | N138: =VLOOKUP(I138,BUNGA!$C$97:$D$98,2,0) -> 1 | O138: SJ | P138: 236000000 | Q138: 236000000 | R138: 236000000 | S138: 236000000 | T138: 236000000
A139: =A138+1 -> 132 | B139: =VLOOKUP(C139,$W:$X,2,0) -> 0305 | C139: OBLIGASI PEMERINTAH | D139: Indonesia | E139: 0013084439091000 | F139: BANK UOB INDONESIA | G139: Citibank - Obligasi FR072 | H139: UOB | I139: IDR | J139: CLOSE | K139: CLOSE | L139: CLOSE | M139: CLOSE | N139: CLOSE | P139: 1500000000 | Q139: 1500000000 | R139: 1500000000 | S139: 1500000000 | T139: 1500000000
A140: =A139+1 -> 133 | B140: =VLOOKUP(C140,$W:$X,2,0) -> 0307 | C140: REKSADANA | D140: Indonesia | E140: 0013084439091000 | F140: BANK UOB INDONESIA | G140: Citibank - Reksadana SDP | H140: UOB | I140: IDR | J140: CLOSE | K140: CLOSE | L140: CLOSE | M140: CLOSE | N140: CLOSE | P140: 549980807 | Q140: 634063462 | R140: 1227536927 | S140: 1301827718 | T140: 1301827718
A141: =A140+1 -> 134 | B141: =VLOOKUP(C141,$W:$X,2,0) -> 0307 | C141: REKSADANA | D141: Indonesia | E141: 0013084439091000 | F141: BANK UOB INDONESIA | G141: Citibank - Reksadana SDPP | H141: UOB | I141: IDR | J141: CLOSE | K141: CLOSE | L141: CLOSE | M141: CLOSE | N141: CLOSE | P141: 1411453237 | Q141: 1411453237 | R141: 1524708144 | S141: 1422201565 | T141: 1422201565
A142: =A141+1 -> 135 | B142: =VLOOKUP(C142,$W:$X,2,0) -> 0307 | C142: REKSADANA | D142: Indonesia | E142: 0013084439091000 | F142: BANK UOB INDONESIA | G142: UOB - Reksadana SDI (Schroder Dana Istimewa) | H142: UOB | I142: USD | J142: CLOSE | K142: CLOSE | L142: CLOSE | M142: CLOSE | N142: CLOSE | P142: 226586251 | Q142: 429765191
A143: =A142+1 -> 136 | B143: =VLOOKUP(C143,$W:$X,2,0) -> 0307 | C143: REKSADANA | D143: Indonesia | E143: 0013084439091000 | F143: BANK UOB INDONESIA | G143: UOB - Reksadana SDA II | H143: UOB | I143: IDR | J143: CLOSE | K143: CLOSE | L143: CLOSE | M143: CLOSE | N143: CLOSE | P143: 417256967 | Q143: 224407877
A144: =A143+1 -> 137 | B144: =VLOOKUP(C144,$W:$X,2,0) -> 0307 | C144: REKSADANA | D144: Indonesia | E144: 0010003358091000 | F144: STANDARD CHARTERED | G144: Reksadana SDMP | H144: SC | I144: IDR | J144: CLOSE | K144: CLOSE | L144: CLOSE | M144: CLOSE | N144: CLOSE | O144: - | P144: 370846598 | Q144: 0 | R144: 0 | S144: 0 | T144: 0
A145: =A144+1 -> 138 | B145: =VLOOKUP(C145,$W:$X,2,0) -> 0307 | C145: REKSADANA | D145: Indonesia | E145: 0010003358091000 | F145: STANDARD CHARTERED | G145: Reksadana MOUA | H145: SC | I145: IDR | J145: CLOSE | K145: CLOSE | L145: CLOSE | M145: CLOSE | N145: CLOSE | O145: - | P145: 87230604 | Q145: 0 | R145: 0 | S145: 0 | T145: 0
A146: =A145+1 -> 139 | B146: =VLOOKUP(C146,$W:$X,2,0) -> 0307 | C146: REKSADANA | D146: Indonesia | E146: 0010003358091000 | F146: STANDARD CHARTERED | G146: Reksadana SDPP | H146: SC | I146: IDR | J146: CLOSE | K146: CLOSE | L146: CLOSE | M146: CLOSE | N146: CLOSE | O146: - | P146: 0 | Q146: 0 | R146: 0 | S146: 603490925 | T146: 0
A147: =A146+1 -> 140 | B147: =VLOOKUP(C147,$W:$X,2,0) -> 0307 | C147: REKSADANA | D147: Indonesia | E147: 0010003358091000 | F147: STANDARD CHARTERED | G147: Reksadana MDS | H147: SC | I147: IDR | J147: CLOSE | K147: CLOSE | L147: CLOSE | M147: CLOSE | N147: CLOSE | O147: - | P147: 0 | Q147: 0 | R147: 436026214 | S147: 504657757 | T147: 0
A148: =A147+1 -> 141 | B148: =VLOOKUP(C148,$W:$X,2,0) -> 0307 | C148: REKSADANA | D148: Indonesia | E148: 0010003358091000 | F148: STANDARD CHARTERED | G148: Reksadana SDK | H148: SC | I148: IDR | J148: CLOSE | K148: CLOSE | L148: CLOSE | M148: CLOSE | N148: CLOSE | O148: - | P148: 0 | Q148: 0 | R148: 323949804 | S148: 0 | T148: 0
A149: =A148+1 -> 142 | B149: =VLOOKUP(C149,$W:$X,2,0) -> 0307 | C149: REKSADANA | D149: Indonesia | E149: 0010003358091000 | F149: STANDARD CHARTERED | G149: Reksadana SDK | H149: SC | I149: IDR | J149: CLOSE | K149: CLOSE | L149: CLOSE | M149: CLOSE | N149: CLOSE | O149: - | P149: 0 | Q149: 304174890 | R149: 404174890 | S149: 0 | T149: 0
A150: =A149+1 -> 143 | B150: =VLOOKUP(C150,$W:$X,2,0) -> 0307 | C150: REKSADANA | D150: Indonesia | E150: 0010003358091000 | F150: STANDARD CHARTERED | G150: Reksadana Mansyaf USD $11.000 | H150: SC | I150: IDR | J150: CLOSE | K150: CLOSE | L150: CLOSE | M150: CLOSE | N150: CLOSE | O150: - | P150: 0 | Q150: 170500000 | R150: 170500000 | S150: 157234000 | T150: 0
A151: =A150+1 -> 144 | B151: =VLOOKUP(C151,$W:$X,2,0) -> 0399 | C151: INVESTASI LAINNYA | D151: Indonesia | E151: 0010003358091000 | F151: STANDARD CHARTERED | G151: Asuransi Prudent 721 | H151: SC | I151: IDR | J151: CLOSE | K151: CLOSE | L151: CLOSE | M151: CLOSE | N151: CLOSE | O151: - | P151: 0 | Q151: 0 | R151: 498503366 | S151: 745520823 | T151: 0
A152: =A151+1 -> 145 | B152: =VLOOKUP(C152,$W:$X,2,0) -> 0399 | C152: INVESTASI LAINNYA | D152: Indonesia | E152: 0010003358091000 | F152: STANDARD CHARTERED | G152: Asuransi Prudent 141 | H152: SC | I152: IDR | J152: CLOSE | K152: CLOSE | L152: CLOSE | M152: CLOSE | N152: CLOSE | O152: - | P152: 0 | Q152: 179956104 | R152: 578723665 | S152: 590545251 | T152: 0
A153: =A152+1 -> 146 | B153: =VLOOKUP(C153,$W:$X,2,0) -> 0399 | C153: INVESTASI LAINNYA | D153: Indonesia | E153: 0010003358091000 | F153: STANDARD CHARTERED | G153: Asuransi Jiwasraya 206 | H153: SC | I153: IDR | J153: CLOSE | K153: CLOSE | L153: CLOSE | M153: CLOSE | N153: CLOSE | O153: - | P153: 0 | Q153: 0 | R153: 168253767 | S153: 168253767 | T153: 0
A154: =A153+1 -> 147 | B154: =VLOOKUP(C154,$W:$X,2,0) -> 0399 | C154: INVESTASI LAINNYA | D154: Indonesia | E154: 0010003358091000 | F154: STANDARD CHARTERED | G154: Asuransi Jiwasraya 484 | H154: SC | I154: IDR | J154: CLOSE | K154: CLOSE | L154: CLOSE | M154: CLOSE | N154: CLOSE | O154: - | P154: 0 | Q154: 0 | R154: 265207993 | S154: 265207993 | T154: 2000000000
A155: =A154+1 -> 148 | B155: =VLOOKUP(C155,$W:$X,2,0) -> 0399 | C155: INVESTASI LAINNYA | D155: Indonesia | E155: 0010003358091000 | F155: STANDARD CHARTERED | G155: Asuransi Jiwasraya 196 | H155: SC | I155: IDR | J155: CLOSE | K155: CLOSE | L155: CLOSE | M155: CLOSE | N155: CLOSE | O155: - | P155: 0 | Q155: 0 | R155: 275531185 | S155: 275531185 | T155: 2000000000
... A167: =A166+1 -> 160 | B167: =VLOOKUP(C167,$W:$X,2,0) -> 0399 | C167: INVESTASI LAINNYA | D167: Indonesia | E167: 0013084496091000 | F167: BANK CENTRAL ASIA | G167: BCA Asuransi AIA No. Polis 5291 | H167: BCA | I167: IDR | J167: CLOSE | K167: CLOSE | L167: CLOSE | M167: CLOSE | N167: CLOSE | O167: - | P167: 0 | Q167: 39063410 | R167: 0 | S167: 0 | T167: 0
A168: =A167+1 -> 161 | B168: =VLOOKUP(C168,$W:$X,2,0) -> 0305 | C168: OBLIGASI PEMERINTAH | D168: Indonesia | F168: BANK PAN INDONESIA | G168: Obligasi ORI017 | H168: PAN | I168: IDR | J168: CLOSE | K168: CLOSE | L168: CLOSE | M168: CLOSE | N168: CLOSE | P168: 0 | Q168: 0 | R168: 3000000000 | S168: 3000000000 | T168: 3000000000
A169: =A168+1 -> 162 | B169: =VLOOKUP(C169,$W:$X,2,0) -> 0305 | C169: OBLIGASI PEMERINTAH | D169: Indonesia | F169: BANK PAN INDONESIA | G169: Obligasi SR013 | H169: PAN | I169: IDR | J169: CLOSE | K169: CLOSE | L169: CLOSE | M169: CLOSE | N169: CLOSE | P169: 0 | Q169: 0 | R169: 2400000000 | S169: 2000000000 | T169: 2400000000
A170: =A169+1 -> 163 | B170: =VLOOKUP(C170,$W:$X,2,0) -> 0305 | C170: OBLIGASI PEMERINTAH | D170: Indonesia | F170: BANK PAN INDONESIA | G170: Obligasi ORI019 | H170: PAN | I170: IDR | J170: CLOSE | K170: CLOSE | L170: CLOSE | M170: CLOSE | N170: CLOSE | P170: 0 | Q170: 2000000000 | R170: 2000000000 | S170: 2000000000 | T170: 0
A171: =A170+1 -> 164 | B171: =VLOOKUP(C171,$W:$X,2,0) -> 0305 | C171: OBLIGASI PEMERINTAH | D171: Indonesia | F171: BANK PAN INDONESIA | G171: Obligasi SBR010 | H171: PAN | I171: IDR | J171: CLOSE | K171: CLOSE | L171: CLOSE | M171: CLOSE | N171: CLOSE | P171: 0 | Q171: 2000000000 | R171: 3000000000 | S171: 3000000000 | T171: 0
A172: =A171+1 -> 165 | B172: =VLOOKUP(C172,$W:$X,2,0) -> 0305 | C172: OBLIGASI PEMERINTAH | D172: Indonesia | F172: BANK PAN INDONESIA | G172: Obligasi INDON 42 USD $200.000 | H172: PAN | I172: IDR | J172: CLOSE | K172: CLOSE | L172: CLOSE | M172: CLOSE | N172: CLOSE | P172: 0 | Q172: 3100000000 | R172: 3100000000 | S172: 2858800000 | T172: 2845600000
A173: =A172+1 -> 166 | B173: =VLOOKUP(C173,$W:$X,2,0) -> 0305 | C173: OBLIGASI PEMERINTAH | D173: Indonesia | F173: BANK PAN INDONESIA | G173: Obligasi INDON 24 New USD $200.000 | H173: PAN | I173: IDR | J173: CLOSE | K173: CLOSE | L173: CLOSE | M173: CLOSE | N173: CLOSE | P173: 0 | Q173: 3100000000 | R173: 3100000000 | S173: 2858800000 | T173: 2845600000
A174: =A173+1 -> 167 | B174: =VLOOKUP(C174,$W:$X,2,0) -> 0305 | C174: OBLIGASI PEMERINTAH | D174: Indonesia | F174: BANK PAN INDONESIA | G174: Obligasi PT Pindad | H174: PAN | I174: IDR | J174: CLOSE | K174: CLOSE | L174: CLOSE | M174: CLOSE | N174: CLOSE | P174: 0 | Q174: 0 | R174: 0 | S174: 0 | T174: 2000000000
A175: =A174+1 -> 168 | B175: =VLOOKUP(C175,$W:$X,2,0) -> 0305 | C175: OBLIGASI PEMERINTAH | D175: Indonesia | F175: BANK PAN INDONESIA | G175: Obligasi FR081 | H175: PAN | I175: IDR | J175: CLOSE | K175: CLOSE | L175: CLOSE | M175: CLOSE | N175: CLOSE | P175: 3000000000 | Q175: 3000000000 | R175: 3000000000 | S175: 3000000000 | T175: 0
A176: =A175+1 -> 169 | B176: =VLOOKUP(C176,$W:$X,2,0) -> 0305 | C176: OBLIGASI PEMERINTAH | D176: Indonesia | F176: BANK PAN INDONESIA | G176: Obligasi INDON 24 New USD $200.000 | H176: PAN | I176: IDR | J176: CLOSE | K176: CLOSE | L176: CLOSE | M176: CLOSE | N176: CLOSE | P176: 3219000000 | Q176: 3100000000 | R176: 3100000000 | S176: 2858800000 | T176: 2845600000
A177: =A176+1 -> 170 | B177: =VLOOKUP(C177,$W:$X,2,0) -> 0305 | C177: OBLIGASI PEMERINTAH | D177: Indonesia | F177: BANK PAN INDONESIA | G177: Obligasi SUKUK 27 USD $200.000 | H177: PAN | I177: IDR | J177: CLOSE | K177: CLOSE | L177: CLOSE | M177: CLOSE | N177: CLOSE | P177: 3219000000 | Q177: 3100000000 | R177: 3100000000 | S177: 2858800000 | T177: 2845600000
A178: =A177+1 -> 171 | B178: =VLOOKUP(C178,$W:$X,2,0) -> 0305 | C178: OBLIGASI PEMERINTAH | D178: Indonesia | F178: BANK PAN INDONESIA | G178: Obligasi INDOIS 27 USD $300.000. 2024 $200.000 | H178: PAN | I178: IDR | J178: CLOSE | K178: CLOSE | L178: CLOSE | M178: CLOSE | N178: CLOSE | P178: 3219000000 | Q178: 4650000000 | R178: 4650000000 | S178: 4288200000 | T178: 4268400000
A179: =A178+1 -> 172 | B179: =VLOOKUP(C179,$W:$X,2,0) -> 0305 | C179: OBLIGASI PEMERINTAH | D179: Indonesia | F179: BANK PAN INDONESIA | G179: Obligasi SR019 | H179: PAN | I179: IDR | J179: CLOSE | K179: CLOSE | L179: CLOSE | M179: CLOSE | N179: CLOSE | P179: 2600000000 | Q179: 2600000000 | R179: 0 | S179: 0 | T179: 0
... A184: =A183+1 -> 177 | B184: =VLOOKUP(C184,$W:$X,2,0) -> 0399 | C184: INVESTASI LAINNYA | D184: Indonesia | F184: BANK CIMB NIAGA | G184: Asuransi CIMB Sunlif Polis No. 808973921 | H184: CIMB | I184: IDR | J184: CLOSE | K184: CLOSE | L184: CLOSE | M184: CLOSE | N184: CLOSE | P184: 0 | Q184: 0 | R184: 0 | S184: 0 | T184: 1859969393
A185: =A184+1 -> 178 | B185: =VLOOKUP(C185,$W:$X,2,0) -> 0307 | C185: REKSADANA | D185: Indonesia | E185: 0013862420091000 | F185: BANK HSBC INDONESIA | G185: Reksadana SDP 90 | H185: HSBC | I185: IDR | J185: CLOSE | K185: CLOSE | L185: CLOSE | M185: CLOSE | N185: CLOSE | P185: 0 | Q185: 490849503 | R185: 300807399 | S185: 968068071 | T185: 0
A186: =A185+1 -> 179 | B186: =VLOOKUP(C186,$W:$X,2,0) -> 0307 | C186: REKSADANA | D186: Indonesia | E186: 0013862420091000 | F186: BANK HSBC INDONESIA | G186: Reksadana MS Syariah USD $53.448 | H186: HSBC | I186: USD | J186: CLOSE | K186: CLOSE | L186: CLOSE | M186: CLOSE | N186: CLOSE | P186: 0 | Q186: 0 | R186: 580723000 | S186: 763985712 | T186: 661730052
A187: =A186+1 -> 180 | B187: =VLOOKUP(C187,$W:$X,2,0) -> 0307 | C187: REKSADANA | D187: Indonesia | E187: 0013862420091000 | F187: BANK HSBC INDONESIA | G187: Reksadana SDPP | H187: HSBC | I187: IDR | J187: CLOSE | K187: CLOSE | L187: CLOSE | M187: CLOSE | N187: CLOSE | P187: 0 | Q187: 0 | R187: 0 | S187: 0 | T187: 1022596897
A188: =A187+1 -> 181 | B188: =VLOOKUP(C188,$W:$X,2,0) -> 0307 | C188: REKSADANA | D188: Indonesia | E188: 0013862420091000 | F188: BANK HSBC INDONESIA | G188: Reksadana Manulife Dana Saham | H188: HSBC | I188: IDR | J188: CLOSE | K188: CLOSE | L188: CLOSE | M188: CLOSE | N188: CLOSE | P188: 0 | Q188: 0 | R188: 0 | S188: 0 | T188: 1728081046
A189: =A188+1 -> 182 | B189: =VLOOKUP(C189,$W:$X,2,0) -> 0307 | C189: REKSADANA | D189: Indonesia | E189: 0013862420091000 | F189: BANK HSBC INDONESIA | G189: SUKUK SR 011 | H189: HSBC | I189: IDR | J189: CLOSE | K189: CLOSE | L189: CLOSE | M189: CLOSE | N189: CLOSE | P189: 0 | Q189: 0 | R189: 0 | S189: 0 | T189: 3000000000
A190: =A189+1 -> 183 | B190: =VLOOKUP(C190,$W:$X,2,0) -> 0307 | C190: REKSADANA | D190: Indonesia | E190: 0013862420091000 | F190: BANK HSBC INDONESIA | G190: Reksadana M Pendapatan Tetap | H190: HSBC | I190: IDR | J190: CLOSE | K190: CLOSE | L190: CLOSE | M190: CLOSE | N190: CLOSE | P190: 0 | Q190: 0 | R190: 0 | S190: 0 | T190: 1619992451
A191: =A190+1 -> 184 | B191: =VLOOKUP(C191,$W:$X,2,0) -> 0307 | C191: REKSADANA | D191: Indonesia | E191: 0013862420091000 | F191: BANK HSBC INDONESIA | G191: Reksadana MDSA | H191: HSBC | I191: IDR | J191: CLOSE | K191: CLOSE | L191: CLOSE | M191: CLOSE | N191: CLOSE | P191: 0 | Q191: 376556671 | R191: 0 | S191: 0 | T191: 0
A192: =A191+1 -> 185 | B192: =VLOOKUP(C192,$W:$X,2,0) -> 0305 | C192: OBLIGASI PEMERINTAH | D192: Indonesia | E192: 0013862420091000 | F192: BANK HSBC INDONESIA | G192: OBLIGASI USD INDON 50 $165.840 | H192: HSBC | I192: IDR | J192: CLOSE | K192: CLOSE | L192: CLOSE | M192: CLOSE | N192: CLOSE | P192: 2669194800 | Q192: 0 | R192: 0 | S192: 0 | T192: 0
A193: =A192+1 -> 186 | B193: =VLOOKUP(C193,$W:$X,2,0) -> 0305 | C193: OBLIGASI PEMERINTAH | D193: Indonesia | E193: 0013862420091000 | F193: BANK HSBC INDONESIA | G193: OBLIGASI ORI025T6 | H193: HSBC | I193: IDR | J193: CLOSE | K193: CLOSE | L193: CLOSE | M193: CLOSE | N193: CLOSE | P193: 2041200000 | Q193: 0 | R193: 0 | S193: 0 | T193: 0
A194: =A193+1 -> 187 | B194: =VLOOKUP(C194,$W:$X,2,0) -> 0305 | C194: OBLIGASI PEMERINTAH | D194: Indonesia | E194: 0013862420091000 | F194: BANK HSBC INDONESIA | G194: OBLIGASI ORI026T6 | H194: HSBC | I194: IDR | J194: CLOSE | K194: CLOSE | L194: CLOSE | M194: CLOSE | N194: CLOSE | P194: 1940000000 | Q194: 0 | R194: 0 | S194: 0 | T194: 0
A195: =A194+1 -> 188 | B195: =VLOOKUP(C195,$W:$X,2,0) -> 0307 | C195: REKSADANA | D195: Indonesia | F195: SINARMAS ASSET MANAGEMENT | G195: Sinarmas Asset Mng. - Equity link note 111475 | H195: SMAS | I195: IDR | J195: CLOSE | K195: CLOSE | L195: CLOSE | M195: CLOSE | N195: CLOSE | P195: 0 | Q195: 0 | R195: 0 | S195: 1052659450 | T195: 1072392000
A196: =A195+1 -> 189 | B196: =VLOOKUP(C196,$W:$X,2,0) -> 0307 | C196: REKSADANA | D196: Indonesia | F196: SINARMAS ASSET MANAGEMENT | G196: Sinarmas Asset Mng. - Credit Link note 110807 | H196: SMAS | I196: IDR | J196: CLOSE | K196: CLOSE | L196: CLOSE | M196: CLOSE | N196: CLOSE | P196: 0 | Q196: 0 | R196: 0 | S196: 908816730 | T196: 895007000
A197: =A196+1 -> 190 | B197: =VLOOKUP(C197,$W:$X,2,0) -> 0307 | C197: REKSADANA | D197: Indonesia | F197: SINARMAS ASSET MANAGEMENT | G197: Sinarmas Sinarmas Saham | H197: SMAS | I197: IDR | J197: CLOSE | K197: CLOSE | L197: CLOSE | M197: CLOSE | N197: CLOSE | P197: 5450835 | Q197: 0 | R197: 0 | S197: 0 | T197: 0
A198: =A197+1 -> 191 | B198: =VLOOKUP(C198,$W:$X,2,0) -> 0399 | C198: INVESTASI LAINNYA | D198: Indonesia | E198: 0013429402091000 | F198: BANK DBS INDONESIA | G198: Asuransi Jiwasraya RA 020101697 | H198: SSEK | I198: IDR | J198: CLOSE | K198: CLOSE | L198: CLOSE | M198: CLOSE | N198: CLOSE | P198: 0 | Q198: 0 | R198: 159446670 | S198: 159446670 | T198: 1539516000
A199: =A198+1 -> 192 | B199: =VLOOKUP(C199,$W:$X,2,0) -> 0399 | C199: INVESTASI LAINNYA | D199: Indonesia | E199: 0013429402091000 | F199: BANK DBS INDONESIA | G199: Asuransi Jiwasraya RA 020105627 | H199: SSEK | I199: IDR | J199: CLOSE | K199: CLOSE | L199: CLOSE | M199: CLOSE | N199: CLOSE | P199: 0 | Q199: 0 | R199: 110528100 | S199: 110528100 | T199: 1070000000
A200: =A199+1 -> 193 | B200: =VLOOKUP(C200,$W:$X,2,0) -> 0399 | C200: INVESTASI LAINNYA | D200: Indonesia | E200: 0013429402091000 | F200: BANK DBS INDONESIA | G200: Asuransi Jiwasraya RA 020104638 | H200: SSEK | I200: IDR | J200: CLOSE | K200: CLOSE | L200: CLOSE | M200: CLOSE | N200: CLOSE | P200: 0 | Q200: 0 | R200: 113677428 | S200: 113677428 | T200: 1000000000
A201: =A200+1 -> 194 | B201: =VLOOKUP(C201,$W:$X,2,0) -> 0399 | C201: INVESTASI LAINNYA | D201: Indonesia | E201: 0013429402091000 | F201: BANK DBS INDONESIA | G201: Asuransi Jiwasraya RA 020101753 | H201: SSEK | I201: IDR | J201: CLOSE | K201: CLOSE | L201: CLOSE | M201: CLOSE | N201: CLOSE | P201: 0 | Q201: 0 | R201: 265205093 | S201: 265205093 | T201: 1265860000
A202: =A201+1 -> 195 | B202: =VLOOKUP(C202,$W:$X,2,0) -> 0399 | C202: INVESTASI LAINNYA | D202: Indonesia | E202: 0013429402091000 | F202: BANK DBS INDONESIA | G202: Asuransi Jiwasraya RA 020100903 | H202: SSEK | I202: IDR | J202: CLOSE | K202: CLOSE | L202: CLOSE | M202: CLOSE | N202: CLOSE | P202: 0 | Q202: 0 | R202: 321899470 | S202: 321899470 | T202: 2888028000
A203: =A202+1 -> 196 | B203: =VLOOKUP(C203,$W:$X,2,0) -> 0399 | C203: INVESTASI LAINNYA | D203: Indonesia | E203: 0013429402091000 | F203: BANK DBS INDONESIA | G203: Asuransi Jiwasraya RA 020101243 | H203: SSEK | I203: IDR | J203: CLOSE | K203: CLOSE | L203: CLOSE | M203: CLOSE | N203: CLOSE | P203: 0 | Q203: 0 | R203: 200729952 | S203: 200729952 | T203: 1324395000
A204: =A203+1 -> 197 | B204: =VLOOKUP(C204,$W:$X,2,0) -> 0399 | C204: INVESTASI LAINNYA | D204: Indonesia | E204: 0013429402091000 | F204: BANK DBS INDONESIA | G204: Asuransi Jiwasraya RA 0201011583 | H204: SSEK | I204: IDR | J204: CLOSE | K204: CLOSE | L204: CLOSE | M204: CLOSE | N204: CLOSE | P204: 0 | Q204: 0 | R204: 266558320 | S204: 266558320 | T204: 2565860000
A205: =A204+1 -> 198 | B205: =VLOOKUP(C205,$W:$X,2,0) -> 0399 | C205: INVESTASI LAINNYA | D205: Indonesia | E205: 0013429402091000 | F205: BANK DBS INDONESIA | G205: Asuransi Jiwasraya RA 020103416 | H205: SSEK | I205: IDR | J205: CLOSE | K205: CLOSE | L205: CLOSE | M205: CLOSE | N205: CLOSE | P205: 0 | Q205: 0 | R205: 241533922 | S205: 241533922 | T205: 2160000000
A206: =A205+1 -> 199 | B206: =VLOOKUP(C206,$W:$X,2,0) -> 0307 | C206: REKSADANA | D206: Indonesia | E206: 0013429402091000 | F206: BANK DBS INDONESIA | G206: SUKUK SR013 | H206: SSEK | I206: IDR | J206: CLOSE | K206: CLOSE | L206: CLOSE | M206: CLOSE | N206: CLOSE | P206: 0 | Q206: 0 | R206: 0 | S206: 3000000000 | T206: 3000000000
A207: =A206+1 -> 200 | B207: =VLOOKUP(C207,$W:$X,2,0) -> 0307 | C207: REKSADANA | D207: Indonesia | E207: 0013429402091000 | F207: BANK DBS INDONESIA | G207: SUKUK ST007 | H207: SSEK | I207: IDR | J207: CLOSE | K207: CLOSE | L207: CLOSE | M207: CLOSE | N207: CLOSE | P207: 0 | Q207: 0 | R207: 0 | S207: 3000000000 | T207: 3000000000
A208: =A207+1 -> 201 | B208: =VLOOKUP(C208,$W:$X,2,0) -> 0307 | C208: REKSADANA | D208: Indonesia | E208: 0013429402091000 | F208: BANK DBS INDONESIA | G208: DBS USD 106,446 - REKSADANA MS S | H208: SSEK | I208: IDR | J208: CLOSE | K208: CLOSE | L208: CLOSE | M208: CLOSE | N208: CLOSE | P208: 0 | Q208: 0 | R208: 0 | S208: 0 | T208: 1514513688
...

Sheet PIUTANG
C1: 2. PIUTANG
C2: Uang Tunai/Tabungan/Giro/Deposito
C4: 3173042409640005 | D4: SINDJAJA JONANY
I5: =SUM(I8:I55) -> 0 | K5: =SUM(K8:K55) -> 0 | L5: =SUM(L8:L55) -> 0 | M5: =SUM(M8:M55) -> 0 | N5: =SUM(N8:N55) -> 0 | O5: =SUM(O8:O55) -> 0
A6: NO | B6: KODE | C6: DESKRIPSI | D6: LOKASI PENERIMA PINJAMAN | E6: PENERIMA PINJAMAN | G6: NILAI PIUTANG | H6: TAHUN DIMULAI | I6: NILAI PIUTANG SAAT INI (2025) | J6: (HARTA PPS/ HARTA INVESTASI PPS) | K6: NILAI TAHUN SEBELUMNYA
E7: NIK / NPWP | F7: NAMA | K7: 2024 | L7: 2023 | M7: 2022 | N7: 2021 | O7: 2020 | Q7: - | R7: - | S7: -
A8: 1 | B8: =VLOOKUP(C8,$R:$S,2,0) -> - | C8: - | Q8: 0201 | R8: PIUTANG USAHA | S8: 0201
A9: =A8+1 -> 2 | Q9: 0202 | R9: PIUTANG AFILIASI | S9: 0202
A10: =A9+1 -> 3 | Q10: 0209 | R10: PIUTANG LAINNYA | S10: 0209
A11: =A10+1 -> 4
A12: =A11+1 -> 5
A13: =A12+1 -> 6
A14: =A13+1 -> 7
A15: =A14+1 -> 8
A16: =A15+1 -> 9
A17: =A16+1 -> 10
A18: =A17+1 -> 11
A19: =A18+1 -> 12
A20: =A19+1 -> 13
A21: =A20+1 -> 14
A22: =A21+1 -> 15
... A55: =A54+1 -> 48

Sheet HARTA BERGERAK
C1: 4. HARTA BERGERAK
C2: Motor/Mobil
C4: 3173042409640005 | D4: SINDJAJA JONANY | K4: CEK TYPE DI STNK (DIBAWAH TULISAN MERK)
J5: =SUM(J8:J55) -> 1858000000 | K5: =SUM(K8:K55) -> 1251300000 | M5: =SUM(M8:M55) -> 2287500000 | N5: =SUM(N8:N55) -> 1852500000 | O5: =SUM(O8:O55) -> 1852500000 | P5: =SUM(P8:P55) -> 2272500000 | Q5: =SUM(Q8:Q55) -> 1264500000
A6: NO | B6: KODE | C6: DESKRIPSI | E6: NOMOR POLISI/REGISTRASI | F6: KEPEMILIKAN | I6: TAHUN PEROLEHAN | J6: HARGA PEROLEHAN | K6: NILAI SAAT INI (2025) | L6: (Harta PPS/ Harta Investasi PPS) | M6: NILAI TAHUN SEBELUMNYA
C7: TIPE | D7: MEREK/MODEL | F7: MILIK SENDIRI/ ORANG LAIN | G7: NIK / NPWP | H7: NAMA | M7: 2024 | N7: 2023 | O7: 2022 | P7: 2021 | Q7: 2020 | S7: - | T7: - | U7: -
A8: 1 | B8: =VLOOKUP(C8,T:U,2,0) -> 0403 | C8: MOBIL PENUMPANG | D8: LEXUS RX300 | E8: B 1778 JYO | F8: OTHER | G8: 3173044110760006 | H8: ROSALINA CHANDRA | I8: 2021 | J8: 1407000000 | K8: 1008000000 | L8: - | M8: 1407000000 | N8: 1407000000 | O8: 1407000000 | P8: 1407000000 | Q8: 0 | S8: 0401 | T8: SEPEDA | U8: 0401
A9: 2 | B9: =VLOOKUP(C9,T:U,2,0) -> 0403 | C9: MOBIL PENUMPANG | D9: EV NETA X | E9: B 1309 UNS | F9: TAXPAYER | G9: 3173042409640005 | H9: SINDJAJA JONANY | I9: 2024 | J9: 435000000 | K9: 235000000 | L9: - | M9: 435000000 | N9: 0 | O9: 0 | P9: 0 | Q9: 0 | S9: 0402 | T9: SEPEDA MOTOR | U9: 0402
A10: 3 | B10: =VLOOKUP(C10,T:U,2,0) -> 0402 | C10: SEPEDA MOTOR | D10: YAMAHA VEGA ZR | E10: B 6697 BVO | F10: TAXPAYER | G10: 3173042409640005 | H10: SINDJAJA JONANY | I10: 2025 | J10: 8000000 | K10: 3600000 | L10: - | M10: 0 | N10: 0 | O10: 0 | P10: 0 | Q10: 0 | S10: 0403 | T10: MOBIL PENUMPANG | U10: 0403
A11: 4 | B11: =VLOOKUP(C11,T:U,2,0) -> 0402 | C11: SEPEDA MOTOR | D11: YAMAHA VEGA ZR | E11: B 3674 SBT | F11: TAXPAYER | G11: 3173042409640005 | H11: SINDJAJA JONANY | I11: 2025 | J11: 8000000 | K11: 4700000 | L11: - | M11: 0 | N11: 0 | O11: 0 | P11: 0 | Q11: 0 | S11: 0404 | T11: BUS | U11: 0404
S12: 0405 | T12: KENDARAAN ANGKUTAN JALAN | U12: 0405
C13: SEPEDA MOTOR | D13: MOTOR HONDA NF 100 | E13: B 4525 MK | I13: 2002 | J13: CLOSE | K13: CLOSE | L13: - | M13: 10500000 | N13: 10500000 | O13: 10500000 | P13: 10500000 | Q13: 10500000 | S13: 0406 | T13: KENDARAAN TUJUAN KHUSUS | U13: 0406
C14: MOBIL PENUMPANG | D14: TOYOTA FORTUNER 2.5G AT | E14: B 2178 MR | I14: 2015 | J14: CLOSE | K14: DILAPOR JUAL 2025. HARUSNYA 2024 | L14: - | M14: 435000000 | N14: 435000000 | O14: 435000000 | P14: 435000000 | Q14: 435000000 | S14: 0407 | T14: KERETA | U14: 0407
C15: MOBIL PENUMPANG | D15: VW GOLF Tsi | E15: NO.POL : B 668 ROS | I15: CLOSE | J15: CLOSE | K15: CLOSE | L15: - | M15: 0 | N15: 0 | O15: 0 | P15: 0 | Q15: 399000000 | S15: 0408 | T15: PESAWAT TERBANG | U15: 0408
C16: MOBIL PENUMPANG | D16: VW TIGUAN 1.4 AT | E16: B 1207 UJL | I16: CLOSE | J16: CLOSE | K16: CLOSE | L16: - | M16: 0 | N16: 0 | O16: 0 | P16: 420000000 | Q16: 420000000 | S16: 0409 | T16: KAPAL | U16: 0409
S17: 0410 | T17: MESIN | U17: 0410
S18: 0411 | T18: GEROBAK | U18: 0411
S19: 0412 | T19: KAPAL PESIAR | U19: 0412
S20: 0499 | T20: HARTA BERGERAK LAINNYA | U20: 0499
S22: OWNERSHIP MOVEABLE ASSET
S23: Code | T23: Code Description
S24: OTHER | T24: Atas nama pihak lain
S25: TAXPAYER | T25: Atas nama sendiri

Sheet HARTA TIDAK BERGERAK
C1: 5. HARTA TIDAK BERGERAK
C2: Tanah Kosong/Tanah Bangunan untuk Tempat Tinggal/Apartemen/Vessel/Tanah atau Lahan untuk Usaha/Tanah Bangunan untuk Usaha atau yang disewakan
C4: 3173042409640005 | D4: SINDJAJA JONANY | F4: CEK PBB 2025 | L4: CEK NJOP PBB 2025
K5: =SUM(K8:K55) -> 21454481063 | L5: =SUM(L8:L55) -> 57938723564 | N5: =SUM(N8:N55) -> 21454481063 | O5: =SUM(O8:O55) -> 19271771063 | P5: =SUM(P8:P55) -> 15371771063 | Q5: =SUM(Q8:Q55) -> 15251771063 | R5: =SUM(R8:R55) -> 14207771063
A6: NO | B6: KODE | C6: DESKRIPSI | D6: LOKASI HARTA | E6: DETAIL | F6: UKURAN PROPERTI | H6: SUMBER KEPEMILIKAN | I6: NOMOR SERTIFIKAT | J6: TAHUN PEROLEHAN | K6: HARGA PEROLEHAN | L6: NILAI SAAT INI (2025) | M6: (Harta PPS/ Harta Investasi PPS) | N6: NILAI TAHUN SEBELUMNYA
F7: TANAH | G7: BANGUNAN | N7: 2024 | O7: 2023 | P7: 2022 | Q7: 2021 | R7: 2020 | T7: - | U7: - | V7: -
A8: 1 | B8: =VLOOKUP(C8,$U:$V,2,0) -> 0502 | C8: TANAH DAN/ATAU BANGUNAN UNTUK TEMPAT TINGGAL | D8: Indonesia | E8: RUMAH, JL. KEADILAN V NO. 33 A, RT 012 RW 05, GLODOK, TAMAN SARI, JAKARTA BARAT | F8: 84 M2 | G8: 200 M2 | H8: Own Income | I8: 317405000500900900 | J8: 1992 | K8: 60000000 | L8: 1318220000 | M8: - | N8: 60000000 | O8: 60000000 | P8: 60000000 | Q8: 60000000 | R8: 60000000 | T8: 0501 | U8: TANAH KOSONG | V8: 0501 | W8: NOP: 31.71.070.001.013-0028.0
A9: =A8+1 -> 2 | B9: =VLOOKUP(C9,$U:$V,2,0) -> 0502 | C9: TANAH DAN/ATAU BANGUNAN UNTUK TEMPAT TINGGAL | D9: Indonesia | E9: RUMAH,JL.WALET INDAH I NO. 21, KAV.ST/NI-2, RT 14 RW 06, KAPUK MUARA, PENJARINGAN, JAKARTA UTARA | F9: 420 M2 | G9: 381 M2 | H9: Own Income | I9: 317501000204600030 | J9: 2001 | K9: 905310000 | L9: 10227585000 | M9: - | N9: 905310000 | O9: 905310000 | P9: 905310000 | Q9: 905310000 | R9: 905310000 | T9: 0502 | U9: TANAH DAN/ATAU BANGUNAN UNTUK TEMPAT TINGGAL | V9: 0502 | W9: NOP: 31.71.070.001.017-0141.0
A10: =A9+1 -> 3 | B10: =VLOOKUP(C10,$U:$V,2,0) -> 0501 | C10: TANAH KOSONG | D10: Indonesia | E10: KAVLING, LAKSANA BISNIS PARK UNIT BB02, LAKSANA, PAKU HAJI, KAB. TANGERANG, BANTEN | F10: 0 M2 | G10: 930 M2 | H10: Own Income | I10: 361915101300403160 | J10: 2016 | K10: 581250000 | L10: 959760000 | M10: - | N10: 581250000 | O10: 581250000 | P10: 581250000 | Q10: 581250000 | R10: 581250000 | T10: 0503 | U10: APARTEMEN | V10: 0503
A11: =A10+1 -> 4 | B11: =VLOOKUP(C11,$U:$V,2,0) -> 0501 | C11: TANAH KOSONG | D11: Indonesia | E11: KAVLING, LAKSANA BISNIS PARK UNIT BB03, LAKSANA, PAKU HAJI, KAB. TANGERANG, BANTEN | F11: 0 M2 | G11: 930 M2 | H11: Own Income | I11: 361915101300403170 | J11: 2016 | K11: 581250000 | L11: 959760000 | M11: - | N11: 581250000 | O11: 581250000 | P11: 581250000 | Q11: 581250000 | R11: 581250000 | T11: 0504 | U11: VESSEL | V11: 0504
A12: =A11+1 -> 5 | B12: =VLOOKUP(C12,$U:$V,2,0) -> 0501 | C12: TANAH KOSONG | D12: Indonesia | E12: TANAH, DESA KEDAUNG BARAT, SEPATAN TIMUR, KAB. TANGERANG, BANTEN | F12: 192 M2 | G12: 0 M2 | H12: Own Income | I12: AJB - MARTIA SH NO. 270 | J12: 2016 | K12: 30720000 | L12: 30720000 | M12: - | N12: 30720000 | O12: 30720000 | P12: 30720000 | Q12: 30720000 | R12: 30720000 | T12: 0505 | U12: TANAH ATAU LAHAN UNTUK USAHA (LAHAN PERTANIAN, PERKEBUNAN, DSB) | V12: 0505
A13: =A12+1 -> 6 | B13: =VLOOKUP(C13,$U:$V,2,0) -> 0502 | C13: TANAH DAN/ATAU BANGUNAN UNTUK TEMPAT TINGGAL | D13: Indonesia | E13: RUMAH, JL.WALET PERMAI 3 NO.7 ST/K7-08, KAPUK MUARA, PENJARINGAN, JAKARTA UTARA | F13: 175 M2 | G13: 198 M2 | H13: Own Income | I13: 317501000204501510 | J13: 2016 | K13: 2850000000 | L13: 4121625000 | M13: - | N13: 2850000000 | O13: 2850000000 | P13: 2850000000 | Q13: 2850000000 | R13: 2850000000 | T13: 0506 | U13: TANAH DAN/ATAU BANGUNAN UNTUK USAHA (TOKO, PABRIK, DSB) | V13: 0506
A14: =A13+1 -> 7 | B14: =VLOOKUP(C14,$U:$V,2,0) -> 0502 | C14: TANAH DAN/ATAU BANGUNAN UNTUK TEMPAT TINGGAL | D14: Indonesia | E14: RUMAH, PIK 2 TYPE GLADIOL, JL. TAMPA 2, SALEMBARAN JATI, KOSAMBI, KAB. TANGERANG, BANTEN | F14: 100 M2 | G14: 142 M2 | H14: Own Income | I14: 361916100200315650 | J14: 2021 | K14: 1164000000 | L14: 1164000000 | M14: 427100000 | N14: 1164000000 | O14: 1164000000 | P14: 1164000000 | Q14: 1044000000 | R14: 0 | T14: 0507 | U14: TANAH DAN/ATAU BANGUNAN YANG DISEWAKAN | V14: 0507
A15: =A14+1 -> 8 | B15: =VLOOKUP(C15,$U:$V,2,0) -> 0502 | C15: TANAH DAN/ATAU BANGUNAN UNTUK TEMPAT TINGGAL | D15: Indonesia | E15: RUMAH, JL. WALET BLOK E6. NO. 6 (BLOK R2 KAV. NO.9), RT 15 RW 06, KAPUK MUARA, PENJARINGAN, JAKARTA UTARA | F15: 175 M2 | G15: 131 M2 | H15: Own Income | I15: 317501000204700550 | J15: 2023 | K15: 3900000000 | L15: 3974225000 | M15: - | N15: 3900000000 | O15: 3900000000 | P15: 0 | Q15: 0 | R15: 0 | T15: 0509 | U15: HARTA TIDAK BERGERAK LAINNYA | V15: 0509
A16: =A15+1 -> 9 | B16: =VLOOKUP(C16,$U:$V,2,0) -> 0502 | C16: TANAH DAN/ATAU BANGUNAN UNTUK TEMPAT TINGGAL | D16: Indonesia | E16: RUMAH, JL. DANAU SINGKARAK G1/50, BENDUNGAN HILIR (KEPEMILIKAN 1/2 BAGIAN), JAKARTA PUSAT | F16: 217 M2 | G16: 164 M2 | H16: Own Income | I16: 317301000201300590 | J16: 2024 | K16: 2350000000 | L16: =4606543000/2 -> 2303271500 | M16: - | N16: 2350000000 | O16: 0 | P16: 0 | Q16: 0 | R16: 0
A17: =A16+1 -> 10 | B17: =VLOOKUP(C17,$U:$V,2,0) -> 0506 | C17: TANAH DAN/ATAU BANGUNAN UNTUK USAHA (TOKO, PABRIK, DSB) | D17: Indonesia | E17: TOKO, JEMBATAN ITC MG II LTI III/ BLOK A/3, ANCOL, PADEMANGAN, JAKARTA UTARA | F17: 0 M2 | G17: 20 M2 | H17: Own Income | I17: 317501100302013190 | J17: 1999 | K17: 170000000 | L17: 511180000 | M17: - | N17: 170000000 | O17: 170000000 | P17: 170000000 | Q17: 170000000 | R17: 170000000
A18: =A17+1 -> 11 | B18: =VLOOKUP(C18,$U:$V,2,0) -> 0506 | C18: TANAH DAN/ATAU BANGUNAN UNTUK USAHA (TOKO, PABRIK, DSB) | D18: Indonesia | E18: RUKO, JL. MANGGA DUA RAYA BLOK F-5 NO.15, RT 03 RW 13, MANGGA DUA SELATAN, SAWAH BESAR, JAKARTA PUSAT | F18: 63 M2 | G18: 219 M2 | H18: Own Income | I18: 317306000500208350 | J18: 2000 | K18: 490500000 | L18: 3154842000 | M18: - | N18: 490500000 | O18: 490500000 | P18: 490500000 | Q18: 490500000 | R18: 490500000 | T18: Source of Income
A19: =A18+1 -> 12 | B19: =VLOOKUP(C19,$U:$V,2,0) -> 0506 | C19: TANAH DAN/ATAU BANGUNAN UNTUK USAHA (TOKO, PABRIK, DSB) | D19: Indonesia | E19: RUKO, JL. MANGGA DUA RAYA BLOK F-5 NO.16, RT 03 RW 13, MANGGA DUA SELATAN, SAWAH BESAR, JAKARTA PUSAT | F19: 76 M2 | G19: 304 M2 | H19: Own Income | I19: 317306000500200900 | J19: 2003 | K19: 600000000 | L19: 4119580000 | M19: - | N19: 600000000 | O19: 600000000 | P19: 600000000 | Q19: 600000000 | R19: 600000000 | T19: Code Name | U19: Code Description
A20: =A19+1 -> 13 | B20: =VLOOKUP(C20,$U:$V,2,0) -> 0506 | C20: TANAH DAN/ATAU BANGUNAN UNTUK USAHA (TOKO, PABRIK, DSB) | D20: Indonesia | E20: TOKO, JEMBATAN ITC LT.II BLOK A NO.69, ANCOL, PADEMANGAN, JAKARTA UTARA | F20: 0 M2 | G20: 17 M2 | H20: Own Income | I20: 317501100302009920 | J20: 2003 | K20: 230000000 | L20: 409265000 | M20: - | N20: 230000000 | O20: 230000000 | P20: 230000000 | Q20: 230000000 | R20: 230000000 | T20: Debt | U20: Utang
A21: =A20+1 -> 14 | B21: =VLOOKUP(C21,$U:$V,2,0) -> 0502 | C21: TANAH DAN/ATAU BANGUNAN UNTUK TEMPAT TINGGAL | D21: Indonesia | E21: RUMAH, JL. CAMAR INDAH I BLOK D-A NO.12, KAPUK MUARA, PENJARINGAN, JAKARTA UTARA | F21: 100 M2 | G21: 316 M2 | H21: Own Income | I21: 317501000204302860 | J21: 2008 | K21: 1450000000 | L21: 3211900000 | M21: - | N21: 1450000000 | O21: 1450000000 | P21: 1450000000 | Q21: 1450000000 | R21: 1450000000 | T21: Gift | U21: Hadiah
A22: =A21+1 -> 15 | B22: =VLOOKUP(C22,$U:$V,2,0) -> 0506 | C22: TANAH DAN/ATAU BANGUNAN UNTUK USAHA (TOKO, PABRIK, DSB) | D22: Indonesia | E22: KOMPLEK PERGUDANGAN SENTRA INDUSTRI TERPADU PIK, BLOK E2 NO. 55, KAMAL MUARA, PENJARINGAN, JAKARTA UTARA | F22: 162 M2 | G22: 252 M2 | H22: Own Income | I22: 317501000101401930 | J22: 2009 | K22: 472843636 | L22: 2437506000 | M22: - | N22: 472843636 | O22: 472843636 | P22: 472843636 | Q22: 472843636 | R22: 472843636 | T22: Grant | U22: Hibah
A23: =A22+1 -> 16 | B23: =VLOOKUP(C23,$U:$V,2,0) -> 0506 | C23: TANAH DAN/ATAU BANGUNAN UNTUK USAHA (TOKO, PABRIK, DSB) | D23: Indonesia | E23: KOMPLEK PERGUDANGAN SENTRA INDUSTRI TERPADU PIK, BLOK E2 NO. 56, KAMAL MUARA, PENJARINGAN, JAKARTA UTARA | F23: 162 M2 | G23: 252 M2 | H23: Own Income | I23: 317501000101401940 | J23: 2009 | K23: 472843636 | L23: 2437506000 | M23: - | N23: 472843636 | O23: 472843636 | P23: 472843636 | Q23: 472843636 | R23: 472843636 | T23: Inheritance | U23: Warisan
A24: =A23+1 -> 17 | B24: =VLOOKUP(C24,$U:$V,2,0) -> 0506 | C24: TANAH DAN/ATAU BANGUNAN UNTUK USAHA (TOKO, PABRIK, DSB) | D24: Indonesia | E24: KOMPLEK PERGUDANGAN SENTRA INDUSTRI TERPADU PIK, BLOK E2 NO. 57, KAMAL MUARA, PENJARINGAN, JAKARTA UTARA | F24: 162 M2 | G24: 252 M2 | H24: Own Income | I24: 317501000101401950 | J24: 2009 | K24: 527570909 | L24: 2437506000 | M24: - | N24: 527570909 | O24: 527570909 | P24: 527570909 | Q24: 527570909 | R24: 527570909 | T24: Other sources | U24: Sumber lainnya
A25: =A24+1 -> 18 | B25: =VLOOKUP(C25,$U:$V,2,0) -> 0506 | C25: TANAH DAN/ATAU BANGUNAN UNTUK USAHA (TOKO, PABRIK, DSB) | D25: Indonesia | E25: KOMPLEK PERGUDANGAN SENTRA INDUSTRI TERPADU PIK, BLOK E2 NO. 58, KAMAL MUARA, PENJARINGAN, JAKARTA UTARA | F25: 162 M2 | G25: 252 M2 | H25: Own Income | I25: 317501000101401960 | J25: 2009 | K25: 527570909 | L25: 2437506000 | M25: - | N25: 527570909 | O25: 527570909 | P25: 527570909 | Q25: 527570909 | R25: 527570909 | T25: Own Income | U25: Hasil Sendiri
A26: =A25+1 -> 19 | B26: =VLOOKUP(C26,$U:$V,2,0) -> 0506 | C26: TANAH DAN/ATAU BANGUNAN UNTUK USAHA (TOKO, PABRIK, DSB) | D26: Indonesia | E26: TOKO, MANGGA DUA SQUARE UG-B145B, ANCOL, PADEMANGAN, JAKARTA UTARA | F26: 0 M2 | G26: 13 M2 | H26: Own Income | I26: 317501100302322570 | J26: 2009 | K26: 337336364 | L26: 337336364 | M26: 243069000 | N26: 337336364 | O26: 337336364 | P26: 337336364 | Q26: 337336364 | R26: 337336364
A27: =A26+1 -> 20 | B27: =VLOOKUP(C27,$U:$V,2,0) -> 0506 | C27: TANAH DAN/ATAU BANGUNAN UNTUK USAHA (TOKO, PABRIK, DSB) | D27: Indonesia | E27: KOMPLEK PERGUDANGAN SENTRA INDUSTRI TERPADU PIK, BLOK E2 NO. 59, KAMAL MUARA, PENJARINGAN, JAKARTA UTARA | F27: 162 M2 | G27: 252 M2 | H27: Own Income | I27: 317501000101401970 | J27: 2011 | K27: 527570909 | L27: 2437506000 | M27: - | N27: 527570909 | O27: 527570909 | P27: 527570909 | Q27: 527570909 | R27: 527570909
A28: =A27+1 -> 21 | B28: =VLOOKUP(C28,$U:$V,2,0) -> 0506 | C28: TANAH DAN/ATAU BANGUNAN UNTUK USAHA (TOKO, PABRIK, DSB) | D28: Indonesia | E28: RUKO, KOMPLEK TAMAN SURYA III BLOK J1 NO.14, PEGADUNGAN, KALIDERES, JAKARTA BARAT | F28: 144 M2 | G28: 180 M2 | H28: Own Income | I28: 317402100302904980 | J28: 2012 | K28: 567360000 | L28: 2055312000 | M28: - | N28: 567360000 | O28: 567360000 | P28: 567360000 | Q28: 567360000 | R28: 567360000
A29: =A28+1 -> 22 | B29: =VLOOKUP(C29,$U:$V,2,0) -> 0506 | C29: TANAH DAN/ATAU BANGUNAN UNTUK USAHA (TOKO, PABRIK, DSB) | D29: Indonesia | E29: RUKO, KOMPLEK TAMAN SURYA III BLOK J1 NO.15, PEGADUNGAN, KALIDERES, JAKARTA BARAT | F29: 156 M2 | G29: 180 M2 | H29: Own Income | I29: 317402100302904990 | J29: 2012 | K29: 567360000 | L29: 1945260000 | M29: - | N29: 567360000 | O29: 567360000 | P29: 567360000 | Q29: 567360000 | R29: 567360000
A30: =A29+1 -> 23 | B30: =VLOOKUP(C30,$U:$V,2,0) -> 0506 | C30: TANAH DAN/ATAU BANGUNAN UNTUK USAHA (TOKO, PABRIK, DSB) | D30: Indonesia | E30: RUKO, JL. MANGGA DUA RAYA BLOK F-5 NO.14, RT 03 RW 13, MANGGA DUA SELATAN, SAWAH BESAR, JAKARTA PUSAT | F30: 63 M2 | G30: 219 M2 | H30: Own Income | I30: 317306000500208340 | J30: 2016 | K30: 490500000 | L30: 3154842000 | M30: - | N30: 490500000 | O30: 490500000 | P30: 490500000 | Q30: 490500000 | R30: 490500000
A31: =A30+1 -> 24 | B31: =VLOOKUP(C31,$U:$V,2,0) -> 0506 | C31: TANAH DAN/ATAU BANGUNAN UNTUK USAHA (TOKO, PABRIK, DSB) | D31: Indonesia | E31: TOKO, JEMBATAN ITC LT.II BLOK A NO.68, ANCOL, PADEMANGAN, JAKARTA UTARA | F31: 0 M2 | G31: 16 M2 | H31: Own Income | I31: 317501100302009910 | J31: 2016 | K31: 210000000 | L31: 402015000 | M31: - | N31: 210000000 | O31: 210000000 | P31: 210000000 | Q31: 210000000 | R31: 210000000
A32: =A31+1 -> 25 | B32: =VLOOKUP(C32,$U:$V,2,0) -> 0506 | C32: TANAH DAN/ATAU BANGUNAN UNTUK USAHA (TOKO, PABRIK, DSB) | D32: Indonesia | E32: KIOS, PASAR PAGI MANGGA DUA LANTAI SB BLOK C NO.54 JAK-UT | F32: 0 M2 | G32: - | H32: Own Income | I32: - | J32: 2016 | K32: 31082000 | L32: 31082000 | M32: - | N32: 31082000 | O32: 31082000 | P32: 31082000 | Q32: 31082000 | R32: 31082000
A33: =A32+1 -> 26 | B33: =VLOOKUP(C33,$U:$V,2,0) -> 0506 | C33: TANAH DAN/ATAU BANGUNAN UNTUK USAHA (TOKO, PABRIK, DSB) | D33: Indonesia | E33: KIOS, PASAR PAGI MANGGA DUA LANTAI SB BLOK C NO.55 JAK-UT | F33: 0 M2 | G33: - | H33: Own Income | I33: - | J33: 2016 | K33: 31082000 | L33: 31082000 | M33: - | N33: 31082000 | O33: 31082000 | P33: 31082000 | Q33: 31082000 | R33: 31082000
A34: =A33+1 -> 27 | B34: =VLOOKUP(C34,$U:$V,2,0) -> 0506 | C34: TANAH DAN/ATAU BANGUNAN UNTUK USAHA (TOKO, PABRIK, DSB) | D34: Indonesia | E34: KIOS, PASAR PAGI MANGGA DUA LANTAI SB BLOK C NO.56 JAK-UT | F34: 0 M2 | G34: - | H34: Own Income | I34: - | J34: 2016 | K34: 41400000 | L34: 41400000 | M34: - | N34: 41400000 | O34: 41400000 | P34: 41400000 | Q34: 41400000 | R34: 41400000
A35: =A34+1 -> 28 | B35: =VLOOKUP(C35,$U:$V,2,0) -> 0506 | C35: TANAH DAN/ATAU BANGUNAN UNTUK USAHA (TOKO, PABRIK, DSB) | D35: Indonesia | E35: KIOS, PASAR TANAH ABANG BLOK B LANTAI L01 LOS FKS NO.056, KAMPUNG BALI, TANAH ABANG, JAKARTA PUSAT | F35: 0 M2 | G35: 5 M2 | H35: Own Income | I35: 317301000702431000 | J35: 2016 | K35: 678804500 | L35: 678804500 | M35: 326500000 | N35: 678804500 | O35: 678804500 | P35: 678804500 | Q35: 678804500 | R35: 678804500
A36: =A35+1 -> 29 | B36: =VLOOKUP(C36,$U:$V,2,0) -> 0506 | C36: TANAH DAN/ATAU BANGUNAN UNTUK USAHA (TOKO, PABRIK, DSB) | D36: Indonesia | E36: KIOS, PASAR TANAH ABANG BLOK B LANTAI L01 LOS FKS NO.057, KAMPUNG BALI, TANAH ABANG, JAKARTA PUSAT | F36: 0 M2 | G36: 4 M2 | H36: Own Income | I36: 317301000702431010 | J36: 2016 | K36: 608126200 | L36: 608126200 | M36: 293500000 | N36: 608126200 | O36: 608126200 | P36: 608126200 | Q36: 608126200 | R36: 608126200
C38: TANAH KOSONG | D38: Indonesia | E38: TANAH, DESA KEDAUNG BARAT, SEPATAN TIMUR, KAB. TANGERANG, BANTEN | F38: - | G38: 0 M2 | H38: Own Income | I38: - | J38: 2016 | K38: CLOSE | L38: CLOSE | M38: - | N38: 0 | O38: 6520000 | P38: 6520000 | Q38: 6520000 | R38: 6520000
C39: TANAH KOSONG | D39: Indonesia | E39: TANAH, DESA KEDAUNG BARAT, SEPATAN TIMUR, KAB. TANGERANG, BANTEN | F39: - | G39: 0 M2 | H39: Own Income | I39: - | J39: 2016 | K39: CLOSE | L39: CLOSE | N39: 0 | O39: 24740000 | P39: 24740000 | Q39: 24740000 | R39: 24740000
C40: TANAH KOSONG | D40: Indonesia | E40: TANAH, DESA KEDAUNG BARAT, SEPATAN TIMUR, KAB. TANGERANG, BANTEN | F40: - | G40: 0 M2 | H40: Own Income | I40: - | J40: 2016 | K40: CLOSE | L40: CLOSE | N40: 0 | O40: 29400000 | P40: 29400000 | Q40: 29400000 | R40: 29400000
C41: TANAH KOSONG | D41: Indonesia | E41: TANAH, DESA KEDAUNG BARAT, SEPATAN TIMUR, KAB. TANGERANG, BANTEN | F41: - | G41: 0 M2 | H41: Own Income | I41: - | J41: 2016 | K41: CLOSE | L41: CLOSE | N41: 0 | O41: 27740000 | P41: 27740000 | Q41: 27740000 | R41: 27740000
C42: TANAH KOSONG | D42: Indonesia | E42: TANAH, DESA KEDAUNG BARAT, SEPATAN TIMUR, KAB. TANGERANG, BANTEN | F42: - | G42: 0 M2 | H42: Own Income | I42: - | J42: 2016 | K42: CLOSE | L42: CLOSE | N42: 0 | O42: 27850000 | P42: 27850000 | Q42: 27850000 | R42: 27850000
C43: TANAH KOSONG | D43: Indonesia | E43: TANAH, DESA KEDAUNG BARAT, SEPATAN TIMUR, KAB. TANGERANG, BANTEN | F43: - | G43: 0 M2 | H43: Own Income | I43: - | J43: 2016 | K43: CLOSE | L43: CLOSE | N43: 0 | O43: 10000000 | P43: 10000000 | Q43: 10000000 | R43: 10000000
C44: TANAH KOSONG | D44: Indonesia | E44: TANAH, DESA KEDAUNG BARAT, SEPATAN TIMUR, KAB. TANGERANG, BANTEN | F44: - | G44: 0 M2 | H44: Own Income | I44: - | J44: 2016 | K44: CLOSE | L44: CLOSE | N44: 0 | O44: 41040000 | P44: 41040000 | Q44: 41040000 | R44: 41040000

Sheet HIT 2024
B1: NO. | C1: KODE | D1: NAMA HARTA | E1: TAHUN PEROLEHAN | F1: HARGA PEROLEHAN | G1: KETERANGAN
B2: 1 | C2: 061 | D2: TANAH DAN RUMAH LAMANDAU | E2: 2009 | F2: 1320000000 | G2: JALAN LAMANDAU 1 NO. 19
B3: 2 | C3: 061 | D3: APARTEMEN SERPONG MIDTOWN | E3: 2016 | F3: 1538793523 | G3: PPJB
B4: 3 | C4: 061 | D4: TANAH DAN BANGUNAN DESA LEGOK | E4: 2016 | F4: 1987500000 | G4: JL. DESA LEGOK GAOK RT. 02 RW. 05
B5: 4 | C5: 061 | D5: TANAH KELURAHAN TANJUNG DUREN SELATAN, GROGOL | E5: 2016 | F5: 350370000 | G5: 1609/XIII/CATTELYA
B6: 5 | C6: 061 | D6: TANAH DAN BANGUNAN SENTRA BUMI NIAGA SURYA GRAND | E6: 2016 | F6: 1025000000 | G6: 006/LG/PPJB-SP/XI/16 | H6: =SUM(F2:F6) -> 6221663523
B7: 6 | C7: 062 | D7: APARTEMEN LUCKY TOWER RESIDENCE | E7: 2016 | F7: 2554200000 | G7: 00004/PP-APT/SMU/III/2014
B8: 7 | C8: 043 | D8: MOBIL SMART PASSION | E8: 2010 | F8: 220000000 | G8: NO. POL : B 1660 SOE
B9: 8 | C9: 043 | D9: MOBIL BMW X5 | E9: 2020 | F9: 980000000 | G9: NO.POL : B 2523 SXP - 70600392011
B10: 9 | C10: 043 | D10: MOBIL ALPHARD | E10: 2021 | F10: 1240500000 | G10: NO. POL : B 304 DEV - 70601882111 | H10: =SUM(H6+SUM(F7:F10)) -> 11216363523
B11: 10 | C11: 051 | D11: PERHIASAN | E11: 2019 | F11: 4763000000
B12: 11 | C12: 051 | D12: PERHIASAN | E12: 2019 | F12: 87000000
B13: 12 | C13: 053 | D13: PERABOTAN DAN SENI | E13: 2019 | F13: 1086000000
B14: 13 | C14: 053 | D14: KOLEKSI UANG KUNO | E14: 2019 | F14: 360000000 | H14: =SUM(H10+SUM(F11:F14)) -> 17512363523
B15: 14 | C15: 053 | D15: PERABOTAN DAN SENI | E15: 2019 | F15: 14000000
B16: 15 | C16: 011 | D16: VALUTA ASING USD | E16: 2019 | F16: 3564000000
B17: 16 | C17: 011 | D17: VALUTA ASING AUD | E17: 2024 | F17: 504094000
B18: 17 | C18: 032 | D18: SAHAM BATAVIA LAND | E18: 2016 | F18: 5700000000 | G18: AKTA NO. 14 | H18: =SUM(H14+SUM(F15:F18)) -> 27294457523
B19: 18 | C19: 031 | D19: SAHAM PT. FAC SEKURITAS INDONESIA | E19: 2020 | F19: 86958597
B20: 19 | C20: 012 | D20: TABUNGAN | E20: 2024 | F20: 1689737 | G20: PANIN USD - 1004008898
B21: 20 | C21: 012 | D21: TABUNGAN | E21: 2024 | F21: 48293672 | G21: WELLS FARGO, USA (USD) - 3908725520
B22: 21 | C22: 012 | D22: TABUNGAN | E22: 2024 | F22: 1.008188e+08 | G22: HSBC, AUS (AUD) - 012615621118 | H22: =SUM(H18+SUM(F19:F22)) -> 27532218329
B23: 22 | C23: 012 | D23: TABUNGAN | E23: 2024 | F23: 47297325 | G23: HSBC, AUS (AUD) - 012640249090
B24: 23 | C24: 012 | D24: TABUNGAN | E24: 2024 | F24: 527718970 | G24: HSBC, AUS (USD) - 012640249090
B25: 24 | C25: 014 | D25: DEPOSITO | E25: 2024 | F25: 912979464 | G25: HSBC, AUS (AUD) - 012615621053
B26: 25 | C26: 013 | D26: TABUNGAN GIRO | E26: 2024 | F26: 5526951 | G26: HSBC, HKG (HKD) - 622168102888 | H26: =SUM(H22+SUM(F23:F26)) -> 29025741039
B27: 26 | C27: 012 | D27: TABUNGAN | E27: 2024 | F27: 20820000 | G27: HSBC, HKG (HKD) - 622168102888
B28: 27 | C28: 012 | D28: TABUNGAN | E28: 2024 | F28: 26092256 | G28: HSBC, HKG (USD) - 622168102888
B29: 28 | C29: 012 | D29: TABUNGAN | E29: 2024 | F29: 103772808 | G29: OCBC, SGP (USD) - 508013802201
B30: 29 | C30: 012 | D30: TABUNGAN | E30: 2024 | F30: 102044280 | G30: OCBC, SGP (SGD) - 6524013254 | H30: =SUM(H26+SUM(F27:F30)) -> 29278470383
B31: 30 | C31: 012 | D31: TABUNGAN | E31: 2024 | F31: 17878500 | G31: OCBC, SGP (SGD) - 6521012150
B32: 31 | C32: 012 | D32: TABUNGAN | E32: 2024 | F32: 286056000 | G32: OCBC, SGP (SGD) - 584269120001
B33: 32 | C33: 012 | D33: TABUNGAN | E33: 2024 | F33: 0 | G33: OCBC, SGP (SGD) - 584269138001
B34: 33 | C34: 014 | D34: DEPOSITO | E34: 2024 | F34: 441058879 | G34: OCBC, SGP (USD) - 508655545401 | H34: =SUM(H30+SUM(F31:F34)) -> 30023463762
B35: 34 | C35: 014 | D35: DEPOSITO | E35: 2024 | F35: 264098555 | G35: OCBC, SGP (USD) - 508655545401
B36: 35 | C36: 014 | D36: DEPOSITO | E36: 2024 | F36: 876232850 | G36: OCBC, SGP (USD) - 508655545401
B37: 36 | C37: 014 | D37: DEPOSITO | E37: 2024 | F37: 876232850 | G37: OCBC, SGP (USD) - 508655545401
B38: 37 | C38: 012 | D38: TABUNGAN | E38: 2024 | F38: 180943 | G38: PANIN - 1002000998 | H38: =SUM(H34+SUM(F35:F38)) -> 32040208960
B39: 38 | C39: 012 | D39: TABUNGAN | E39: 2024 | F39: 5272572 | G39: PANIN - 1002890077
B40: 39 | C40: 012 | D40: TABUNGAN | E40: 2024 | F40: 803897 | G40: PANIN USD - 1004307679
B41: 40 | C41: 012 | D41: TABUNGAN | E41: 2024 | F41: 3923313 | G41: MANDIRI - 10220004259296
B42: 41 | C42: 012 | D42: TABUNGAN | E42: 2024 | F42: 0 | G42: PANIN - 1032009917 | H42: =SUM(H38+SUM(F39:F42)) -> 32050208742
B43: 42 | C43: 014 | D43: DEPOSITO | E43: 2024 | F43: 172683330 | G43: PANIN - 100112016447
B44: 43 | C44: 011 | D44: UANG TUNAI | E44: 2024 | F44: 0 | G44: AKUMULASI SD 2024
B45: 44 | C45: 061 | D45: APARTEMEN - NEW SOUTH WALES, AUSTRALIA | E45: 2022 | F45: 9520453147 | G45: 812/5, JOYNTON AVENUE ZETLAND
B46: 45 | C46: 012 | D46: TABUNGAN | E46: 2024 | F46: 155917 | G46: PANIN - 1002056562 | H46: =SUM(H42+SUM(F43:F46)) -> 41743501136
B47: 46 | C47: 012 | D47: TABUNGAN | E47: 2024 | F47: 155000000 | G47: UOB - 6293035781
B48: 47 | C48: 013 | D48: TABUNGAN GIRO | E48: 2024 | F48: 1000000 | G48: UOB - 6293061006
B49: 48 | C49: 012 | D49: TABUNGAN | E49: 2024 | F49: 16178323 | G49: UOB USD - 6299004411
B50: 49 | C50: 014 | D50: DEPOSITO | E50: 2024 | F50: 522954440 | G50: UOB - 6290003714 | H50: =SUM(H46+SUM(F47:F50)) -> 42438633899
B51: 50 | C51: 014 | D51: DEPOSITO | E51: 2024 | F51: 519743666 | G51: UOB - 6290003714
B52: 51 | C52: 014 | D52: DEPOSITO | E52: 2024 | F52: 514030503 | G52: UOB - 6290003714
B53: 52 | C53: 014 | D53: DEPOSITO | E53: 2024 | F53: 136079025 | G53: PANIN - 100112011723 - MAUREEN
B54: 53 | C54: 014 | D54: DEPOSITO | E54: 2024 | F54: 0 | G54: PANIN - 100112023397 - MAUREEN | H54: =SUM(H50+SUM(F51:F54)) -> 43608487093
B55: 54 | C55: 014 | D55: DEPOSITO | E55: 2024 | F55: 310583872 | G55: PANIN - 100112027093 - MAUREEN
B56: 55 | C56: 012 | D56: TABUNGAN | E56: 2024 | F56: 51192698 | G56: PANIN - 1002059208
B57: 56 | C57: 012 | D57: TABUNGAN | E57: 2024 | F57: 308295 | G57: PANIN - 1002063444
B58: 57 | C58: 014 | D58: DEPOSITO | E58: 2024 | F58: 50536943 | G58: PANIN - 100112030335 | H58: =SUM(H54+SUM(F55:F58)) -> 44021108901
B59: 58 | C59: 014 | D59: DEPOSITO | E59: 2024 | F59: 60157808 | G59: PANIN - 100112031436
B60: 59 | C60: 014 | D60: DEPOSITO | E60: 2024 | F60: 55144657 | G60: PANIN - 100112031448
B61: 60 | C61: 014 | D61: DEPOSITO | E61: 2024 | F61: 252500000 | G61: PANIN - 100112031709
B62: 61 | C62: 014 | D62: DEPOSITO | E62: 2024 | F62: 175060064 | G62: PANIN - 100112027785 - MAUREEN | H62: =SUM(H58+SUM(F59:F62)) -> 44563971430
B63: 62 | C63: 014 | D63: DEPOSITO | E63: 2024 | F63: 436645424 | G63: PANIN - 100112031357 - MAUREEN
B64: 63 | C64: 014 | D64: DEPOSITO | E64: 2024 | F64: 1000000000 | G64: BCA - 2610261071 - DEVI TAURISA
B65: 64 | C65: 014 | D65: DEPOSITO | E65: 2024 | F65: 514030503 | G65: UOB - 629000374
B66: 65 | C66: 014 | D66: DEPOSITO | E66: 2024 | F66: 505847387 | G66: UOB - 629000374 | H66: =SUM(H62+SUM(F63:F66)) -> 47020494744
B67: 66 | C67: 014 | D67: DEPOSITO | E67: 2024 | F67: 1011694773 | G67: UOB - 629000374
B68: 67 | C68: 019 | D68: SETARA KAS LAINNYA | E68: 2024 | F68: 2500000000 | G68: AKUMULASI SD 2024
B69: 68 | C69: 021 | D69: PIUTANG | E69: 2024 | F69: 950000000 | G69: MARGARETH NICOLE
F70: =SUM(F2:F69) -> 51482189517 | H70: =SUM(H66+SUM(F67:F69)) -> 51482189517

Sheet HARTA LAINNYA
C1: 6. HARTA LAINNYA
C2: Emas Batangan/Emas Perhiasan/Permata/Barang Barang Seni dan Antik/Peralatan Elektronik/Perabot Rumah Tangga/Harta Tidak Berwujud Lainnya
C4: 3173042409640005 | D4: SINDJAJA JONANY
G5: =SUM(G8:G55) -> 6964760000 | H5: =SUM(H8:H55) -> 20319280000 | J5: =SUM(J8:J55) -> 7113010000 | K5: =SUM(K8:K55) -> 7063060000 | L5: =SUM(L8:L55) -> 7032965000 | M5: =SUM(M8:M55) -> 6927635000 | N5: =SUM(N8:N55) -> 7237655000
A6: NO | B6: KODE | C6: DESKRIPSI | D6: TAHUN PEROLEHAN | E6: BUKTI KEPEMILIKAN/NOMOR AKUN | F6: INFORMASI TAMBAHAN | G6: HARGA PEROLEHAN | H6: NILAI SAAT INI (2025) | I6: (Harta PPS/ Harta Investasi PPS) | J6: NILAI TAHUN SEBELUMNYA
J7: 2024 | K7: 2023 | L7: 2022 | M7: 2021 | N7: 2020 | P7: - | Q7: - | R7: -
A8: 1 | B8: =VLOOKUP(C8,$Q:$R,2,0) -> 0701 | C8: EMAS BATANGAN | D8: 2014 | E8: - | F8: LM & PERHIASAN | G8: 6677260000 | H8: =G8*3 -> 20031780000 | I8: - | J8: 6677260000 | K8: 6677260000 | L8: 6677260000 | M8: 6677260000 | N8: 6677260000 | P8: 0601 | Q8: PATEN | R8: 0601
A9: =A8+1 -> 2 | B9: =VLOOKUP(C9,$Q:$R,2,0) -> 0712 | C9: PERSEDIAAN USAHA | D9: 2025 | E9: - | F9: - | G9: =H9 -> 287500000 | H9: 287500000 | I9: - | J9: 435750000 | K9: 385800000 | L9: 355705000 | M9: 250375000 | N9: 560395000 | P9: 0602 | Q9: ROYALTI | R9: 0602
P10: 0603 | Q10: MEREK DAGANG | R10: 0603
P11: 0699 | Q11: HARTA TIDAK BERWUJUD LAINNYA | R11: 0699
P12: 0701 | Q12: EMAS BATANGAN | R12: 0701
P13: 0702 | Q13: EMAS PERHIASAN | R13: 0702
P14: 0703 | Q14: BATANGAN NON EMAS | R14: 0703
P15: 0704 | Q15: PERHIASAN NON EMAS | R15: 0704
P16: 0705 | Q16: PERMATA | R16: 0705
P17: 0706 | Q17: BARANG-BARANG SENI DAN ANTIK | R17: 0706
P18: 0707 | Q18: PERALATAN OLAH RAGA KHUSUS | R18: 0707
P19: 0708 | Q19: PERALATAN ELEKTRONIK | R19: 0708
P20: 0709 | Q20: PERABOT RUMAH TANGGA | R20: 0709
P21: 0710 | Q21: PERALATAN KANTOR | R21: 0710
... P23: 0712 | Q23: PERSEDIAAN USAHA | R23: 0712

Sheet HUTANG
C1: B. UTANG PAJAK PADA AKHIR TAHUN
C4: 3173042409640005 | D4: SINDJAJA JONANY
H5: =SUM(H8:H55) -> 0 | J5: =SUM(J8:J55) -> 0 | K5: =SUM(K8:K55) -> 0 | L5: =SUM(L8:L55) -> 0 | M5: =SUM(M8:M55) -> 0 | N5: =SUM(N8:N55) -> 0
A6: NO | B6: KODE | C6: DESKRIPSI | D6: KREDITUR | F6: NEGARA KREDITUR | G6: TAHUN PEMINJAMAN | H6: NILAI PIUTANG SAAT INI (2025) | I6: KETERANGAN | J6: NILAI TAHUN SEBELUMNYA
D7: NIK / NPWP | E7: NAMA | J7: 2024 | K7: 2023 | L7: 2022 | M7: 2021 | N7: 2020 | P7: - | Q7: - | R7: -
A8: 1 | B8: =VLOOKUP(C8,$Q:$R,2,0) -> - | C8: - | P8: 101 | Q8: UTANG BANK/LEMBAGA KEUANGAN BUKAN BANK | R8: 101
A9: =A8+1 -> 2 | P9: 102 | Q9: KARTU KREDIT | R9: 102
A10: =A9+1 -> 3 | P10: 103 | Q10: UTANG AFILIASI | R10: 103
A11: =A10+1 -> 4 | P11: 109 | Q11: UTANG LAINNYA | R11: 109
A12: =A11+1 -> 5
A13: =A12+1 -> 6 | Q13: Hutang
A14: =A13+1 -> 7
A15: =A14+1 -> 8
A16: =A15+1 -> 9
A17: =A16+1 -> 10
A18: =A17+1 -> 11
A19: =A18+1 -> 12
A20: =A19+1 -> 13
A21: =A20+1 -> 14
A22: =A21+1 -> 15
A23: =A22+1 -> 16
A24: =A23+1 -> 17
A25: =A24+1 -> 18
... A55: =A54+1 -> 48

Sheet OMSET
A1: Daftar Jumlah Peredaran Bruto dan Pembayaran PPh Final berdasarkan PP 55 Tahun 2022 | J1: Daftar Jumlah Peredaran Bruto dan Pembayaran PPh Final berdasarkan PP 55 Tahun 2022
A2: Per Masa Pajak Serta Dari Masing-Masing Tempat Usaha Tahun 2025 | J2: Per Masa Pajak Serta Dari Masing-Masing Tempat Usaha Tahun 2025
A5: NAMA | C5: SINDJAJA JONANY | J5: NAMA | L5: SINDJAJA JONANY
A6: NPWP | C6: 06.651.224.5-044.002 | J6: NPWP | L6: 06.651.224.5-044.001
A7: ALAMAT | C7: ITC MANGGA DUA LT. 3 BLOK. A NO. 3 JAK-UT | J7: ALAMAT | L7: PASAR PAGI MG DUA LT SEMIBASEMENT BLOK C/54-55 JAK-UT
A10: Masa | B10: Peredaran Bruto | C10: PPh Final | D10: Total Peredaran Bruto Cabang | E10: Total Peredaran Bruto Akum 2 Cabang | F10: Perhitungan Pengurangan | G10: PPh Final Harus Dibayar | H10: Paraf | J10: Masa | K10: Peredaran Bruto | L10: PPh Final | M10: Total Peredaran Bruto Cabang | N10: Total Peredaran Bruto Akum 2 Cabang | O10: Perhitungan Pengurangan | P10: PPh Final Harus Dibayar | Q10: Paraf | T10: Bulan | U10: Omset | V10: PPh Final | W10: Total Peredaran Bruto | X10: Perhitungan Pengurangan | Y10: PPh Final Harus Dibayar
A11: Januari | B11: 115180000 | C11: =B11/200 -> 575900 | D11: =+B11 -> 115180000 | E11: =D11 -> 115180000 | F11: =E11-500000000 -> -384820000 | G11: =IF(E11<500000000,"FREE",IF(F11="FREE",F11/200,C11)) -> FREE | J11: Januari | K11: 126980000 | L11: =K11/200 -> 634900 | M11: =+K11 -> 126980000 | N11: =E11+M11 -> 242160000 | O11: =N11-500000000 -> -257840000 | P11: =IF(M11<500000000,"FREE",IF(P10="FREE",O11/200,L11)) -> FREE | T11: 1 | U11: =B11+K11 -> 242160000 | V11: =C11+L11 -> 1210800 | W11: =U11 -> 242160000 | X11: =+W11-500000000 -> -257840000 | Y11: FREE
A12: Februari | B12: 46620000 | C12: =B12/200 -> 233100 | D12: =+D11+B12 -> 161800000 | E12: =N11+B12 -> 288780000 | F12: =E12-500000000 -> -211220000 | G12: =IF(E12<500000000,"FREE",IF(F12="FREE",F12/200,C12)) -> FREE | J12: Februari | K12: 57220000 | L12: =K12/200 -> 286100 | M12: =+M11+K12 -> 184200000 | N12: =E12+K12 -> 346000000 | O12: =N12-500000000 -> -154000000 | P12: =IF(N12<500000000,"FREE",IF(O12="FREE",O12/200,L12)) -> FREE | T12: 2 | U12: =B12+K12 -> 103840000 | V12: =C12+L12 -> 519200 | W12: =U12+W11 -> 346000000 | X12: =+W12-500000000 -> -154000000 | Y12: =IF(W12<500000000,"FREE",IF(Y11="FREE",X12/200,V12)) -> FREE
A13: Maret | B13: 49120000 | C13: =B13/200 -> 245600 | D13: =+D12+B13 -> 210920000 | E13: =N12+B13 -> 395120000 | F13: =E13-500000000 -> -104880000 | G13: =IF(E13<500000000,"FREE",IF(F13="FREE",F13/200,C13)) -> FREE | J13: Maret | K13: 71720000 | L13: =K13/200 -> 358600 | M13: =+M12+K13 -> 255920000 | N13: =E13+K13 -> 466840000 | O13: =N13-500000000 -> -33160000 | P13: =IF(M13<500000000,"FREE",IF(P12="FREE",O13/200,L13)) -> FREE | T13: 3 | U13: =B13+K13 -> 120840000 | V13: =C13+L13 -> 604200 | W13: =U13+W12 -> 466840000 | X13: =+W13-500000000 -> -33160000 | Y13: =IF(W13<500000000,"FREE",IF(Y12="FREE",X13/200,V13)) -> FREE
A14: April | B14: 134080000 | C14: =B14/200 -> 670400 | D14: =+D13+B14 -> 345000000 | F14: =E14-500000000 -> -500000000 | G14: =367000 -> 367000 | J14: April | K14: 152480000 | L14: =K14/200 -> 762400 | M14: =+M13+K14 -> 408400000 | N14: =E14+K14 -> 152480000 | O14: =N14-500000000 -> -347520000 | P14: =900000 -> 900000 | T14: 4 | U14: =B14+K14 -> 286560000 | V14: =C14+L14 -> 1432800 | W14: =U14+W13 -> 753400000 | X14: =+W14-500000000 -> 253400000 | Y14: =IF(W14<500000000,"FREE",IF(Y13="FREE",X14/200,V14)) -> 1267000
A15: Mei | B15: 147560000 | C15: =B15/200 -> 737800 | D15: =+D14+B15 -> 492560000 | F15: =E15-500000000 -> -500000000 | G15: =C15 -> 737800 | J15: Mei | K15: 160360000 | L15: =K15/200 -> 801800 | M15: =+M14+K15 -> 568760000 | N15: =E15+K15 -> 160360000 | O15: =N15-500000000 -> -339640000 | P15: =L15 -> 801800 | T15: 5 | U15: =B15+K15 -> 307920000 | V15: =C15+L15 -> 1539600 | W15: =U15+W14 -> 1061320000 | X15: =+W15-500000000 -> 561320000 | Y15: =IF(W15<500000000,"FREE",IF(Y14="FREE",X15/200,V15)) -> 1539600
A16: Juni | B16: 142240000 | C16: =B16/200 -> 711200 | D16: =+D15+B16 -> 634800000 | F16: =E16-500000000 -> -500000000 | G16: =C16 -> 711200 | J16: Juni | K16: 157040000 | L16: =K16/200 -> 785200 | M16: =+M15+K16 -> 725800000 | N16: =E16+K16 -> 157040000 | O16: =N16-500000000 -> -342960000 | P16: =L16 -> 785200 | T16: 6 | U16: =B16+K16 -> 299280000 | V16: =C16+L16 -> 1496400 | W16: =U16+W15 -> 1360600000 | X16: =+W16-500000000 -> 860600000 | Y16: =IF(W16<500000000,"FREE",IF(Y15="FREE",X16/200,V16)) -> 1496400
A17: Juli | B17: 156700000 | C17: =B17/200 -> 783500 | D17: =+D16+B17 -> 791500000 | F17: =E17-500000000 -> -500000000 | G17: =C17 -> 783500 | J17: Juli | K17: 172900000 | L17: =K17/200 -> 864500 | M17: =+M16+K17 -> 898700000 | N17: =E17+K17 -> 172900000 | O17: =N17-500000000 -> -327100000 | P17: =L17 -> 864500 | T17: 7 | U17: =B17+K17 -> 329600000 | V17: =C17+L17 -> 1648000 | W17: =U17+W16 -> 1690200000 | X17: =+W17-500000000 -> 1190200000 | Y17: =IF(W17<500000000,"FREE",IF(Y16="FREE",X17/200,V17)) -> 1648000
A18: Agustus | B18: 138860000 | C18: =B18/200 -> 694300 | D18: =+D17+B18 -> 930360000 | F18: =E18-500000000 -> -500000000 | G18: =C18 -> 694300 | J18: Agustus | K18: 121260000 | L18: =K18/200 -> 606300 | M18: =+M17+K18 -> 1019960000 | N18: =E18+K18 -> 121260000 | O18: =N18-500000000 -> -378740000 | P18: =L18 -> 606300 | T18: 8 | U18: =B18+K18 -> 260120000 | V18: =C18+L18 -> 1300600 | W18: =U18+W17 -> 1950320000 | X18: =+W18-500000000 -> 1450320000 | Y18: =IF(W18<500000000,"FREE",IF(Y17="FREE",X18/200,V18)) -> 1300600
A19: September | B19: 172940000 | C19: =B19/200 -> 864700 | D19: =+D18+B19 -> 1103300000 | F19: =E19-500000000 -> -500000000 | G19: =C19 -> 864700 | J19: September | K19: 159540000 | L19: =K19/200 -> 797700 | M19: =+M18+K19 -> 1179500000 | N19: =E19+K19 -> 159540000 | O19: =N19-500000000 -> -340460000 | P19: =L19 -> 797700 | T19: 9 | U19: =B19+K19 -> 332480000 | V19: =C19+L19 -> 1662400 | W19: =U19+W18 -> 2282800000 | X19: =+W19-500000000 -> 1782800000 | Y19: =IF(W19<500000000,"FREE",IF(Y18="FREE",X19/200,V19)) -> 1662400
A20: Oktober | B20: 164220000 | C20: =B20/200 -> 821100 | D20: =+D19+B20 -> 1267520000 | F20: =E20-500000000 -> -500000000 | G20: =C20 -> 821100 | J20: Oktober | K20: 151620000 | L20: =K20/200 -> 758100 | M20: =+M19+K20 -> 1331120000 | N20: =E20+K20 -> 151620000 | O20: =N20-500000000 -> -348380000 | P20: =L20 -> 758100 | T20: 10 | U20: =B20+K20 -> 315840000 | V20: =C20+L20 -> 1579200 | W20: =U20+W19 -> 2598640000 | X20: =+W20-500000000 -> 2098640000 | Y20: =IF(W20<500000000,"FREE",IF(Y19="FREE",X20/200,V20)) -> 1579200
A21: November | B21: 180980000 | C21: =B21/200 -> 904900 | D21: =+D20+B21 -> 1448500000 | F21: =E21-500000000 -> -500000000 | G21: =C21 -> 904900 | J21: November | K21: 166980000 | L21: =K21/200 -> 834900 | M21: =+M20+K21 -> 1498100000 | N21: =E21+K21 -> 166980000 | O21: =N21-500000000 -> -333020000 | P21: =L21 -> 834900 | T21: 11 | U21: =B21+K21 -> 347960000 | V21: =C21+L21 -> 1739800 | W21: =U21+W20 -> 2946600000 | Y21: =IF(W21<500000000,"FREE",IF(Y20="FREE",X21/200,V21)) -> 1739800
A22: Desember | B22: 171880000 | C22: =B22/200 -> 859400 | D22: =+D21+B22 -> 1620380000 | F22: =E22-500000000 -> -500000000 | G22: =C22 -> 859400 | J22: Desember | K22: 158680000 | L22: =K22/200 -> 793400 | M22: =+M21+K22 -> 1656780000 | N22: =E22+K22 -> 158680000 | O22: =N22-500000000 -> -341320000 | P22: =L22 -> 793400 | T22: 12 | U22: =B22+K22 -> 330560000 | V22: =C22+L22 -> 1652800 | W22: =U22+W21 -> 3277160000 | Y22: =IF(W22<500000000,"FREE",IF(Y21="FREE",X22/200,V22)) -> 1652800
A23: Total | B23: =+SUM(B11:B22) -> 1620380000 | C23: =+SUM(C11:C22) -> 8101900 | D23: =IF(D22=B23,"-","ERROR") -> - | F23: - | G23: =SUM(G11:G22) -> 6743900 | H23: - | J23: Total | K23: =+SUM(K11:K22) -> 1656780000 | L23: =+SUM(L11:L22) -> 8283900 | M23: =IF(M22=K23,"-","ERROR") -> - | O23: - | P23: =SUM(P11:P22) -> 7141900 | Q23: - | T23: Total | U23: =SUM(U11:U22) -> 3277160000 | V23: =SUM(V11:V22) -> 16385800 | Y23: =SUM(Y11:Y22) -> 13885800

Sheet PPN
A1: NPWP Penjual | B1: Nama Penjual | C1: Nomor Faktur Pajak | D1: Tanggal Faktur Pajak | E1: Masa Pajak | F1: Tahun | G1: Masa Pajak Pengkreditkan | H1: Tahun Pajak Pengkreditan | I1: Status Faktur | J1: Harga Jual/Penggantian/DPP | K1: DPP Nilai Lain/DPP | L1: PPN | M1: PPnBM | N1: Perekam | O1: Referensi | P1: Nomor SP2D | Q1: Valid | R1: Dilaporkan | S1: Dilaporkan oleh Penjual | W1: Harga Jual/Penggantian/DPP | X1: DPP Nilai Lain/DPP | Y1: PPN

Sheet BUPOT
A1: NAMA PEMOTONG/PEMUNGUT PPh | B1: NPWP PEMOTONG/PEMUNGUT PPh | C1: NOMOR BUKTI PEMOTONGAN/PEMUNGUTAN | D1: TANGGAL BUKTI PEMOTONGAN/PEMUNGUTAN | E1: JENIS PAJAK | F1: PENGHASILAN BRUTO | G1: PPh YANG DIPOTONG/DIPUNGUT | K1: PENGHASILAN BRUTO | L1: PPh YANG DIPOTONG/DIPUNGUT
A2: BANK DBS INDONESIA | B2: 0013429402091000 | C2: 25086M5MC | D2: 45688 | E2: PPh Pasal 21 | F2: 2526316 | G2: 126316 | H2: 1 | J2: 1 | K2: =SUMIFS($F$1:$F$9,$H$1:$H$9,$J2) -> 2526316 | L2: =SUMIFS($G$1:$G$9,$H$1:$H$9,$J2) -> 126316
A3: MANULIFE ASET MANAJEMEN INDONESIA | B3: 0017703000054000 | C3: 25045L1GT | D3: 45869 | E3: PPh Pasal 21 | F3: 500000 | G3: 12500 | H3: 7 | J3: 2 | K3: =SUMIFS($F$1:$F$9,$H$1:$H$9,$J3) -> 0 | L3: =SUMIFS($G$1:$G$9,$H$1:$H$9,$J3) -> 0
A4: ASURANSI JIWA MANULIFE INDONESIA | B4: 0013825153073000 | C4: 2507KO02F | D4: 45991 | E4: PPh Pasal 21 | F4: 44393684 | G4: 2219684 | H4: 11 | J4: 3 | K4: =SUMIFS($F$1:$F$9,$H$1:$H$9,$J4) -> 0 | L4: =SUMIFS($G$1:$G$9,$H$1:$H$9,$J4) -> 0
A5: ASURANSI JIWA MANULIFE INDONESIA | B5: 0013825153073000 | C5: 2507KO00S | D5: 45991 | E5: PPh Pasal 21 | F5: 3631579 | G5: 181579 | H5: 11 | J5: 4 | K5: =SUMIFS($F$1:$F$9,$H$1:$H$9,$J5) -> 0 | L5: =SUMIFS($G$1:$G$9,$H$1:$H$9,$J5) -> 0
A6: ASURANSI JIWA MANULIFE INDONESIA | B6: 0013825153073000 | C6: 2507KO04M | D6: 45991 | E6: PPh Pasal 21 | F6: 51167368 | G6: 2558368 | H6: 11 | J6: 5 | K6: =SUMIFS($F$1:$F$9,$H$1:$H$9,$J6) -> 0 | L6: =SUMIFS($G$1:$G$9,$H$1:$H$9,$J6) -> 0
A7: ASURANSI JIWA MANULIFE INDONESIA | B7: 0013825153073000 | C7: 2507KNZRM | D7: 45991 | E7: PPh Pasal 21 | F7: 3631579 | G7: 181579 | H7: 11 | J7: 6 | K7: =SUMIFS($F$1:$F$9,$H$1:$H$9,$J7) -> 0 | L7: =SUMIFS($G$1:$G$9,$H$1:$H$9,$J7) -> 0
J8: 7 | K8: =SUMIFS($F$1:$F$9,$H$1:$H$9,$J8) -> 500000 | L8: =SUMIFS($G$1:$G$9,$H$1:$H$9,$J8) -> 12500
A9: TOTAL PPh 21 TIDAK FINAL | F9: =SUM(F2:F8) -> 105850526 | G9: =SUM(G2:G8) -> 5280026 | J9: 8 | K9: =SUMIFS($F$1:$F$9,$H$1:$H$9,$J9) -> 0 | L9: =SUMIFS($G$1:$G$9,$H$1:$H$9,$J9) -> 0
A10: NORMA 50% | F10: =F9*50% -> 52925263 | G10: =G9 -> 5280026 | J10: 9 | K10: =SUMIFS($F$1:$F$9,$H$1:$H$9,$J10) -> 0 | L10: =SUMIFS($G$1:$G$9,$H$1:$H$9,$J10) -> 0
J11: 10 | K11: =SUMIFS($F$1:$F$9,$H$1:$H$9,$J11) -> 0 | L11: =SUMIFS($G$1:$G$9,$H$1:$H$9,$J11) -> 0
A12: MG DUA JAYA | B12: 0027473420047000 | C12: 2508IHENM | D12: 46038 | E12: BP A1 | F12: 117000000 | G12: 2407500 | J12: 11 | K12: =SUMIFS($F$1:$F$9,$H$1:$H$9,$J12) -> 102824210 | L12: =SUMIFS($G$1:$G$9,$H$1:$H$9,$J12) -> 5141210
E13: Pengurang | F13: 5850000 | K13: =SUM(K2:K14) -> 13467782193505 | L13: =SUM(L2:L14) -> 671798646505
E14: Gaji | F14: =F12 -> 117000000 | G14: =G12 -> 2407500 | J14: 12 | K14: =SUMIFS($F$1:$F$9,$H$1:$H$9,$J14) -> 0 | L14: =SUMIFS($G$1:$G$9,$H$1:$H$9,$J14) -> 0
F15: =F12-F13 -> 111150000 | K15: =K13*50% -> 6.7338911e+12
F16: =SUM(F10,F15) -> 164075263 | G16: =SUM(G14,G9) -> 7687526
A24: 1 | B24: ASURANSI JIWA MANULIFE INDONESIA | C24: 13825153073000 | D24: 51167368 | E24: 0 | F24: 51167368
B25: 2 | C25: ASURANSI JIWA MANULIFE INDONESIA | D25: 13825153073000 | E25: 3631579 | F25: 0 | G25: 3631579
B26: 3 | C26: ASURANSI JIWA MANULIFE INDONESIA | D26: 13825153073000 | E26: 44393684 | F26: 0 | G26: 44393684
B27: 4 | C27: ASURANSI JIWA MANULIFE INDONESIA | D27: 13825153073000 | E27: 3631579 | F27: 0 | G27: 3631579
B28: 5 | C28: MG DUA JAYA | D28: 27473420047000 | E28: 117000000 | F28: 5850000 | G28: 111150000

Sheet BUNGA
B2: DESKRIPSI | C2: NOMOR AKUN | D2: ATAS NAMA | E2: NAMA BANK/INSTITUSI | F2: NILAI SAAT INI (2025) | G2: BUNGA 1 TAHUN (MATA UANG ASAL) | H2: BUNGA 1 TAHUN | I2: PAJAK | J2: BUNGA-PAJAK
D4: 0010003358091000 | E4: STANDARD CHARTERED BANK | F4: 479109679 | H4: 4791096.8 | I4: 479109.68 | J4: =H4-I4 -> 4311987.1 | K4: 0010003358091000
D5: 0011080454091000 | E5: BANK MEGA | F5: 4479793691 | H5: 1.0708768e+08 | I5: 10708768 | J5: =H5-I5 -> 96378912 | K5: 0011080454091000
D6: 0013084496091000 | E6: BANK CENTRAL ASIA | F6: 2298137063 | H6: 22981371 | I6: 2298137.1 | J6: =H6-I6 -> 20683234 | K6: 0013084496091000
D7: 0013121660091000 | E7: BANK PAN INDONESIA | F7: 520301174 | H7: 5203011.7 | I7: 520301.17 | J7: =H7-I7 -> 4682710.6 | K7: 0013121660091000
D8: 0013106687091000 | E8: BANK CIMB NIAGA | F8: 703053335 | H8: 7030533.4 | I8: 703053.34 | J8: =H8-I8 -> 6327480 | K8: 0013106687091000
D9: 0011049194091000 | E9: BANK OCBC NISP | F9: 282662537 | H9: 2826625.4 | I9: 282662.54 | J9: =H9-I9 -> 2543962.8 | K9: 0011049194091000
D10: 0010611739093000 | E10: BANK MANDIRI | F10: 69884414 | H10: 698844.14 | I10: 69884.414 | J10: =H10-I10 -> 628959.73 | K10: 0010611739093000
D11: 0013862420091000 | E11: BANK HSBC INDONESIA | F11: 227131466 | H11: 2271314.7 | I11: 227131.47 | J11: =H11-I11 -> 2044183.2 | K11: 0013862420091000
D12: 0013093232091000 | E12: BANK MAYBANK INDONESIA | F12: 289120215 | H12: 2891202.1 | I12: 289120.22 | J12: =H12-I12 -> 2602081.9 | K12: 0013093232091000
D13: 0013429402073000 | E13: BANK DBS INDONESIA | F13: 96981465 | H13: 969814.65 | I13: 96981.465 | J13: =H13-I13 -> 872833.19 | K13: 0013429402073000
D14: 0013084439091000 | E14: BANK UOB INDONESIA | F14: 1129652895 | H14: 11296529 | I14: 1129652.9 | J14: =H14-I14 -> 10166876 | K14: 0013084439091000
H15: =SUM(H4:H14) -> 1.6804802e+08 | I15: =SUM(I4:I14) -> 16804802 | J15: =SUM(J4:J14) -> 1.5124322e+08
B21: OBLIGASI | L21: 85
B22: DESKRIPSI | C22: TINGKAT IMBALAN | D22: JATUH TEMPO | E22: NAMA BANK/INSTITUSI | F22: NILAI SAAT INI (2025) | G22: CAPITAL GAIN | H22: IMBALAN | I22: PAJAK | J22: BUNGA-PAJAK | L22: 94
L23: =SUM(L4:L22) -> 179
H31: =SUM(H24:H30) -> 0 | I31: =SUM(I24:I30) -> 0 | J31: =SUM(J24:J30) -> 0
B32: KEUNTUNGAN PENJUALAN OBLIGASI
B33: DESKRIPSI | C33: TINGKAT IMBALAN | D33: JATUH TEMPO | E33: NAMA BANK/INSTITUSI | F33: NILAI SAAT INI (2025) | G33: CAPITAL GAIN | H33: IMBALAN | I33: PAJAK | J33: BUNGA-PAJAK
J39: =SUM(J37:J38) -> 0
B40: Total Kenaikan Harta berdasarkan Selisih Kurs
B41: DESKRIPSI | C41: NOMOR AKUN | D41: ATAS NAMA | E41: NAMA BANK/INSTITUSI | F41: SALDO 2024 (dalam mata uang asal) | G41: SALDO 2025 (dalam mata uang asal) | H41: Nilai 2024 | I41: Nilai 2025 | J41: Kurs 2024 | K41: Kurs 2025 | L41: Selisih Kurs | N41: Estimasi Bunga dalam mata uang asal | O41: Est Bunga Net | P41: Estimasi Bunga dalam mata uang Rupiah
A43: USD | B43: TABUNGAN | C43: 306812112560 | D43: ROSALINA CHANDRA | E43: STANDARD CHARTERED | F43: 3506 | G43: 436 | H43: =F43*J43 -> 56429070 | I43: =G43*K43 -> 7314772 | J43: 16095 | K43: 16777 | L43: =IF(G43<F43,G43*(K43-J43),F43*(K43-J43)) -> 297352
A44: USD | B44: TABUNGAN | C44: 010212029003270 | D44: SINDJAJA JONANY | E44: BANK MEGA | F44: 1695 | G44: 2287 | H44: =F44*J44 -> 27281025 | I44: =G44*K44 -> 38368999 | J44: 16095 | K44: 16777 | L44: =IF(G44<F44,G44*(K44-J44),F44*(K44-J44)) -> 1155990
A45: USD | B45: TABUNGAN | C45: 8740530683 | D45: SINDJAJA JONANY | E45: BANK CENTRAL ASIA | F45: 721 | G45: 16631 | H45: =F45*J45 -> 11604495 | I45: =G45*K45 -> 279018287 | J45: 16095 | K45: 16777 | L45: =IF(G45<F45,G45*(K45-J45),F45*(K45-J45)) -> 491722
A46: USD | B46: TABUNGAN | C46: 5910700598 | D46: ROSALINA CHANDRA | E46: BANK CENTRAL ASIA | F46: 19413 | G46: 10084 | H46: =F46*J46 -> 312452235 | I46: =G46*K46 -> 169179268 | J46: 16095 | K46: 16777 | L46: =IF(G46<F46,G46*(K46-J46),F46*(K46-J46)) -> 6877288
A47: USD | B47: TABUNGAN | C47: 0704400221 | D47: SINDJAJA JONANY | E47: BANK PAN INDONESIA | F47: 6222 | G47: 16730 | H47: =F47*J47 -> 100143090 | I47: =G47*K47 -> 280679210 | J47: 16095 | K47: 16777 | L47: =IF(G47<F47,G47*(K47-J47),F47*(K47-J47)) -> 4243404
A48: USD | B48: TABUNGAN | C48: 016077380800 | D48: SINDJAJA JONANY OR ROSALINA CHANDRA | E48: BANK HSBC INDONESIA | F48: 2221 | G48: 4574 | H48: =F48*J48 -> 35746995 | I48: =G48*K48 -> 76737998 | J48: 16095 | K48: 16777 | L48: =IF(G48<F48,G48*(K48-J48),F48*(K48-J48)) -> 1514722
A49: USD | B49: TABUNGAN | C49: 016075723800 | D49: SINDJAJA JONANY | E49: BANK HSBC INDONESIA | F49: 0 | G49: 14 | H49: =F49*J49 -> 0 | I49: =G49*K49 -> 234878 | J49: 16095 | K49: 16777 | L49: =IF(G49<F49,G49*(K49-J49),F49*(K49-J49)) -> 0
B50: TABUNGAN | C50: 1120239370 | D50: SINDJAJA JONANY | E50: BANK DBS INDONESIA | F50: 5636 | G50: 73 | H50: =F50*J50 -> 90711420 | I50: =G50*K50 -> 1224721 | J50: 16095 | K50: 16777 | L50: =IF(G50<F50,G50*(K50-J50),F50*(K50-J50)) -> 49786
B51: TABUNGAN | C51: 1121191105 | D51: ROSALINA CHANDRA | E51: BANK DBS INDONESIA | F51: 0 | G51: 559 | H51: =F51*J51 -> 0 | I51: =G51*K51 -> 9378343 | J51: 16095 | K51: 16777 | L51: =IF(G51<F51,G51*(K51-J51),F51*(K51-J51)) -> 0
B52: TABUNGAN | C52: 6309001432 | D52: ROSALINA CHANDRA | E52: BANK UOB INDONESIA | F52: 11 | G52: 15331 | H52: =F52*J52 -> 177045 | I52: =G52*K52 -> 257208187 | J52: 16095 | K52: 16777 | L52: =IF(G52<F52,G52*(K52-J52),F52*(K52-J52)) -> 7502
B53: TABUNGAN | C53: 6419000709 | D53: SINDJAJA JONANY | E53: BANK UOB INDONESIA | F53: 3334 | G53: 918 | H53: =F53*J53 -> 53660730 | I53: =G53*K53 -> 15401286 | J53: 16095 | K53: 16777 | L53: =IF(G53<F53,G53*(K53-J53),F53*(K53-J53)) -> 626076
B54: TABUNGAN | C54: 6419000059 | D54: SINDJAJA JONANY | E54: BANK UOB INDONESIA | F54: 0 | G54: 4374 | H54: =F54*J54 -> 0 | I54: =G54*K54 -> 73382598 | J54: 16095 | K54: 16777 | L54: =IF(G54<F54,G54*(K54-J54),F54*(K54-J54)) -> 0
B55: TABUNGAN | C55: 6309001742 | D55: ROSALINA CHANDRA | E55: BANK UOB INDONESIA | F55: 0 | G55: 4949 | H55: =F55*J55 -> 0 | I55: =G55*K55 -> 83029373 | J55: 16095 | K55: 16777 | L55: =IF(G55<F55,G55*(K55-J55),F55*(K55-J55)) -> 0
B58: REKSADANA | C58: MFI2 USD | D58: SJ | E58: Manulife USD Fixed Income Kelas A2 | F58: 0 | G58: 22298 | H58: =F58*J58 -> 0 | I58: =G58*K58 -> 374093546 | J58: 16095 | K58: 16777 | L58: =IF(G58<F58,G58*(K58-J58),F58*(K58-J58)) -> 0
B59: OBLIGASI PEMERINTAH | C59: USD INDON 34 | D59: SJ | E59: STANDARD CHARTERED BANK | F59: 0 | G59: 120000 | H59: =F59*J59 -> 0 | I59: =G59*K59 -> 2013240000 | J59: 16095 | K59: 16777 | L59: =IF(G59<F59,G59*(K59-J59),F59*(K59-J59)) -> 0
B60: OBLIGASI PEMERINTAH | C60: USD INDOIS 27 | D60: SJ | E60: BANK MEGA | F60: 0 | G60: 200000 | H60: =F60*J60 -> 0 | I60: =G60*K60 -> 3355400000 | J60: 16095 | K60: 16777 | L60: =IF(G60<F60,G60*(K60-J60),F60*(K60-J60)) -> 0
B61: OBLIGASI PEMERINTAH | C61: Obligasi INDOIS 30 USD $200.000, 2024 $41.443 | D61: RC | E61: BANK CENTRAL ASIA | F61: 41443 | G61: 41389 | H61: =F61*J61 -> 667025085 | I61: =G61*K61 -> 694383253 | J61: 16095 | K61: 16777 | L61: =IF(G61<F61,G61*(K61-J61),F61*(K61-J61)) -> 28227298
B62: OBLIGASI PEMERINTAH | C62: Obligasi INDON 27NN USD $344.868 | D62: RC | E62: BANK CENTRAL ASIA | F62: 344868 | G62: 355380 | H62: =F62*J62 -> 5550650460 | I62: =G62*K62 -> 5962210260 | J62: 16095 | K62: 16777 | L62: =IF(G62<F62,G62*(K62-J62),F62*(K62-J62)) -> 235199976
B63: OBLIGASI PEMERINTAH | C63: Obligasi INDON 32 USD $100.000, 2024 USD $94,885 | D63: SJ | E63: BANK CENTRAL ASIA | F63: 94885 | G63: 109500 | H63: =F63*J63 -> 1527174075 | I63: =G63*K63 -> 1837081500 | J63: 16095 | K63: 16777 | L63: =IF(G63<F63,G63*(K63-J63),F63*(K63-J63)) -> 64711570
... B78: OBLIGASI PEMERINTAH | C78: Obligasi USD BNI 26 | D78: SJ | E78: BANK PAN INDONESIA | F78: 0 | G78: 180000 | H78: =F78*J78 -> 0 | I78: =G78*K78 -> 3019860000 | J78: 16095 | K78: 16777 | L78: =IF(G78<F78,G78*(K78-J78),F78*(K78-J78)) -> 0
B79: OBLIGASI PEMERINTAH | C79: OBLIGASI USD INDON 48 $171150 | D79: SJ | E79: BANK HSBC INDONESIA | F79: 171150 | G79: 174720 | H79: 2754659250 | I79: =G79*K79 -> 2931277440 | J79: 16095 | K79: 16777 | L79: =IF(G79<F79,G79*(K79-J79),F79*(K79-J79)) -> 116724300
B80: OBLIGASI PEMERINTAH | C80: OBLIGASI USD INDON 52 | D80: SJ | E80: BANK HSBC INDONESIA | F80: 0 | G80: 159600 | H80: 0 | I80: =G80*K80 -> 2677609200 | J80: 16095 | K80: 16777 | L80: =IF(G80<F80,G80*(K80-J80),F80*(K80-J80)) -> 0
B81: OBLIGASI PEMERINTAH | C81: USD INDON 42 - $134.691 | D81: SJ | E81: BANK DBS INDONESIA | F81: 134691 | G81: 42800 | H81: 2167851645 | I81: =G81*K81 -> 718055600 | J81: 16095 | K81: 16777 | L81: =IF(G81<F81,G81*(K81-J81),F81*(K81-J81)) -> 29189600
B82: UNIT LINK DI ASURANSI | C82: Asuransi MWO USD | D82: RC | E82: BANK DBS INDONESIA | F82: 0 | G82: 29595 | H82: 0 | I82: =G82*K82 -> 496515315 | J82: 16095 | K82: 16777 | L82: =IF(G82<F82,G82*(K82-J82),F82*(K82-J82)) -> 0
B83: OBLIGASI PEMERINTAH | C83: Obligasi USD INDON 42 | D83: RC | E83: BANK DBS INDONESIA | F83: 0 | G83: 66878 | H83: 0 | I83: =G83*K83 -> 1122012206 | J83: 16095 | K83: 16777 | L83: =IF(G83<F83,G83*(K83-J83),F83*(K83-J83)) -> 0
B84: OBLIGASI PEMERINTAH | C84: Obligasi USD INDON 45 | D84: RC | E84: BANK DBS INDONESIA | F84: 0 | G84: 141200 | H84: 0 | I84: =G84*K84 -> 2368912400 | J84: 16095 | K84: 16777 | L84: =IF(G84<F84,G84*(K84-J84),F84*(K84-J84)) -> 0
B85: OBLIGASI PEMERINTAH | C85: Obligasi USD INDON 47 | D85: RC | E85: BANK DBS INDONESIA | F85: 0 | G85: 150350 | H85: 0 | I85: =G85*K85 -> 2522421950 | J85: 16095 | K85: 16777 | L85: =IF(G85<F85,G85*(K85-J85),F85*(K85-J85)) -> 0
B86: OBLIGASI PEMERINTAH | C86: Citibank - Obligasi Pemerintah INDON 42 USD $310.000, 2022 - $492.660, 2024 $527.799 | D86: SJ | E86: BANK UOB INDONESIA | F86: 527799 | G86: 522291 | H86: 8494924905 | I86: =G86*K86 -> 8762476107 | J86: 16095 | K86: 16777 | L86: =IF(G86<F86,G86*(K86-J86),F86*(K86-J86)) -> 356202462
B87: OBLIGASI PEMERINTAH | C87: Citibank - Obligasi Pemerintah USD INDON 37 USD $250.000 | D87: RC | E87: BANK UOB INDONESIA | F87: 250000 | G87: 185123 | H87: 4023750000 | I87: =G87*K87 -> 3105808571 | J87: 16095 | K87: 16777 | L87: =IF(G87<F87,G87*(K87-J87),F87*(K87-J87)) -> 126253886
B88: OBLIGASI PEMERINTAH | C88: Citibank Singapore - Invesment Fund 841879901 USD $150.000 | D88: RC | E88: BANK UOB INDONESIA | F88: 143942.22 | G88: 150000 | H88: 2316750000 | I88: =G88*K88 -> 2516550000 | J88: 16095 | K88: 16777 | L88: =IF(G88<F88,G88*(K88-J88),F88*(K88-J88)) -> 98168593
B89: OBLIGASI PEMERINTAH | C89: UOB - Obligasi USD INDON 47 $60.000 | D89: SJ | E89: BANK UOB INDONESIA | F89: 60000 | G89: 59464 | H89: 965700000 | I89: =G89*K89 -> 997627528 | J89: 16095 | K89: 16777 | L89: =IF(G89<F89,G89*(K89-J89),F89*(K89-J89)) -> 40554448
B90: OBLIGASI PEMERINTAH | C90: Obligasi USD INDON 30N | D90: RC | E90: BANK UOB INDONESIA | F90: 0 | G90: 61226 | H90: 0 | I90: =G90*K90 -> 1027188602 | J90: 16095 | K90: 16777 | L90: =IF(G90<F90,G90*(K90-J90),F90*(K90-J90)) -> 0
B91: OBLIGASI PEMERINTAH | C91: Obligasi USD INDON 42 | D91: RC | E91: BANK UOB INDONESIA | F91: 0 | G91: 105988 | H91: 0 | I91: =G91*K91 -> 1778160676 | J91: 16095 | K91: 16777 | L91: =IF(G91<F91,G91*(K91-J91),F91*(K91-J91)) -> 0
B93: Total Kenaikan Harta berdasarkan Selisih Kurs | F93: =SUM(F43:F77) -> 1162825 | G93: =SUM(G43:G92) -> 4931770 | H93: =SUM(H43:H77) -> 18715668375 | I93: =SUM(I43:I92) -> 82740305290 | L93: =SUM(L43:L92) -> 1.4916453e+09
D96: currency for upload | E96: currency MENKEU
B97: 1. Rp 16.777,00 Untuk dolar Amerika Serikat (USD) 1,- | C97: USD | D97: =ROUNDDOWN(E97,0) -> 16777 | E97: 16777
C98: IDR | D98: 1 | E98: 1
B100: Cash Dividend
B101: Akun | C101: Payment Date | D101: Symbol | E101: Quantity (shares) | F101: Dividend | G101: Amount
B102: 0010016087093000 | C102: 45672 | D102: BBRI | E102: =G102/F102 -> 40000 | F102: 135 | G102: 5400000 | H102: 0010016087093000
B103: 0023992449091000 | C103: 45672 | D103: ADRO | E103: =G103/F103 -> 75000 | F103: 106.84 | G103: 8013000 | H103: 0023992449091000
B104: 0013084496091000 | C104: 45758 | D104: BBCA | E104: =G104/F104 -> 145000 | F104: 250 | G104: 36250000 | H104: 0013084496091000
B105: 0010016087093000 | C105: 45770 | D105: BBRI | E105: =G105/F105 -> 40000 | F105: 208.4 | G105: 8336000 | H105: 0010016087093000
B106: 0010016061093000 | C106: 45772 | D106: BBNI | E106: 40330 | F106: 374.06 | G106: 15086486 | H106: 0010016061093000
B107: 0010005411091000 | C107: 45824 | D107: INCO | E107: =G107/F107 -> 40000 | F107: 53.4 | G107: 2136000 | H107: 0010005411091000
B108: 0010000131093000 | C108: 45828 | D108: TLKM | E108: 180000 | F108: 212.47 | G108: 38243972 | H108: 0010000131093000
B109: 0023992449091000 | C109: 45834 | D109: ADRO | E109: =G109/F109 -> 75000 | F109: 166.69 | G109: 12501750 | H109: 0023992449091000
B110: 0010000511051000 | C110: 45840 | D110: PGAS | E110: 30000 | F110: 182.08 | G110: 5462431 | H110: 0010000511051000
B111: 0012211272054000 | C111: 45847 | D111: BUDI | E111: =G111/F111 -> 500000 | F111: 2 | G111: 1000000 | H111: 0012211272054000
B112: 0010005668092000 | C112: 45856 | D112: INKP | E112: =G112/F112 -> 50000 | F112: 50 | G112: 2500000 | H112: 0010005668092000
B113: 0010017523092000 | C113: 45856 | D113: LSIP | E113: =G113/F113 -> 50000 | F113: 65 | G113: 3250000 | H113: 0010017523092000
B114: 0012211272054000 | C114: 46002 | D114: BUDI | E114: =G114/F114 -> 500000 | F114: 7 | G114: 3500000 | H114: 0012211272054000
B115: 0013452768092000 | C115: 46002 | D115: EXCL | E115: =G115/F115 -> 1063 | F115: 159 | G115: 169017 | H115: 0013452768092000
B116: 0013084496091000 | C116: 22/12/2025 | D116: BBCA | E116: =G116/F116 -> 145000 | F116: 55 | G116: 7975000 | H116: 0013084496091000
G117: =SUM(G102:G116) -> 149823656

Sheet RECAP
B1: DASHBOARD
B2: POINT | C2: 2024 | D2: 2025 DJP | E2: 2025 CTX
B3: KAS | C3: =KAS!N$5 -> 14579487152 | D3: =KAS!J$5 -> 11475827934 | E3: =KAS!J$5 -> 11475827934 | G3: PERUSAHAAN | H3: KODE | I3: KAS | K3: INVEST | M3: TOTAL
B4: PIUTANG | C4: =PIUTANG!K$5 -> 0 | D4: =PIUTANG!I$5 -> 0 | E4: =PIUTANG!I$5 -> 0 | I4: 2024 | J4: 2025 | K4: 2024 | L4: 2025 | M4: 2024 | N4: 2025
B5: INVEST | C5: =INVEST!P$5 -> 157557581602 | D5: =INVEST!J$5 -> 229892184504 | E5: =INVEST!L$5 -> 230091984504 | G5: STANDARD CHARTERED BANK | H5: SC | I5: =SUMIFS(KAS!$N$8:$N$211,KAS!$F$8:$F$211,$G5) -> 271005371 | J5: =SUMIFS(KAS!$J$8:$J$211,KAS!$F$8:$F$211,$G5) -> 479109679 | K5: =SUMIFS(INVEST!$P$8:$P$215,INVEST!$H$8:$H$215,RECAP!$H5) -> 6385118067 | L5: =SUMIFS(INVEST!$J$8:$J$215,INVEST!$H$8:$H$215,RECAP!$H5) -> 30768099335 | M5: =SUM(I5,K5) -> 6656123438 | N5: =SUM(J5,L5) -> 31247209014
B6: HARTA BERGERAK | C6: ='HARTA BERGERAK'!M$5 -> 2287500000 | D6: ='HARTA BERGERAK'!J$5 -> 1858000000 | E6: ='HARTA BERGERAK'!K$5 -> 1251300000 | G6: BANK MEGA | H6: MG | I6: =SUMIFS(KAS!$N$8:$N$211,KAS!$F$8:$F$211,$G6) -> 4775316278 | J6: =SUMIFS(KAS!$J$8:$J$211,KAS!$F$8:$F$211,$G6) -> 4479793691 | K6: =SUMIFS(INVEST!$P$8:$P$215,INVEST!$H$8:$H$215,RECAP!$H6) -> 3619000000 | L6: =SUMIFS(INVEST!$J$8:$J$215,INVEST!$H$8:$H$215,RECAP!$H6) -> 3355400000 | M6: =SUM(I6,K6) -> 8394316278 | N6: =SUM(J6,L6) -> 7835193691
B7: HARTA TIDAK BERGERAK | C7: ='HARTA TIDAK BERGERAK'!N$5 -> 21454481063 | D7: ='HARTA TIDAK BERGERAK'!K$5 -> 21454481063 | E7: ='HARTA TIDAK BERGERAK'!L$5 -> 57938723564 | G7: BANK CENTRAL ASIA | H7: BCA | I7: =SUMIFS(KAS!$N$8:$N$211,KAS!$F$8:$F$211,$G7) -> 2616448367 | J7: =SUMIFS(KAS!$J$8:$J$211,KAS!$F$8:$F$211,$G7) -> 2298137063 | K7: =SUMIFS(INVEST!$P$8:$P$215,INVEST!$H$8:$H$215,RECAP!$H7) -> 39884712270 | L7: =SUMIFS(INVEST!$J$8:$J$215,INVEST!$H$8:$H$215,RECAP!$H7) -> 52573788229 | M7: =SUM(I7,K7) -> 42501160637 | N7: =SUM(J7,L7) -> 54871925292
B8: HARTA LAINNYA | C8: ='HARTA LAINNYA'!J$5 -> 7113010000 | D8: ='HARTA LAINNYA'!G$5 -> 6964760000 | E8: ='HARTA LAINNYA'!H$5 -> 20319280000 | G8: BANK PAN INDONESIA | H8: PAN | I8: =SUMIFS(KAS!$N$8:$N$211,KAS!$F$8:$F$211,$G8) -> 179521963 | J8: =SUMIFS(KAS!$J$8:$J$211,KAS!$F$8:$F$211,$G8) -> 520301174 | K8: =SUMIFS(INVEST!$P$8:$P$215,INVEST!$H$8:$H$215,RECAP!$H8) -> 34499750000 | L8: =SUMIFS(INVEST!$J$8:$J$215,INVEST!$H$8:$H$215,RECAP!$H8) -> 33958010000 | M8: =SUM(I8,K8) -> 34679271963 | N8: =SUM(J8,L8) -> 34478311174
B9: TOTAL HARTA | C9: =SUM(C3:C8) -> 202992059817 | D9: =SUM(D3:D8) -> 271645253501 | E9: =SUM(E3:E8) -> 321077116002 | F9: total harta dan hutang | G9: BANK CIMB NIAGA | H9: CIMB | I9: =SUMIFS(KAS!$N$8:$N$211,KAS!$F$8:$F$211,$G9) -> 3833567707 | J9: =SUMIFS(KAS!$J$8:$J$211,KAS!$F$8:$F$211,$G9) -> 703053335 | K9: =SUMIFS(INVEST!$P$8:$P$215,INVEST!$H$8:$H$215,RECAP!$H9) -> 1100000000 | L9: =SUMIFS(INVEST!$J$8:$J$215,INVEST!$H$8:$H$215,RECAP!$H9) -> 6862623126 | M9: =SUM(I9,K9) -> 4933567707 | N9: =SUM(J9,L9) -> 7565676461
B10: TOTAL HUTANG | C10: =HUTANG!J$5 -> 0 | D10: =HUTANG!H5 -> 0 | E10: =D10 -> 0 | G10: BANK OCBC NISP | H10: OCBC | I10: =SUMIFS(KAS!$N$8:$N$211,KAS!$F$8:$F$211,$G10) -> 225113597 | J10: =SUMIFS(KAS!$J$8:$J$211,KAS!$F$8:$F$211,$G10) -> 282662537 | K10: =SUMIFS(INVEST!$P$8:$P$215,INVEST!$H$8:$H$215,RECAP!$H10) -> 1000000000 | L10: =SUMIFS(INVEST!$J$8:$J$215,INVEST!$H$8:$H$215,RECAP!$H10) -> 1000000000 | M10: =SUM(I10,K10) -> 1225113597 | N10: =SUM(J10,L10) -> 1282662537
B11: NET | C11: =C9-C10 -> 202992059817 | D11: =D9-D10 -> 271645253501 | E11: =E9-E10 -> 321077116002 | G11: BANK MANDIRI | H11: MDRI | I11: =SUMIFS(KAS!$N$8:$N$211,KAS!$F$8:$F$211,$G11) -> 131871464 | J11: =SUMIFS(KAS!$J$8:$J$211,KAS!$F$8:$F$211,$G11) -> 69884414 | K11: =SUMIFS(INVEST!$P$8:$P$215,INVEST!$H$8:$H$215,RECAP!$H11) -> 0 | L11: =SUMIFS(INVEST!$J$8:$J$215,INVEST!$H$8:$H$215,RECAP!$H11) -> 0 | M11: =SUM(I11,K11) -> 131871464 | N11: =SUM(J11,L11) -> 69884414
C12: =C9+C27-C39 -> 2.1723273e+11 | D12: =C12-D9 -> -5.4412527e+10 | G12: BANK HSBC INDONESIA | H12: HSBC | I12: =SUMIFS(KAS!$N$8:$N$211,KAS!$F$8:$F$211,$G12) -> 50013915 | J12: =SUMIFS(KAS!$J$8:$J$211,KAS!$F$8:$F$211,$G12) -> 227131466 | K12: =SUMIFS(INVEST!$P$8:$P$215,INVEST!$H$8:$H$215,RECAP!$H12) -> 18689385072 | L12: =SUMIFS(INVEST!$J$8:$J$215,INVEST!$H$8:$H$215,RECAP!$H12) -> 28748005396 | M12: =SUM(I12,K12) -> 18739398987 | N12: =SUM(J12,L12) -> 28975136862
C13: 257411554758 | D13: =D9-C9 -> 68653193684 | E13: 86598327637 | G13: SINARMAS ASET MGMT | H13: SMAS | I13: =SUMIFS(KAS!$N$8:$N$211,KAS!$F$8:$F$211,$G13) -> 0 | J13: =SUMIFS(KAS!$J$8:$J$211,KAS!$F$8:$F$211,$G13) -> 0 | K13: =SUMIFS(INVEST!$P$8:$P$215,INVEST!$H$8:$H$215,RECAP!$H13) -> 914048481 | L13: =SUMIFS(INVEST!$J$8:$J$215,INVEST!$H$8:$H$215,RECAP!$H13) -> 1821210544 | M13: =SUM(I13,K13) -> 914048481 | N13: =SUM(J13,L13) -> 1821210544
C14: =C13-C11 -> 54419494941 | G14: SINARMAS SEKURITAS | H14: SSEK | I14: =SUMIFS(KAS!$N$8:$N$211,KAS!$F$8:$F$211,$G14) -> 0 | J14: =SUMIFS(KAS!$J$8:$J$211,KAS!$F$8:$F$211,$G14) -> 0 | K14: =SUMIFS(INVEST!$P$8:$P$215,INVEST!$H$8:$H$215,RECAP!$H14) -> 1770860000 | L14: =SUMIFS(INVEST!$J$8:$J$215,INVEST!$H$8:$H$215,RECAP!$H14) -> 3657152090 | M14: =SUM(I14,K14) -> 1770860000 | N14: =SUM(J14,L14) -> 3657152090
B15: Omset UMKM | C15: =OMSET!U23 -> 3277160000 | G15: BANK MAYBANK INDONESIA | H15: MAY | I15: =SUMIFS(KAS!$N$8:$N$211,KAS!$F$8:$F$211,$G15) -> 11225950 | J15: =SUMIFS(KAS!$J$8:$J$211,KAS!$F$8:$F$211,$G15) -> 289120215 | K15: =SUMIFS(INVEST!$P$8:$P$215,INVEST!$H$8:$H$215,RECAP!$H15) -> 12380000000 | L15: =SUMIFS(INVEST!$J$8:$J$215,INVEST!$H$8:$H$215,RECAP!$H15) -> 10140000000 | M15: =SUM(I15,K15) -> 12391225950 | N15: =SUM(J15,L15) -> 10429120215
A16: 0.3 | B16: Est. Margin UMKM (30%) | C16: =C15*A16 -> 983148000 | G16: BANK DBS INDONESIA | H16: DBS | I16: =SUMIFS(KAS!$N$8:$N$211,KAS!$F$8:$F$211,$G16) -> 116829497 | J16: =SUMIFS(KAS!$J$8:$J$211,KAS!$F$8:$F$211,$G16) -> 96981465 | K16: =SUMIFS(INVEST!$P$8:$P$215,INVEST!$H$8:$H$215,RECAP!$H16) -> 12102305545 | L16: =SUMIFS(INVEST!$J$8:$J$215,INVEST!$H$8:$H$215,RECAP!$H16) -> 31407917471 | M16: =SUM(I16,K16) -> 12219135042 | N16: =SUM(J16,L16) -> 31504898936
B17: Bayar Pajak | C17: =OMSET!Y23 -> 13885800 | G17: BANK UOB INDONESIA | H17: UOB | I17: =SUMIFS(KAS!$N$8:$N$211,KAS!$F$8:$F$211,$G17) -> 353573043 | J17: =SUMIFS(KAS!$J$8:$J$211,KAS!$F$8:$F$211,$G17) -> 1129652895 | K17: =SUMIFS(INVEST!$P$8:$P$215,INVEST!$H$8:$H$215,RECAP!$H17) -> 20689652167 | L17: =SUMIFS(INVEST!$J$8:$J$215,INVEST!$H$8:$H$215,RECAP!$H17) -> 21077228313 | M17: =SUM(I17,K17) -> 21043225210 | N17: =SUM(J17,L17) -> 22206881208
B18: Bunga | C18: 0 | G18: CITIBANK SINGAPORE | H18: CBS | I18: =SUMIFS(KAS!$N$8:$N$211,KAS!$F$8:$F$211,$G18) -> 0 | J18: =SUMIFS(KAS!$J$8:$J$211,KAS!$F$8:$F$211,$G18) -> 0 | K18: =SUMIFS(INVEST!$P$8:$P$215,INVEST!$H$8:$H$215,RECAP!$H18) -> 2316750000 | L18: =SUMIFS(INVEST!$J$8:$J$215,INVEST!$H$8:$H$215,RECAP!$H18) -> 2316750000 | M18: =SUM(I18,K18) -> 2316750000 | N18: =SUM(J18,L18) -> 2316750000
B19: Pengeluaran 45 Juta Per Bulan | C19: =MID(B19,13,2)*12*1000000 -> 540000000 | G19: Total | I19: =SUM(I5:I18) -> 12564487152 | J19: =SUM(J5:J18) -> 10575827934 | K19: =SUM(K5:K18) -> 155351581602 | L19: =SUM(L5:L18) -> 227686184504 | M19: =SUM(M5:M18) -> 167916068754 | N19: =SUM(N5:N18) -> 238262012438
B21: Perhitungan | C21: =C16-C17+C18-C19 -> 429262200 | D21: Tidak dipakai
C22: 0 | G22: Perhitungan Kasar | I22: =I19*1% -> 1.2564487e+08 | J22: =J19*1% -> 1.0575828e+08 | K22: =K19*6% -> 9.3210949e+09 | L22: =L19*6% -> 1.3661171e+10 | M22: =SUM(I22,K22) -> 9.4467398e+09 | N22: =SUM(J22,L22) -> 1.3766929e+10
G24: JIKA IMBALAN OBLIGASI
B25: Kenaikan Secara Data Rekap | C25: =D9-C9 -> 68653193684 | G25: 0.055 | K25: =K$19*$G25 -> 8.544337e+09 | L25: =L$19*$G25 -> 1.252274e+10
G26: =G25+0.25% -> 0.0575 | K26: =K$19*$G26 -> 8.9327159e+09 | L26: =L$19*$G26 -> 1.3091956e+10
B27: Sumber Penghasilan | C27: =SUM(C28:C36) -> 1.6695317e+10 | D27: DPP | E27: Pajak | G27: =G26+0.25% -> 0.06 | K27: =K$19*$G27 -> 9.3210949e+09 | L27: =L$19*$G27 -> 1.3661171e+10
B28: Gaji | C28: =D28-E28 -> 114592500 | D28: 117000000 | E28: 2407500 | G28: =G27+0.25% -> 0.0625 | K28: =K$19*$G28 -> 9.7094739e+09 | L28: =L$19*$G28 -> 1.4230387e+10
A29: OK | B29: Pasal 21 | C29: =D29-E29 -> 100570500 | D29: =BUPOT!F9 -> 105850526 | E29: =BUPOT!G9 -> 5280026 | G29: =G28+0.25% -> 0.065 | K29: =K$19*$G29 -> 1.0097853e+10 | L29: =L$19*$G29 -> 1.4799602e+10
A30: OK | B30: Sewa | C30: =D30-E30 -> 108000000 | D30: 120000000 | E30: =D30*10% -> 12000000 | G30: =G29+0.25% -> 0.0675 | K30: =K$19*$G30 -> 1.0486232e+10 | L30: =L$19*$G30 -> 1.5368817e+10
A31: OK | B31: Dividen Reinvest | C31: =BUNGA!G117 -> 149823656 | D31: =C31 -> 149823656 | E31: =D31*0% -> 0 | G31: =G30+0.25% -> 0.07 | K31: =K$19*$G31 -> 1.0874611e+10 | L31: =L$19*$G31 -> 1.5938033e+10
B32: Est. Untung Trading Saham | C32: 150000000
B33: Estimasi Kenaikan Kurs | C33: =BUNGA!L93 -> 1.4916453e+09
A34: OK | B34: Hasil Investasi | C34: =D34-E34 -> 1.3463099e+10 | D34: =SUM(I99,J99) -> 1.4958999e+10 | E34: =D34*10% -> 1.4958999e+09 | G34: Recap IDR USD
A35: OK | B35: Hasil Tabungan & Deposito | C35: =D35-E35 -> 1.3443842e+08 | D35: =O76 -> 1.6804802e+08 | E35: =P76 -> 33609605 | G35: PERUSAHAAN | H35: KODE | I35: KAS | K35: INVEST | M35: TOTAL
B36: Untung UMKM | C36: =C16 -> 983148000 | D36: =C15 -> 3277160000 | E36: =C17 -> 13885800 | I36: IDR | J36: USD | K36: IDR | L36: USD | M36: IDR | N36: USD
C37: =SUM(C28:C36) -> 1.6695317e+10 | D37: =SUM(D28:D36) -> 1.8896881e+10 | E37: =SUM(E28:E36) -> 1.5630828e+09 | G37: STANDARD CHARTERED BANK | H37: SC | I37: =SUMIFS(KAS!$J$8:$J$211,KAS!$F$8:$F$211,$G37,KAS!$H$8:$H$211,I$36) -> 471794907 | J37: =SUMIFS(KAS!$K$8:$K$211,KAS!$F$8:$F$211,$G37,KAS!$H$8:$H$211,J$36) -> 436 | K37: =SUMIFS(INVEST!$L$8:$L$215,INVEST!$H$8:$H$215,RECAP!$H37,INVEST!$I$8:$I$215,K$36) -> 28380765789 | L37: =SUMIFS(INVEST!$M$8:$M$215,INVEST!$H$8:$H$215,RECAP!$H37,INVEST!$I$8:$I$215,L$36) -> 142298 | M37: =SUM(I37,K37) -> 28852560696 | N37: =SUM(J37,L37) -> 142734
G38: BANK MEGA | H38: MG | I38: =SUMIFS(KAS!$J$8:$J$211,KAS!$F$8:$F$211,$G38,KAS!$H$8:$H$211,I$36) -> 4441424692 | J38: =SUMIFS(KAS!$K$8:$K$211,KAS!$F$8:$F$211,$G38,KAS!$H$8:$H$211,J$36) -> 2287 | K38: =SUMIFS(INVEST!$L$8:$L$215,INVEST!$H$8:$H$215,RECAP!$H38,INVEST!$I$8:$I$215,K$36) -> 0 | L38: =SUMIFS(INVEST!$M$8:$M$215,INVEST!$H$8:$H$215,RECAP!$H38,INVEST!$I$8:$I$215,L$36) -> 200000 | M38: =SUM(I38,K38) -> 4441424692 | N38: =SUM(J38,L38) -> 202287
B39: Pengeluaran | C39: =SUM(C40:C42) -> 2454650000 | G39: BANK CENTRAL ASIA | H39: BCA | I39: =SUMIFS(KAS!$J$8:$J$211,KAS!$F$8:$F$211,$G39,KAS!$H$8:$H$211,I$36) -> 1849939508 | J39: =SUMIFS(KAS!$K$8:$K$211,KAS!$F$8:$F$211,$G39,KAS!$H$8:$H$211,J$36) -> 26715 | K39: =SUMIFS(INVEST!$L$8:$L$215,INVEST!$H$8:$H$215,RECAP!$H39,INVEST!$I$8:$I$215,K$36) -> 26850000000 | L39: =SUMIFS(INVEST!$M$8:$M$215,INVEST!$H$8:$H$215,RECAP!$H39,INVEST!$I$8:$I$215,L$36) -> 1533277 | M39: =SUM(I39,K39) -> 28699939508 | N39: =SUM(J39,L39) -> 1559992
B40: Biaya Hidup etc | C40: =C19 -> 540000000 | G40: BANK PAN INDONESIA | H40: PAN | I40: =SUMIFS(KAS!$J$8:$J$211,KAS!$F$8:$F$211,$G40,KAS!$H$8:$H$211,I$36) -> 239621964 | J40: =SUMIFS(KAS!$K$8:$K$211,KAS!$F$8:$F$211,$G40,KAS!$H$8:$H$211,J$36) -> 16730 | K40: =SUMIFS(INVEST!$L$8:$L$215,INVEST!$H$8:$H$215,RECAP!$H40,INVEST!$I$8:$I$215,K$36) -> 15000000000 | L40: =SUMIFS(INVEST!$M$8:$M$215,INVEST!$H$8:$H$215,RECAP!$H40,INVEST!$I$8:$I$215,L$36) -> 1130000 | M40: =SUM(I40,K40) -> 15239621964 | N40: =SUM(J40,L40) -> 1146730
B41: Hibah 2 Milyar | C41: =1750000000 -> 1750000000 | G41: BANK CIMB NIAGA | H41: CIMB | I41: =SUMIFS(KAS!$J$8:$J$211,KAS!$F$8:$F$211,$G41,KAS!$H$8:$H$211,I$36) -> 703053335 | J41: =SUMIFS(KAS!$K$8:$K$211,KAS!$F$8:$F$211,$G41,KAS!$H$8:$H$211,J$36) -> 0 | K41: =SUMIFS(INVEST!$L$8:$L$215,INVEST!$H$8:$H$215,RECAP!$H41,INVEST!$I$8:$I$215,K$36) -> 6862623126 | L41: =SUMIFS(INVEST!$M$8:$M$215,INVEST!$H$8:$H$215,RECAP!$H41,INVEST!$I$8:$I$215,L$36) -> 0 | M41: =SUM(I41,K41) -> 7565676461 | N41: =SUM(J41,L41) -> 0
B42: Rugi Jual Kendaraan | C42: =(435000000+10000000)*37% -> 164650000 | G42: BANK OCBC NISP | H42: OCBC | I42: =SUMIFS(KAS!$J$8:$J$211,KAS!$F$8:$F$211,$G42,KAS!$H$8:$H$211,I$36) -> 282662537 | J42: =SUMIFS(KAS!$K$8:$K$211,KAS!$F$8:$F$211,$G42,KAS!$H$8:$H$211,J$36) -> 0 | K42: =SUMIFS(INVEST!$L$8:$L$215,INVEST!$H$8:$H$215,RECAP!$H42,INVEST!$I$8:$I$215,K$36) -> 1000000000 | L42: =SUMIFS(INVEST!$M$8:$M$215,INVEST!$H$8:$H$215,RECAP!$H42,INVEST!$I$8:$I$215,L$36) -> 0 | M42: =SUM(I42,K42) -> 1282662537 | N42: =SUM(J42,L42) -> 0
G43: BANK MANDIRI | H43: MDRI | I43: =SUMIFS(KAS!$J$8:$J$211,KAS!$F$8:$F$211,$G43,KAS!$H$8:$H$211,I$36) -> 69884414 | J43: =SUMIFS(KAS!$K$8:$K$211,KAS!$F$8:$F$211,$G43,KAS!$H$8:$H$211,J$36) -> 0 | K43: =SUMIFS(INVEST!$L$8:$L$215,INVEST!$H$8:$H$215,RECAP!$H43,INVEST!$I$8:$I$215,K$36) -> 0 | L43: =SUMIFS(INVEST!$M$8:$M$215,INVEST!$H$8:$H$215,RECAP!$H43,INVEST!$I$8:$I$215,L$36) -> 0 | M43: =SUM(I43,K43) -> 69884414 | N43: =SUM(J43,L43) -> 0
B44: Selisih Penghasilan-Pengeluaran | C44: =C27-C39 -> 1.4240667e+10 | G44: BANK HSBC INDONESIA | H44: HSBC | I44: =SUMIFS(KAS!$J$8:$J$211,KAS!$F$8:$F$211,$G44,KAS!$H$8:$H$211,I$36) -> 150158590 | J44: =SUMIFS(KAS!$K$8:$K$211,KAS!$F$8:$F$211,$G44,KAS!$H$8:$H$211,J$36) -> 4588 | K44: =SUMIFS(INVEST!$L$8:$L$215,INVEST!$H$8:$H$215,RECAP!$H44,INVEST!$I$8:$I$215,K$36) -> 23139118756 | L44: =SUMIFS(INVEST!$M$8:$M$215,INVEST!$H$8:$H$215,RECAP!$H44,INVEST!$I$8:$I$215,L$36) -> 334320 | M44: =SUM(I44,K44) -> 23289277346 | N44: =SUM(J44,L44) -> 338908
G45: SINARMAS ASET MGMT | H45: SMAS | I45: =SUMIFS(KAS!$J$8:$J$211,KAS!$F$8:$F$211,$G45,KAS!$H$8:$H$211,I$36) -> 0 | J45: =SUMIFS(KAS!$K$8:$K$211,KAS!$F$8:$F$211,$G45,KAS!$H$8:$H$211,J$36) -> 0 | K45: =SUMIFS(INVEST!$L$8:$L$215,INVEST!$H$8:$H$215,RECAP!$H45,INVEST!$I$8:$I$215,K$36) -> 1821210544 | L45: =SUMIFS(INVEST!$M$8:$M$215,INVEST!$H$8:$H$215,RECAP!$H45,INVEST!$I$8:$I$215,L$36) -> 0 | M45: =SUM(I45,K45) -> 1821210544 | N45: =SUM(J45,L45) -> 0
B46: Selisih Kenaikan yang belum tercover | C46: =C25-C44 -> 5.4412527e+10 | G46: SINARMAS SEKURITAS | H46: SSEK | I46: =SUMIFS(KAS!$J$8:$J$211,KAS!$F$8:$F$211,$G46,KAS!$H$8:$H$211,I$36) -> 0 | J46: =SUMIFS(KAS!$K$8:$K$211,KAS!$F$8:$F$211,$G46,KAS!$H$8:$H$211,J$36) -> 0 | K46: =SUMIFS(INVEST!$L$8:$L$215,INVEST!$H$8:$H$215,RECAP!$H46,INVEST!$I$8:$I$215,K$36) -> 3657152090 | L46: =SUMIFS(INVEST!$M$8:$M$215,INVEST!$H$8:$H$215,RECAP!$H46,INVEST!$I$8:$I$215,L$36) -> 0 | M46: =SUM(I46,K46) -> 3657152090 | N46: =SUM(J46,L46) -> 0
G47: BANK MAYBANK INDONESIA | H47: MAY | I47: =SUMIFS(KAS!$J$8:$J$211,KAS!$F$8:$F$211,$G47,KAS!$H$8:$H$211,I$36) -> 289120215 | J47: =SUMIFS(KAS!$K$8:$K$211,KAS!$F$8:$F$211,$G47,KAS!$H$8:$H$211,J$36) -> 0 | K47: =SUMIFS(INVEST!$L$8:$L$215,INVEST!$H$8:$H$215,RECAP!$H47,INVEST!$I$8:$I$215,K$36) -> 10140000000 | L47: =SUMIFS(INVEST!$M$8:$M$215,INVEST!$H$8:$H$215,RECAP!$H47,INVEST!$I$8:$I$215,L$36) -> 0 | M47: =SUM(I47,K47) -> 10429120215 | N47: =SUM(J47,L47) -> 0
G48: BANK DBS INDONESIA | H48: DBS | I48: =SUMIFS(KAS!$J$8:$J$211,KAS!$F$8:$F$211,$G48,KAS!$H$8:$H$211,I$36) -> 86378401 | J48: =SUMIFS(KAS!$K$8:$K$211,KAS!$F$8:$F$211,$G48,KAS!$H$8:$H$211,J$36) -> 632 | K48: =SUMIFS(INVEST!$L$8:$L$215,INVEST!$H$8:$H$215,RECAP!$H48,INVEST!$I$8:$I$215,K$36) -> 24180000000 | L48: =SUMIFS(INVEST!$M$8:$M$215,INVEST!$H$8:$H$215,RECAP!$H48,INVEST!$I$8:$I$215,L$36) -> 430823 | M48: =SUM(I48,K48) -> 24266378401 | N48: =SUM(J48,L48) -> 431455
G49: BANK UOB INDONESIA | H49: UOB | I49: =SUMIFS(KAS!$J$8:$J$211,KAS!$F$8:$F$211,$G49,KAS!$H$8:$H$211,I$36) -> 700631451 | J49: =SUMIFS(KAS!$K$8:$K$211,KAS!$F$8:$F$211,$G49,KAS!$H$8:$H$211,J$36) -> 25572 | K49: =SUMIFS(INVEST!$L$8:$L$215,INVEST!$H$8:$H$215,RECAP!$H49,INVEST!$I$8:$I$215,K$36) -> 5405966829 | L49: =SUMIFS(INVEST!$M$8:$M$215,INVEST!$H$8:$H$215,RECAP!$H49,INVEST!$I$8:$I$215,L$36) -> 934092 | M49: =SUM(I49,K49) -> 6106598280 | N49: =SUM(J49,L49) -> 959664
A50: Tahun | B50: Kas + Investasi | C50: Hasil Invest 6,5% | G50: CITIBANK SINGAPORE | H50: CBS | I50: =SUMIFS(KAS!$J$8:$J$211,KAS!$F$8:$F$211,$G50,KAS!$H$8:$H$211,I$36) -> 0 | J50: =SUMIFS(KAS!$K$8:$K$211,KAS!$F$8:$F$211,$G50,KAS!$H$8:$H$211,J$36) -> 0 | K50: =SUMIFS(INVEST!$L$8:$L$215,INVEST!$H$8:$H$215,RECAP!$H50,INVEST!$I$8:$I$215,K$36) -> 0 | L50: =SUMIFS(INVEST!$M$8:$M$215,INVEST!$H$8:$H$215,RECAP!$H50,INVEST!$I$8:$I$215,L$36) -> 150000 | M50: =SUM(I50,K50) -> 0 | N50: =SUM(J50,L50) -> 150000
A51: 2024 | B51: =SUM(C3:C5) -> 172137068754 | C51: =B51*106.5% -> 1.8332598e+11 | G51: Total | I51: =SUM(I37:I50) -> 9284670014 | J51: =SUM(J37:J50) -> 76960 | K51: =SUM(K37:K50) -> 146436837134 | L51: =SUM(L37:L50) -> 4854810 | M51: =SUM(M37:M50) -> 155721507148 | N51: =SUM(N37:N50) -> 4931770
A52: 2025 | B52: =SUM(D3:D5) -> 241368012438 | G52: Ekuivalen | I52: =I53 -> 92846700 | J52: =J53*16777 -> 12911579 | K52: =K53 -> 1.0250579e+10 | L52: =L53*16777 -> 3.2579659e+09 | M52: =M53 -> 1.0343425e+10 | N52: =N53*16777 -> 3270877474
A53: Selisih | B53: =B52-B51 -> 69230943684 | G53: Perhitungan Bunga | I53: =I51*1% -> 92846700 | J53: =J51*1% -> 769.6 | K53: =K51*7% -> 1.0250579e+10 | L53: =L51*4% -> 194192.4 | M53: =SUM(I53,K53) -> 1.0343425e+10 | N53: =SUM(J53,L53) -> 194962
G54: TAB 1 %
G55: INVEST IDR 7 %, USD 4% | L55: Total Keseluruhan | M55: =M52+N52 -> 1.3614303e+10
G59: DETIL KAS 2025
G60: PERUSAHAAN | H60: KODE | I60: TABUNGAN | K60: DEPOSITO | M60: TOTAL
I61: IDR | J61: USD (DIRUPIAHKAN) | K61: IDR | L61: USD (DIRUPIAHKAN) | M61: IDR | N61: USD (DIRUPIAHKAN)
F62: 0010003358091000 | G62: STANDARD CHARTERED BANK | H62: SC | I62: 471794907 | J62: 7314772 | K62: 0 | L62: 0 | M62: =SUM(I62,K62) -> 471794907 | N62: =SUM(J62,L62) -> 7314772 | O62: =SUM(I62:J62)*1%+SUM(K62:L62)*4% -> 4791096.8 | P62: =O62*20% -> 958219.36
F63: 0011080454091000 | G63: BANK MEGA | H63: MG | I63: 2365099919 | J63: 38368999 | K63: 2076324773 | L63: 0 | M63: =SUM(I63,K63) -> 4441424692 | N63: =SUM(J63,L63) -> 38368999 | O63: =SUM(I63:J63)*1%+SUM(K63:L63)*4% -> 1.0708768e+08 | P63: =O63*20% -> 21417536
F64: 0013084496091000 | G64: BANK CENTRAL ASIA | H64: BCA | I64: 1849939508 | J64: 448197555 | K64: 0 | L64: 0 | M64: =SUM(I64,K64) -> 1849939508 | N64: =SUM(J64,L64) -> 448197555 | O64: =SUM(I64:J64)*1%+SUM(K64:L64)*4% -> 22981371 | P64: =O64*20% -> 4596274.1
F65: 0013121660091000 | G65: BANK PAN INDONESIA | H65: PAN | I65: 239621964 | J65: 280679210 | K65: 0 | L65: 0 | M65: =SUM(I65,K65) -> 239621964 | N65: =SUM(J65,L65) -> 280679210 | O65: =SUM(I65:J65)*1%+SUM(K65:L65)*4% -> 5203011.7 | P65: =O65*20% -> 1040602.3
F66: 0013106687091000 | G66: BANK CIMB NIAGA | H66: CIMB | I66: 703053335 | J66: 0 | K66: 0 | L66: 0 | M66: =SUM(I66,K66) -> 703053335 | N66: =SUM(J66,L66) -> 0 | O66: =SUM(I66:J66)*1%+SUM(K66:L66)*4% -> 7030533.4 | P66: =O66*20% -> 1406106.7
F67: 0011049194091000 | G67: BANK OCBC NISP | H67: OCBC | I67: 282662537 | J67: 0 | K67: 0 | L67: 0 | M67: =SUM(I67,K67) -> 282662537 | N67: =SUM(J67,L67) -> 0 | O67: =SUM(I67:J67)*1%+SUM(K67:L67)*4% -> 2826625.4 | P67: =O67*20% -> 565325.07
F68: 0010611739093000 | G68: BANK MANDIRI | H68: MDRI | I68: 69884414 | J68: 0 | K68: 0 | L68: 0 | M68: =SUM(I68,K68) -> 69884414 | N68: =SUM(J68,L68) -> 0 | O68: =SUM(I68:J68)*1%+SUM(K68:L68)*4% -> 698844.14 | P68: =O68*20% -> 139768.83
F69: 0013862420091000 | G69: BANK HSBC INDONESIA | H69: HSBC | I69: 150158590 | J69: 76972876 | K69: 0 | L69: 0 | M69: =SUM(I69,K69) -> 150158590 | N69: =SUM(J69,L69) -> 76972876 | O69: =SUM(I69:J69)*1%+SUM(K69:L69)*4% -> 2271314.7 | P69: =O69*20% -> 454262.93
G70: SINARMAS ASET MGMT | H70: SMAS | I70: 0 | J70: 0 | K70: 0 | L70: 0 | M70: =SUM(I70,K70) -> 0 | N70: =SUM(J70,L70) -> 0 | O70: =SUM(I70:J70)*1%+SUM(K70:L70)*4% -> 0 | P70: =O70*20% -> 0
G71: SINARMAS SEKURITAS | H71: SSEK | I71: 0 | J71: 0 | K71: 0 | L71: 0 | M71: =SUM(I71,K71) -> 0 | N71: =SUM(J71,L71) -> 0 | O71: =SUM(I71:J71)*1%+SUM(K71:L71)*4% -> 0 | P71: =O71*20% -> 0
F72: 0013093232091000 | G72: BANK MAYBANK INDONESIA | H72: MAY | I72: 289120215 | J72: 0 | K72: 0 | L72: 0 | M72: =SUM(I72,K72) -> 289120215 | N72: =SUM(J72,L72) -> 0 | O72: =SUM(I72:J72)*1%+SUM(K72:L72)*4% -> 2891202.1 | P72: =O72*20% -> 578240.43
F73: 0013429402091000 | G73: BANK DBS INDONESIA | H73: DBS | I73: 86378401 | J73: 10603064 | K73: 0 | L73: 0 | M73: =SUM(I73,K73) -> 86378401 | N73: =SUM(J73,L73) -> 10603064 | O73: =SUM(I73:J73)*1%+SUM(K73:L73)*4% -> 969814.65 | P73: =O73*20% -> 193962.93
F74: 0013084439091000 | G74: BANK UOB INDONESIA | H74: UOB | I74: 700631451 | J74: 429021444 | K74: 0 | L74: 0 | M74: =SUM(I74,K74) -> 700631451 | N74: =SUM(J74,L74) -> 429021444 | O74: =SUM(I74:J74)*1%+SUM(K74:L74)*4% -> 11296529 | P74: =O74*20% -> 2259305.8
G75: CITIBANK SINGAPORE | H75: CBS | I75: 0 | J75: 0 | K75: 0 | L75: 0 | M75: =SUM(I75,K75) -> 0 | N75: =SUM(J75,L75) -> 0 | O75: =SUM(I75:J75)*1%+SUM(K75:L75)*4% -> 0 | P75: =O75*20% -> 0
G76: Total | I76: =SUM(I62:I75) -> 7208345241 | J76: =SUM(J62:J75) -> 1291157920 | K76: =SUM(K62:K75) -> 2076324773 | L76: =SUM(L62:L75) -> 0 | M76: =SUM(M62:M75) -> 9284670014 | N76: =SUM(N62:N75) -> 1291157920 | O76: =SUM(O62:O75) -> 1.6804802e+08 | P76: =SUM(P62:P75) -> 33609605
G77: EST. BUNGA | I77: =I76*1% -> 72083452 | J77: =J76*1% -> 12911579 | K77: =K76*4% -> 83052991 | L77: =L76*4.5% -> 0 | M77: =SUM(I77,K77) -> 1.5513644e+08 | N77: =SUM(J77,L77) -> 12911579
G78: Bunga TAB 1 %, DEPO 4%
G81: DETIL INVESTASI 2025
G82: PERUSAHAAN | H82: KODE | I82: OBLIGASI | K82: REKSADANA | M82: INVESTASI LAINNYA | O82: SAHAM BURSA | Q82: UNIT LINK DI ASURANSI
I83: IDR | J83: USD (DIRUPIAHKAN) | K83: IDR | L83: USD (DIRUPIAHKAN) | M83: IDR | N83: USD (DIRUPIAHKAN) | O83: IDR | P83: USD (DIRUPIAHKAN) | Q83: IDR | R83: USD (DIRUPIAHKAN)
G84: STANDARD CHARTERED BANK | H84: SC | I84: 23107474000 | J84: 2013240000 | K84: 3092117556 | L84: 374093546 | M84: 2181174233 | N84: 0 | O84: 0 | P84: 0 | Q84: 0 | R84: 0
G85: BANK MEGA | H85: MG | I85: 0 | J85: 3355400000 | K85: 0 | L85: 0 | M85: 0 | N85: 0 | O85: 0 | P85: 0 | Q85: 0 | R85: 0
G86: BANK CENTRAL ASIA | H86: BCA | I86: 26850000000 | J86: 25723788229 | K86: 0 | L86: 0 | M86: 0 | N86: 0 | O86: 0 | P86: 0 | Q86: 0 | R86: 0
G87: BANK PAN INDONESIA | H87: PAN | I87: 15000000000 | J87: 18958010000 | K87: 0 | L87: 0 | M87: 0 | N87: 0 | O87: 0 | P87: 0 | Q87: 0 | R87: 0
G88: BANK CIMB NIAGA | H88: CIMB | I88: 6100000000 | J88: 0 | K88: 0 | L88: 0 | M88: 0 | N88: 0 | O88: 0 | P88: 0 | Q88: 762623126 | R88: 0
G89: BANK OCBC NISP | H89: OCBC | I89: 1000000000 | J89: 0 | K89: 0 | L89: 0 | M89: 0 | N89: 0 | O89: 0 | P89: 0 | Q89: 0 | R89: 0
G90: BANK MANDIRI | H90: MDRI | I90: 0 | J90: 0 | K90: 0 | L90: 0 | M90: 0 | N90: 0 | O90: 0 | P90: 0 | Q90: 0 | R90: 0
G91: BANK HSBC INDONESIA | H91: HSBC | I91: 19657400000 | J91: 5608886640 | K91: 3481718756 | L91: 0 | M91: 0 | N91: 0 | O91: 0 | P91: 0 | Q91: 0 | R91: 0
G92: SINARMAS ASET MGMT | H92: SMAS | I92: 0 | J92: 0 | K92: 1821210544 | L92: 0 | M92: 0 | N92: 0 | O92: 0 | P92: 0 | Q92: 0 | R92: 0
G93: SINARMAS SEKURITAS | H93: SSEK | I93: 0 | J93: 0 | K93: 0 | L93: 0 | M93: 0 | N93: 0 | O93: 3657152090 | P93: 0 | Q93: 0 | R93: 0
G94: BANK MAYBANK INDONESIA | H94: MAY | I94: 10140000000 | J94: 0 | K94: 0 | L94: 0 | M94: 0 | N94: 0 | O94: 0 | P94: 0 | Q94: 0 | R94: 0
G95: BANK DBS INDONESIA | H95: DBS | I95: 24180000000 | J95: 6731402156 | K95: 0 | L95: 0 | M95: 0 | N95: 0 | O95: 0 | P95: 0 | Q95: 0 | R95: 496515315
... G97: CITIBANK SINGAPORE | H97: CBS | I97: 0 | J97: 0 | K97: 0 | L97: 2516550000 | M97: 0 | N97: 0 | O97: 0 | P97: 0 | Q97: 0 | R97: 0
G98: Total | I98: =SUM(I84:I97) -> 128440991000 | J98: =SUM(J84:J97) -> 78061988509 | K98: =SUM(K84:K97) -> 11394896685 | L98: =SUM(L84:L97) -> 2890643546 | M98: =SUM(M84:M97) -> 2181174233 | N98: =SUM(N84:N97) -> 0 | O98: =SUM(O84:O97) -> 3657152090 | P98: =SUM(P84:P97) -> 0 | ... R98: =SUM(R84:R97) -> 496515315
G99: EST. BUNGA | I99: =I98*8% -> 10275279280 | J99: =J98*6% -> 4.6837193e+09 | O99: =O98*5% -> 1.828576e+08 | P99: UNTUNG 5%
G100: IDR 8%, USD 6% | Q100: Total Keseluruhan | R100: =SUM(I99:J99,O99) -> 1.5141856e+10

Sheet INVEST (2)
C1: 3. INVESTASI/SEKURITAS
C2: Saham yang dibeli untuk dijual kembali/Saham Non Bursa/Saham Bursa/Obligasi Perusahaan/Obligasi Pemerintah IndonesiaSurat Utang Lainnya/Asuransi/Unit Link di Asuransi
C4: 3172011604670003 | D4: HARYANTO DJOJOE BUNTORO
I5: =SUM(I7:I492) -> 230091984504 | K5: =SUM(K7:K492) -> 230091984504 | O5: =SUM(O7:O492) -> 211977076543 | P5: =SUM(P7:P492) -> 208727216054 | Q5: =SUM(Q7:Q492) -> 206270384779 | R5: =SUM(R7:R492) -> 181609091319 | S5: =SUM(S7:S492) -> 169721004249
A6: NO | B6: KODE | C6: DESKRIPSI | D6: LOKASI HARTA | E6: NAMA | F6: NOMOR AKUN | G6: KODE BANK | H6: KURS | I6: HARGA PEROLEHAN | J6: TAHUN PEROLEHAN | K6: NILAI SAAT INI (2025) | L6: SALDO DALAM BENTUK AWAL (2025) | M6: KURS | N6: (HARTA PPS/ HARTA INVESTASI PPS) | O6: NILAI TAHUN SEBELUMNYA
A7: 1 | B7: =VLOOKUP(C7,$V:$W,2,0) -> 0305 | C7: OBLIGASI PEMERINTAH | D7: Indonesia | E7: STANDARD CHARTERED BANK | F7: OBLIGASI FR 75 | G7: SC | H7: IDR | I7: 1095750000 | J7: 2025 | K7: =ROUNDDOWN(L7*M7,0) -> 1095750000 | L7: 1095750000 | M7: =VLOOKUP(H7,BUNGA!$C$97:$D$98,2,0) -> 1 | N7: SJ | O7: 1000000000 | P7: 1000000000 | Q7: 1000000000 | R7: 1000000000 | S7: 1000000000 | U7: 0301 | V7: SAHAM YANG DIBELI UNTUK DIJUAL KEMBALI | W7: 0301
A8: =A7+1 -> 2 | B8: =VLOOKUP(C8,$V:$W,2,0) -> 0305 | C8: OBLIGASI PEMERINTAH | D8: Indonesia | E8: STANDARD CHARTERED BANK | F8: OBLIGASI FR 80 | G8: SC | H8: IDR | I8: 437628000 | J8: 2025 | K8: =ROUNDDOWN(L8*M8,0) -> 437628000 | L8: 437628000 | M8: =VLOOKUP(H8,BUNGA!$C$97:$D$98,2,0) -> 1 | N8: SJ | O8: 400000000 | P8: 400000000 | Q8: 400000000 | R8: 400000000 | S8: 400000000 | U8: 0302 | V8: SAHAM NON BURSA | W8: 0302
A9: =A8+1 -> 3 | B9: =VLOOKUP(C9,$V:$W,2,0) -> 0305 | C9: OBLIGASI PEMERINTAH | D9: Indonesia | E9: STANDARD CHARTERED BANK | F9: FR064 | G9: SC | H9: IDR | I9: 1850000000 | J9: 2025 | K9: =ROUNDDOWN(L9*M9,0) -> 1850000000 | L9: 1850000000 | M9: =VLOOKUP(H9,BUNGA!$C$97:$D$98,2,0) -> 1 | N9: - | O9: 1850000000 | P9: 1850000000 | Q9: 0 | R9: 0 | S9: 0 | U9: 0303 | V9: SAHAM BURSA | W9: 0303
A10: =A9+1 -> 4 | B10: =VLOOKUP(C10,$V:$W,2,0) -> 0305 | C10: OBLIGASI PEMERINTAH | D10: Indonesia | E10: STANDARD CHARTERED BANK | F10: ST011 | G10: SC | H10: IDR | I10: 2370000000 | J10: 2025 | K10: =ROUNDDOWN(L10*M10,0) -> 2370000000 | L10: 2370000000 | M10: =VLOOKUP(H10,BUNGA!$C$97:$D$98,2,0) -> 1 | N10: RC | O10: 2370000000 | P10: 2370000000 | Q10: 0 | R10: 0 | S10: 0 | U10: 0304 | V10: OBLIGASI PERUSAHAAN | W10: 0304
A11: =A10+1 -> 5 | B11: =VLOOKUP(C11,$V:$W,2,0) -> 0399 | C11: INVESTASI LAINNYA | D11: Indonesia | E11: STANDARD CHARTERED BANK | F11: ASURANSI PRUDENT UMP | G11: SC | H11: IDR | I11: 901170423 | J11: 2025 | K11: =ROUNDDOWN(L11*M11,0) -> 901170423 | L11: 901170423 | M11: =VLOOKUP(H11,BUNGA!$C$97:$D$98,2,0) -> 1 | N11: SJ | O11: 109394265 | P11: 0 | Q11: 0 | R11: 0 | S11: 0 | U11: 0305 | V11: OBLIGASI PEMERINTAH | W11: 0305
A12: =A11+1 -> 6 | B12: =VLOOKUP(C12,$V:$W,2,0) -> 0399 | C12: INVESTASI LAINNYA | D12: Indonesia | E12: STANDARD CHARTERED BANK | F12: ASURANSI PRUDENT VIA | G12: SC | H12: IDR | I12: 1280003810 | J12: 2025 | K12: =ROUNDDOWN(L12*M12,0) -> 1280003810 | L12: 1280003810 | M12: =VLOOKUP(H12,BUNGA!$C$97:$D$98,2,0) -> 1 | N12: SJ | O12: 197646600 | P12: 0 | Q12: 0 | R12: 0 | S12: 0 | U12: 0306 | V12: SURAT UTANG LAINNYA | W12: 0306
A13: =A12+1 -> 7 | B13: =VLOOKUP(C13,$V:$W,2,0) -> 0307 | C13: REKSADANA | D13: Indonesia | E13: STANDARD CHARTERED BANK | F13: MONI 2 0775 | G13: SC | H13: IDR | I13: =L13 -> 1406054056 | J13: 2025 | K13: =ROUNDDOWN(L13*M13,0) -> 1406054056 | L13: 1406054056 | M13: =VLOOKUP(H13,BUNGA!$C$97:$D$98,2,0) -> 1 | N13: SJ | O13: 0 | P13: 0 | Q13: 0 | R13: 0 | S13: 0 | U13: 0307 | V13: REKSADANA | W13: 0307
A14: =A13+1 -> 8 | B14: =VLOOKUP(C14,$V:$W,2,0) -> 0307 | C14: REKSADANA | D14: Indonesia | E14: STANDARD CHARTERED BANK | F14: MONI 2 0403 | G14: SC | H14: IDR | I14: =L14 -> 398528728 | J14: 2025 | K14: =ROUNDDOWN(L14*M14,0) -> 398528728 | L14: 398528728 | M14: =VLOOKUP(H14,BUNGA!$C$97:$D$98,2,0) -> 1 | N14: SJ | O14: 0 | P14: 0 | Q14: 0 | R14: 0 | S14: 0 | U14: 0309 | V14: PENYERTAAN MODAL DALAM PERUSAHAAN LAIN YANG BUKAN ATAS SAHAM | W14: 0309
A15: =A14+1 -> 9 | B15: =VLOOKUP(C15,$V:$W,2,0) -> 0307 | C15: REKSADANA | D15: Indonesia | E15: STANDARD CHARTERED BANK | F15: MFI2 USD | G15: SC | H15: USD | I15: =K15 -> 374093546 | J15: 2025 | K15: =ROUNDDOWN(L15*M15,0) -> 374093546 | L15: 22298 | M15: =VLOOKUP(H15,BUNGA!$C$97:$D$98,2,0) -> 16777 | N15: SJ | O15: 0 | P15: 0 | Q15: 0 | R15: 0 | S15: 0 | U15: 0310 | V15: ASURANSI | W15: 0310
A16: =A15+1 -> 10 | B16: =VLOOKUP(C16,$V:$W,2,0) -> 0307 | C16: REKSADANA | D16: Indonesia | E16: STANDARD CHARTERED BANK | F16: MONI 2 | G16: SC | H16: IDR | I16: =L16 -> 1287534772 | J16: 2025 | K16: =ROUNDDOWN(L16*M16,0) -> 1287534772 | L16: 1287534772 | M16: =VLOOKUP(H16,BUNGA!$C$97:$D$98,2,0) -> 1 | N16: RC | O16: 0 | P16: 0 | Q16: 0 | R16: 0 | S16: 0 | U16: 0311 | V16: UNIT LINK DI ASURANSI | W16: 0311
A17: =A16+1 -> 11 | B17: =VLOOKUP(C17,$V:$W,2,0) -> 0305 | C17: OBLIGASI PEMERINTAH | D17: Indonesia | E17: STANDARD CHARTERED BANK | F17: USD INDON 34 | G17: SC | H17: USD | I17: =K17 -> 2013240000 | J17: 2025 | K17: =ROUNDDOWN(L17*M17,0) -> 2013240000 | L17: 120000 | M17: =VLOOKUP(H17,BUNGA!$C$97:$D$98,2,0) -> 16777 | N17: SJ | O17: 0 | P17: 0 | Q17: 0 | R17: 0 | S17: 0 | U17: 0399 | V17: INVESTASI LAINNYA | W17: 0399
A18: =A16+1 -> 11 | B18: =VLOOKUP(C18,$V:$W,2,0) -> 0305 | C18: OBLIGASI PEMERINTAH | D18: Indonesia | E18: STANDARD CHARTERED BANK | F18: SR 021 | G18: SC | H18: IDR | I18: 1984096000 | J18: 2025 | K18: =ROUNDDOWN(L18*M18,0) -> 1984096000 | L18: 1984096000 | M18: =VLOOKUP(H18,BUNGA!$C$97:$D$98,2,0) -> 1 | N18: SJ | O18: 0 | P18: 0 | Q18: 0 | R18: 0 | S18: 0
A19: =A17+1 -> 12 | B19: =VLOOKUP(C19,$V:$W,2,0) -> 0305 | C19: OBLIGASI PEMERINTAH | D19: Indonesia | E19: STANDARD CHARTERED BANK | F19: SR022 T5 | G19: SC | H19: IDR | I19: 2000000000 | J19: 2025 | K19: =ROUNDDOWN(L19*M19,0) -> 2000000000 | L19: 2000000000 | M19: =VLOOKUP(H19,BUNGA!$C$97:$D$98,2,0) -> 1 | N19: SJ | O19: 0 | P19: 0 | Q19: 0 | R19: 0 | S19: 0
A20: =A19+1 -> 13 | B20: =VLOOKUP(C20,$V:$W,2,0) -> 0305 | C20: OBLIGASI PEMERINTAH | D20: Indonesia | E20: STANDARD CHARTERED BANK | F20: ST014 T4 | G20: SC | H20: IDR | I20: 1700000000 | J20: 2025 | K20: =ROUNDDOWN(L20*M20,0) -> 1700000000 | L20: 1700000000 | M20: =VLOOKUP(H20,BUNGA!$C$97:$D$98,2,0) -> 1 | N20: SJ | O20: 0 | P20: 0 | Q20: 0 | R20: 0 | S20: 0
A21: =A20+1 -> 14 | B21: =VLOOKUP(C21,$V:$W,2,0) -> 0305 | C21: OBLIGASI PEMERINTAH | D21: Indonesia | E21: STANDARD CHARTERED BANK | F21: FR 58 | G21: SC | H21: IDR | I21: 2500000000 | J21: 2025 | K21: =ROUNDDOWN(L21*M21,0) -> 2500000000 | L21: 2500000000 | M21: =VLOOKUP(H21,BUNGA!$C$97:$D$98,2,0) -> 1 | N21: SJ | O21: 0 | P21: 0 | Q21: 0 | R21: 0 | S21: 0 | U21: OWNERSHIP MOVEABLE ASSET
A22: =A21+1 -> 15 | B22: =VLOOKUP(C22,$V:$W,2,0) -> 0305 | C22: OBLIGASI PEMERINTAH | D22: Indonesia | E22: STANDARD CHARTERED BANK | F22: ORI27 T6 | G22: SC | H22: IDR | I22: 2180000000 | J22: 2025 | K22: =ROUNDDOWN(L22*M22,0) -> 2180000000 | L22: 2180000000 | M22: =VLOOKUP(H22,BUNGA!$C$97:$D$98,2,0) -> 1 | N22: SJ | O22: 0 | P22: 0 | Q22: 0 | R22: 0 | S22: 0 | U22: Code | V22: Code Description
A23: =A22+1 -> 16 | B23: =VLOOKUP(C23,$V:$W,2,0) -> 0305 | C23: OBLIGASI PEMERINTAH | D23: Indonesia | E23: STANDARD CHARTERED BANK | F23: FR 78 | G23: SC | H23: IDR | I23: 1220000000 | J23: 2025 | K23: =ROUNDDOWN(L23*M23,0) -> 1220000000 | L23: 1220000000 | M23: =VLOOKUP(H23,BUNGA!$C$97:$D$98,2,0) -> 1 | N23: SJ | O23: 0 | P23: 0 | Q23: 0 | R23: 0 | S23: 0 | U23: OTHER | V23: Atas nama pihak lain
A24: =A23+1 -> 17 | B24: =VLOOKUP(C24,$V:$W,2,0) -> 0305 | C24: OBLIGASI PEMERINTAH | D24: Indonesia | E24: STANDARD CHARTERED BANK | F24: ST015 T2 | G24: SC | H24: IDR | I24: 3000000000 | J24: 2025 | K24: =ROUNDDOWN(L24*M24,0) -> 3000000000 | L24: 3000000000 | M24: =VLOOKUP(H24,BUNGA!$C$97:$D$98,2,0) -> 1 | N24: SJ | O24: 0 | P24: 0 | Q24: 0 | R24: 0 | S24: 0 | U24: TAXPAYER | V24: Atas nama sendiri
A25: =A24+1 -> 18 | B25: =VLOOKUP(C25,$V:$W,2,0) -> 0305 | C25: OBLIGASI PEMERINTAH | D25: Indonesia | E25: STANDARD CHARTERED BANK | F25: SBR014 T2 | G25: SC | H25: IDR | I25: 620000000 | J25: 2025 | K25: =ROUNDDOWN(L25*M25,0) -> 620000000 | L25: 620000000 | M25: =VLOOKUP(H25,BUNGA!$C$97:$D$98,2,0) -> 1 | N25: RC | O25: 0 | P25: 0 | Q25: 0 | R25: 0 | S25: 0
A26: =A25+1 -> 19 | B26: =VLOOKUP(C26,$V:$W,2,0) -> 0305 | C26: OBLIGASI PEMERINTAH | D26: Indonesia | E26: STANDARD CHARTERED BANK | F26: SR021 T5 | G26: SC | H26: IDR | I26: 2150000000 | J26: 2025 | K26: =ROUNDDOWN(L26*M26,0) -> 2150000000 | L26: 2150000000 | M26: =VLOOKUP(H26,BUNGA!$C$97:$D$98,2,0) -> 1 | N26: RC | O26: 0 | P26: 0 | Q26: 0 | R26: 0 | S26: 0
A27: =A26+1 -> 20 | B27: =VLOOKUP(C27,$V:$W,2,0) -> 0305 | C27: OBLIGASI PEMERINTAH | D27: Indonesia | E27: BANK MEGA | F27: USD INDOIS 27 | G27: MG | H27: USD | I27: 3355400000 | J27: 2025 | K27: =ROUNDDOWN(L27*M27,0) -> 3355400000 | L27: 200000 | M27: =VLOOKUP(H27,BUNGA!$C$97:$D$98,2,0) -> 16777 | N27: SJ | O27: 0 | P27: 0 | Q27: 0 | R27: 0 | S27: 0
A28: =A27+1 -> 21 | B28: =VLOOKUP(C28,$V:$W,2,0) -> 0305 | C28: OBLIGASI PEMERINTAH | D28: Indonesia | E28: BANK CENTRAL ASIA | F28: OBLIGASI FR68 | G28: BCA | H28: IDR | I28: =K28 -> 1200000000 | J28: 2025 | K28: =ROUNDDOWN(L28*M28,0) -> 1200000000 | L28: 1200000000 | M28: =VLOOKUP(H28,BUNGA!$C$97:$D$98,2,0) -> 1 | N28: SJ | O28: 2000000000 | P28: 2000000000 | Q28: 2000000000 | R28: 2000000000 | S28: 2000000000
A29: =A28+1 -> 22 | B29: =VLOOKUP(C29,$V:$W,2,0) -> 0305 | C29: OBLIGASI PEMERINTAH | D29: Indonesia | E29: BANK CENTRAL ASIA | F29: OBLIGASI FR74 | G29: BCA | H29: IDR | I29: =K29 -> 1600000000 | J29: 2025 | K29: =ROUNDDOWN(L29*M29,0) -> 1600000000 | L29: 1600000000 | M29: =VLOOKUP(H29,BUNGA!$C$97:$D$98,2,0) -> 1 | N29: SJ | O29: 2000000000 | P29: 2000000000 | Q29: 2000000000 | R29: 2000000000 | S29: 2000000000
A30: =A29+1 -> 23 | B30: =VLOOKUP(C30,$V:$W,2,0) -> 0305 | C30: OBLIGASI PEMERINTAH | D30: Indonesia | E30: BANK CENTRAL ASIA | F30: OBLIGASI FR79 | G30: BCA | H30: IDR | I30: =K30 -> 4500000000 | J30: 2025 | K30: =ROUNDDOWN(L30*M30,0) -> 4500000000 | L30: 4500000000 | M30: =VLOOKUP(H30,BUNGA!$C$97:$D$98,2,0) -> 1 | N30: SJ | O30: 4500000000 | P30: 4500000000 | Q30: 4500000000 | R30: 4500000000 | S30: 4500000000
A31: =A30+1 -> 24 | B31: =VLOOKUP(C31,$V:$W,2,0) -> 0305 | C31: OBLIGASI PEMERINTAH | D31: Indonesia | E31: BANK CENTRAL ASIA | F31: OBLIGASI FR065 | G31: BCA | H31: IDR | I31: =K31 -> 700000000 | J31: 2025 | K31: =ROUNDDOWN(L31*M31,0) -> 700000000 | L31: 700000000 | M31: =VLOOKUP(H31,BUNGA!$C$97:$D$98,2,0) -> 1 | N31: RC | O31: 2000000000 | P31: 2000000000 | Q31: 2000000000 | R31: 2000000000 | S31: 0
A32: =A31+1 -> 25 | B32: =VLOOKUP(C32,$V:$W,2,0) -> 0305 | C32: OBLIGASI PEMERINTAH | D32: Indonesia | E32: BANK CENTRAL ASIA | F32: OBLIGASI FR068 | G32: BCA | H32: IDR | I32: =K32 -> 1200000000 | J32: 2025 | K32: =ROUNDDOWN(L32*M32,0) -> 1200000000 | L32: 1200000000 | M32: =VLOOKUP(H32,BUNGA!$C$97:$D$98,2,0) -> 1 | N32: RC | O32: 2000000000 | P32: 2000000000 | Q32: 2000000000 | R32: 2000000000 | S32: 2000000000
A33: =A32+1 -> 26 | B33: =VLOOKUP(C33,$V:$W,2,0) -> 0305 | C33: OBLIGASI PEMERINTAH | D33: Indonesia | E33: BANK CENTRAL ASIA | F33: OBLIGASI FR072 | G33: BCA | H33: IDR | I33: =K33 -> 1000000000 | J33: 2025 | K33: =ROUNDDOWN(L33*M33,0) -> 1000000000 | L33: 1000000000 | M33: =VLOOKUP(H33,BUNGA!$C$97:$D$98,2,0) -> 1 | N33: RC | O33: 2000000000 | P33: 2000000000 | Q33: 2000000000 | R33: 2000000000 | S33: 2000000000
A34: =A33+1 -> 27 | B34: =VLOOKUP(C34,$V:$W,2,0) -> 0305 | C34: OBLIGASI PEMERINTAH | D34: Indonesia | E34: BANK CENTRAL ASIA | F34: OBLIGASI FR074 | G34: BCA | H34: IDR | I34: =K34 -> 1200000000 | J34: 2025 | K34: =ROUNDDOWN(L34*M34,0) -> 1200000000 | L34: 1200000000 | M34: =VLOOKUP(H34,BUNGA!$C$97:$D$98,2,0) -> 1 | N34: RC | O34: 2000000000 | P34: 2000000000 | Q34: 2000000000 | R34: 2000000000 | S34: 2000000000
A35: =A34+1 -> 28 | B35: =VLOOKUP(C35,$V:$W,2,0) -> 0305 | C35: OBLIGASI PEMERINTAH | D35: Indonesia | E35: BANK CENTRAL ASIA | F35: OBLIGASI FR079 | G35: BCA | H35: IDR | I35: =K35 -> 450000000 | J35: 2025 | K35: =ROUNDDOWN(L35*M35,0) -> 450000000 | L35: 450000000 | M35: =VLOOKUP(H35,BUNGA!$C$97:$D$98,2,0) -> 1 | N35: RC | O35: 700000000 | P35: 700000000 | Q35: 700000000 | R35: 700000000 | S35: 700000000
A36: =A35+1 -> 29 | B36: =VLOOKUP(C36,$V:$W,2,0) -> 0305 | C36: OBLIGASI PEMERINTAH | D36: Indonesia | E36: BANK CENTRAL ASIA | F36: OBLIGASI FR080 | G36: BCA | H36: IDR | I36: =K36 -> 400000000 | J36: 2025 | K36: =ROUNDDOWN(L36*M36,0) -> 400000000 | L36: 400000000 | M36: =VLOOKUP(H36,BUNGA!$C$97:$D$98,2,0) -> 1 | N36: RC | O36: 1000000000 | P36: 1000000000 | Q36: 1000000000 | R36: 1000000000 | S36: 1000000000
A37: =A36+1 -> 30 | B37: =VLOOKUP(C37,$V:$W,2,0) -> 0305 | C37: OBLIGASI PEMERINTAH | D37: Indonesia | E37: BANK CENTRAL ASIA | F37: OBLIGASI FR082 | G37: BCA | H37: IDR | I37: =K37 -> 2000000000 | J37: 2025 | K37: =ROUNDDOWN(L37*M37,0) -> 2000000000 | L37: 2000000000 | M37: =VLOOKUP(H37,BUNGA!$C$97:$D$98,2,0) -> 1 | N37: RC | O37: 3800000000 | P37: 3800000000 | Q37: 3800000000 | R37: 3800000000 | S37: 3800000000
A38: =A37+1 -> 31 | B38: =VLOOKUP(C38,$V:$W,2,0) -> 0305 | C38: OBLIGASI PEMERINTAH | D38: Indonesia | E38: BANK CENTRAL ASIA | F38: OBLIGASI FR091 | G38: BCA | H38: IDR | I38: =K38 -> 1000000000 | J38: 2025 | K38: =ROUNDDOWN(L38*M38,0) -> 1000000000 | L38: 1000000000 | M38: =VLOOKUP(H38,BUNGA!$C$97:$D$98,2,0) -> 1 | N38: RC | O38: 2000000000 | P38: 2000000000 | Q38: 2000000000 | R38: 2000000000 | S38: 0
A39: =A38+1 -> 32 | B39: =VLOOKUP(C39,$V:$W,2,0) -> 0305 | C39: OBLIGASI PEMERINTAH | D39: Indonesia | E39: BANK CENTRAL ASIA | F39: OBLIGASI INDOIS 30 USD | G39: BCA | H39: USD | I39: =K39 -> 694383253 | J39: 2025 | K39: =ROUNDDOWN(L39*M39,0) -> 694383253 | L39: 41389 | M39: =VLOOKUP(H39,BUNGA!$C$97:$D$98,2,0) -> 16777 | N39: RC | O39: 667025085 | P39: 3100000000 | Q39: 3100000000 | R39: 2858800000 | S39: 0
... A133: =A132+1 -> 126 | B133: =VLOOKUP(C133,$V:$W,2,0) -> 0305 | C133: OBLIGASI PEMERINTAH | D133: Indonesia | E133: CITIBANK SINGAPORE | F133: CITIBANK SINGAPORE - INVESMENT FUND 841879901 | G133: CBS | H133: USD | I133: =K133 -> 2516550000 | J133: 2025 | K133: =ROUNDDOWN(L133*M133,0) -> 2516550000 | L133: 150000 | M133: =VLOOKUP(H133,BUNGA!$C$97:$D$98,2,0) -> 16777 | N133: RC | O133: 2316750000 | P133: 2316750000 | Q133: 2325000000 | R133: 2144100000 | S133: 2134200000
A134: =A132+1 -> 126 | B134: =VLOOKUP(C134,$V:$W,2,0) -> 0302 | C134: SAHAM NON BURSA | D134: Indonesia | E134: PT BORNEO JAYA SEJATI | F134: PT BORNEO JAYA SEJATI | G134: - | H134: IDR | I134: =K134 -> 40000000 | J134: 2025 | K134: =ROUNDDOWN(L134*M134,0) -> 40000000 | L134: 40000000 | M134: =VLOOKUP(H134,BUNGA!$C$97:$D$98,2,0) -> 1 | N134: SJ | O134: 40000000 | P134: 40000000 | Q134: 40000000 | R134: 40000000 | S134: 40000000
A135: =A134+1 -> 127 | B135: =VLOOKUP(C135,$V:$W,2,0) -> 0302 | C135: SAHAM NON BURSA | D135: Indonesia | E135: PT.MG DUA JAYA | F135: PT.MG DUA JAYA | G135: - | H135: IDR | I135: =K135 -> 1680000000 | J135: 2025 | K135: =ROUNDDOWN(L135*M135,0) -> 1680000000 | L135: 1680000000 | M135: =VLOOKUP(H135,BUNGA!$C$97:$D$98,2,0) -> 1 | N135: SJ | O135: 1680000000 | P135: 1680000000 | Q135: 1680000000 | R135: 1680000000 | S135: 1680000000
A136: =A135+1 -> 128 | B136: =VLOOKUP(C136,$V:$W,2,0) -> 0302 | C136: SAHAM NON BURSA | D136: Indonesia | E136: PT.KARUNIA RAHMAT INTI SEJAHTERA | F136: PT.KARUNIA RAHMAT INTI SEJAHTERA | G136: - | H136: IDR | I136: =K136 -> 250000000 | J136: 2025 | K136: =ROUNDDOWN(L136*M136,0) -> 250000000 | L136: 250000000 | M136: =VLOOKUP(H136,BUNGA!$C$97:$D$98,2,0) -> 1 | N136: SJ | O136: 250000000 | P136: 250000000 | Q136: 250000000 | R136: 250000000 | S136: 250000000
A137: =A136+1 -> 129 | B137: =VLOOKUP(C137,$V:$W,2,0) -> 0302 | C137: SAHAM NON BURSA | D137: Indonesia | E137: PT.HEPI JAYA BERSAMA | F137: PT.HEPI JAYA BERSAMA | G137: - | H137: IDR | I137: =K137 -> 236000000 | J137: 2025 | K137: =ROUNDDOWN(L137*M137,0) -> 236000000 | L137: 236000000 | M137: =VLOOKUP(H137,BUNGA!$C$97:$D$98,2,0) -> 1 | N137: SJ | O137: 236000000 | P137: 236000000 | Q137: 236000000 | R137: 236000000 | S137: 236000000
B193: =VLOOKUP(C193,$V:$W,2,0) -> 0305 | C193: OBLIGASI PEMERINTAH | D193: Indonesia | E193: BANK UOB INDONESIA | F193: Citibank - Obligasi FR072 | G193: UOB | H193: IDR | I193: CLOSE | J193: CLOSE | K193: CLOSE | L193: CLOSE | M193: CLOSE | O193: 1500000000 | P193: 1500000000 | Q193: 1500000000 | R193: 1500000000 | S193: 1500000000
B194: =VLOOKUP(C194,$V:$W,2,0) -> 0307 | C194: REKSADANA | D194: Indonesia | E194: BANK UOB INDONESIA | F194: Citibank - Reksadana SDP | G194: UOB | H194: IDR | I194: CLOSE | J194: CLOSE | K194: CLOSE | L194: CLOSE | M194: CLOSE | O194: 549980807 | P194: 634063462 | Q194: 1227536927 | R194: 1301827718 | S194: 1301827718
B195: =VLOOKUP(C195,$V:$W,2,0) -> 0307 | C195: REKSADANA | D195: Indonesia | E195: BANK UOB INDONESIA | F195: Citibank - Reksadana SDPP | G195: UOB | H195: IDR | I195: CLOSE | J195: CLOSE | K195: CLOSE | L195: CLOSE | M195: CLOSE | O195: 1411453237 | P195: 1411453237 | Q195: 1524708144 | R195: 1422201565 | S195: 1422201565
B196: =VLOOKUP(C196,$V:$W,2,0) -> 0307 | C196: REKSADANA | D196: Indonesia | E196: BANK UOB INDONESIA | F196: UOB - Reksadana SDI (Schroder Dana Istimewa) | G196: UOB | H196: USD | I196: CLOSE | J196: CLOSE | K196: CLOSE | L196: CLOSE | M196: CLOSE | O196: 226586251 | P196: 429765191
B197: =VLOOKUP(C197,$V:$W,2,0) -> 0307 | C197: REKSADANA | D197: Indonesia | E197: BANK UOB INDONESIA | F197: UOB - Reksadana SDA II | G197: UOB | H197: IDR | I197: CLOSE | J197: CLOSE | K197: CLOSE | L197: CLOSE | M197: CLOSE | O197: 417256967 | P197: 224407877
C198: OBLIGASI | D198: Indonesia | E198: STANDARD CHARTERED | F198: Obligasi FR 72 | G198: SC | H198: IDR | I198: CLOSE | J198: CLOSE | K198: CLOSE | L198: CLOSE | M198: CLOSE | N198: - | O198: 3700000000 | P198: 3700000000 | Q198: 3700000000 | R198: 3700000000 | S198: 3700000000
C199: OBLIGASI | D199: Indonesia | E199: STANDARD CHARTERED | F199: Obligasi FR 81 | G199: SC | H199: IDR | I199: CLOSE | J199: CLOSE | K199: CLOSE | L199: CLOSE | M199: CLOSE | N199: - | O199: 2300000000 | P199: 2300000000 | Q199: 2300000000 | R199: 0 | S199: 0
C200: OBLIGASI | D200: Indonesia | E200: STANDARD CHARTERED | F200: Obligasi ORI021 | G200: SC | H200: IDR | I200: CLOSE | J200: CLOSE | K200: CLOSE | L200: CLOSE | M200: CLOSE | N200: - | O200: 2000000000 | P200: 2000000000 | Q200: 2000000000 | R200: 0 | S200: 0
C201: OBLIGASI | D201: Indonesia | E201: STANDARD CHARTERED | F201: Obligasi INDOIS 28 USD | G201: SC | H201: IDR | I201: CLOSE | J201: CLOSE | K201: CLOSE | L201: CLOSE | M201: CLOSE | N201: - | O201: 1931400000 | P201: 1860000000 | Q201: 1860000000 | R201: 1715280000 | S201: 1707360000
C202: OBLIGASI | D202: Indonesia | E202: STANDARD CHARTERED | F202: SR016 | G202: SC | H202: IDR | I202: CLOSE | J202: CLOSE | K202: CLOSE | L202: CLOSE | M202: CLOSE | N202: - | O202: 1000000000 | P202: 1000000000 | Q202: 0 | R202: 0 | S202: 0
C203: REKSADANA | D203: Indonesia | E203: STANDARD CHARTERED | F203: Reksadana SDMP | G203: SC | H203: IDR | I203: CLOSE | J203: CLOSE | K203: CLOSE | L203: CLOSE | M203: CLOSE | N203: - | O203: 370846598 | P203: 0 | Q203: 0 | R203: 0 | S203: 0
C204: REKSADANA | D204: Indonesia | E204: STANDARD CHARTERED | F204: Reksadana MOUA | G204: SC | H204: IDR | I204: CLOSE | J204: CLOSE | K204: CLOSE | L204: CLOSE | M204: CLOSE | N204: - | O204: 87230604 | P204: 0 | Q204: 0 | R204: 0 | S204: 0
C205: OBLIGASI | D205: Indonesia | E205: STANDARD CHARTERED | F205: Obligasi ST011T2 | G205: SC | H205: IDR | I205: CLOSE | J205: CLOSE | K205: CLOSE | L205: CLOSE | M205: CLOSE | N205: - | O205: 3050000000 | P205: 0 | Q205: 0 | R205: 0 | S205: 0
C206: OBLIGASI | D206: Indonesia | E206: STANDARD CHARTERED | F206: Obligasi SR021 | G206: SC | H206: IDR | I206: CLOSE | J206: CLOSE | K206: CLOSE | L206: CLOSE | M206: CLOSE | N206: - | O206: 2400000000 | P206: 0 | Q206: 0 | R206: 0 | S206: 0
C207: OBLIGASI | D207: Indonesia | E207: STANDARD CHARTERED | F207: Obligasi ORI021 | G207: SC | H207: IDR | I207: CLOSE | J207: CLOSE | K207: CLOSE | L207: CLOSE | M207: CLOSE | N207: - | O207: 1150000000 | P207: 0 | Q207: 0 | R207: 0 | S207: 0
C208: OBLIGASI | D208: Indonesia | E208: STANDARD CHARTERED | F208: Reksadana SDM2 | G208: SC | H208: IDR | I208: CLOSE | J208: CLOSE | K208: CLOSE | L208: CLOSE | M208: CLOSE | N208: - | O208: 120650238 | P208: 0 | Q208: 0 | R208: 0 | S208: 0
C209: OBLIGASI | D209: Indonesia | E209: STANDARD CHARTERED | F209: Obligasi SR011 | G209: SC | H209: IDR | I209: CLOSE | J209: CLOSE | K209: CLOSE | L209: CLOSE | M209: CLOSE | N209: - | O209: 0 | P209: 0 | Q209: 1000000000 | R209: 1000000000 | S209: 1000000000
... C252: INVESTASI LAINNYA | D252: Indonesia | E252: BANK CENTRAL ASIA | F252: BCA Asuransi AIA No. Polis 5291 | G252: BCA | H252: IDR | I252: CLOSE | J252: CLOSE | K252: CLOSE | L252: CLOSE | M252: CLOSE | N252: - | O252: 0 | P252: 39063410 | Q252: 0 | R252: 0 | S252: 0
C253: OBLIGASI PEMERINTAH | D253: Indonesia | E253: BANK PAN INDONESIA | F253: Obligasi ORI017 | G253: PAN | H253: IDR | I253: CLOSE | J253: CLOSE | K253: CLOSE | L253: CLOSE | M253: CLOSE | O253: 0 | P253: 0 | Q253: 3000000000 | R253: 3000000000 | S253: 3000000000
C254: OBLIGASI PEMERINTAH | D254: Indonesia | E254: BANK PAN INDONESIA | F254: Obligasi SR013 | G254: PAN | H254: IDR | I254: CLOSE | J254: CLOSE | K254: CLOSE | L254: CLOSE | M254: CLOSE | O254: 0 | P254: 0 | Q254: 2400000000 | R254: 2000000000 | S254: 2400000000
C255: OBLIGASI PEMERINTAH | D255: Indonesia | E255: BANK PAN INDONESIA | F255: Obligasi ORI019 | G255: PAN | H255: IDR | I255: CLOSE | J255: CLOSE | K255: CLOSE | L255: CLOSE | M255: CLOSE | O255: 0 | P255: 2000000000 | Q255: 2000000000 | R255: 2000000000 | S255: 0
C256: OBLIGASI PEMERINTAH | D256: Indonesia | E256: BANK PAN INDONESIA | F256: Obligasi SBR010 | G256: PAN | H256: IDR | I256: CLOSE | J256: CLOSE | K256: CLOSE | L256: CLOSE | M256: CLOSE | O256: 0 | P256: 2000000000 | Q256: 3000000000 | R256: 3000000000 | S256: 0
C257: OBLIGASI PEMERINTAH | D257: Indonesia | E257: BANK PAN INDONESIA | F257: Obligasi INDON 42 USD $200.000 | G257: PAN | H257: IDR | I257: CLOSE | J257: CLOSE | K257: CLOSE | L257: CLOSE | M257: CLOSE | O257: 0 | P257: 3100000000 | Q257: 3100000000 | R257: 2858800000 | S257: 2845600000
C258: OBLIGASI PEMERINTAH | D258: Indonesia | E258: BANK PAN INDONESIA | F258: Obligasi INDON 24 New USD $200.000 | G258: PAN | H258: IDR | I258: CLOSE | J258: CLOSE | K258: CLOSE | L258: CLOSE | M258: CLOSE | O258: 0 | P258: 3100000000 | Q258: 3100000000 | R258: 2858800000 | S258: 2845600000
C259: OBLIGASI PEMERINTAH | D259: Indonesia | E259: BANK PAN INDONESIA | F259: Obligasi PT Pindad | G259: PAN | H259: IDR | I259: CLOSE | J259: CLOSE | K259: CLOSE | L259: CLOSE | M259: CLOSE | O259: 0 | P259: 0 | Q259: 0 | R259: 0 | S259: 2000000000
C260: OBLIGASI PEMERINTAH | D260: Indonesia | E260: BANK PAN INDONESIA | F260: Obligasi FR081 | G260: PAN | H260: IDR | I260: CLOSE | J260: CLOSE | K260: CLOSE | L260: CLOSE | M260: CLOSE | O260: 3000000000 | P260: 3000000000 | Q260: 3000000000 | R260: 3000000000 | S260: 0
C261: OBLIGASI PEMERINTAH | D261: Indonesia | E261: BANK PAN INDONESIA | F261: Obligasi INDON 24 New USD $200.000 | G261: PAN | H261: IDR | I261: CLOSE | J261: CLOSE | K261: CLOSE | L261: CLOSE | M261: CLOSE | O261: 3219000000 | P261: 3100000000 | Q261: 3100000000 | R261: 2858800000 | S261: 2845600000
C262: OBLIGASI PEMERINTAH | D262: Indonesia | E262: BANK PAN INDONESIA | F262: Obligasi SUKUK 27 USD $200.000 | G262: PAN | H262: IDR | I262: CLOSE | J262: CLOSE | K262: CLOSE | L262: CLOSE | M262: CLOSE | O262: 3219000000 | P262: 3100000000 | Q262: 3100000000 | R262: 2858800000 | S262: 2845600000
C263: OBLIGASI PEMERINTAH | D263: Indonesia | E263: BANK PAN INDONESIA | F263: Obligasi INDOIS 27 USD $300.000. 2024 $200.000 | G263: PAN | H263: IDR | I263: CLOSE | J263: CLOSE | K263: CLOSE | L263: CLOSE | M263: CLOSE | O263: 3219000000 | P263: 4650000000 | Q263: 4650000000 | R263: 4288200000 | S263: 4268400000
C264: OBLIGASI PEMERINTAH | D264: Indonesia | E264: BANK PAN INDONESIA | F264: Obligasi SR019 | G264: PAN | H264: IDR | I264: CLOSE | J264: CLOSE | K264: CLOSE | L264: CLOSE | M264: CLOSE | O264: 2600000000 | P264: 2600000000 | Q264: 0 | R264: 0 | S264: 0
... C270: ASURANSI | D270: Indonesia | E270: BANK CIMB NIAGA | F270: Asuransi Fortunax | G270: CIMB | H270: IDR | I270: CLOSE | J270: CLOSE | K270: CLOSE | L270: CLOSE | M270: CLOSE | O270: 422118838 | P270: 0 | Q270: 0 | R270: 0 | S270: 0
B271: =VLOOKUP(C271,T:U,2,) -> #N/A | C271: REKSADANA | D271: Indonesia | E271: BANK HSBC INDONESIA | F271: Reksadana SDP 90 | G271: HSBC | H271: IDR | I271: CLOSE | J271: CLOSE | K271: CLOSE | L271: CLOSE | M271: CLOSE | O271: 0 | P271: 490849503 | Q271: 300807399 | R271: 968068071 | S271: 0
B272: =VLOOKUP(C272,T:U,2,) -> #N/A | C272: REKSADANA | D272: Indonesia | E272: BANK HSBC INDONESIA | F272: Reksadana MS Syariah USD $53.448 | G272: HSBC | H272: USD | I272: CLOSE | J272: CLOSE | K272: CLOSE | L272: CLOSE | M272: CLOSE | O272: 0 | P272: 0 | Q272: 580723000 | R272: 763985712 | S272: 661730052
B273: =VLOOKUP(C273,T:U,2,) -> #N/A | C273: REKSADANA | D273: Indonesia | E273: BANK HSBC INDONESIA | F273: Reksadana SDPP | G273: HSBC | H273: IDR | I273: CLOSE | J273: CLOSE | K273: CLOSE | L273: CLOSE | M273: CLOSE | O273: 0 | P273: 0 | Q273: 0 | R273: 0 | S273: 1022596897
B274: =VLOOKUP(C274,T:U,2,) -> #N/A | C274: REKSADANA | D274: Indonesia | E274: BANK HSBC INDONESIA | F274: Reksadana Manulife Dana Saham | G274: HSBC | H274: IDR | I274: CLOSE | J274: CLOSE | K274: CLOSE | L274: CLOSE | M274: CLOSE | O274: 0 | P274: 0 | Q274: 0 | R274: 0 | S274: 1728081046
B275: =VLOOKUP(C275,T:U,2,) -> #N/A | C275: REKSADANA | D275: Indonesia | E275: BANK HSBC INDONESIA | F275: SUKUK SR 011 | G275: HSBC | H275: IDR | I275: CLOSE | J275: CLOSE | K275: CLOSE | L275: CLOSE | M275: CLOSE | O275: 0 | P275: 0 | Q275: 0 | R275: 0 | S275: 3000000000
B276: =VLOOKUP(C276,T:U,2,) -> #N/A | C276: REKSADANA | D276: Indonesia | E276: BANK HSBC INDONESIA | F276: Reksadana M Pendapatan Tetap | G276: HSBC | H276: IDR | I276: CLOSE | J276: CLOSE | K276: CLOSE | L276: CLOSE | M276: CLOSE | O276: 0 | P276: 0 | Q276: 0 | R276: 0 | S276: 1619992451
B277: =VLOOKUP(C277,T:U,2,) -> #N/A | C277: OBLIGASI | D277: Indonesia | E277: BANK HSBC INDONESIA | F277: Obligasi SBR 011 | G277: HSBC | H277: IDR | I277: CLOSE | J277: CLOSE | K277: CLOSE | L277: CLOSE | M277: CLOSE | O277: 0 | P277: 1950000000 | Q277: 1950000000 | R277: 0 | S277: 0
B278: =VLOOKUP(C278,T:U,2,) -> #N/A | C278: OBLIGASI | D278: Indonesia | E278: BANK HSBC INDONESIA | F278: Obligasi SR 016 | G278: HSBC | H278: IDR | I278: CLOSE | J278: CLOSE | K278: CLOSE | L278: CLOSE | M278: CLOSE | O278: 0 | P278: 0 | Q278: 1000000000 | R278: 0 | S278: 0
B279: =VLOOKUP(C279,T:U,2,) -> #N/A | C279: OBLIGASI | D279: Indonesia | E279: BANK HSBC INDONESIA | F279: Obligasi ORI 018 | G279: HSBC | H279: IDR | I279: CLOSE | J279: CLOSE | K279: CLOSE | L279: CLOSE | M279: CLOSE | O279: 0 | P279: 0 | Q279: 695100000 | R279: 0 | S279: 0
B280: =VLOOKUP(C280,T:U,2,) -> #N/A | C280: OBLIGASI | D280: Indonesia | E280: BANK HSBC INDONESIA | F280: Obligasi ORI 019 | G280: HSBC | H280: IDR | I280: CLOSE | J280: CLOSE | K280: CLOSE | L280: CLOSE | M280: CLOSE | O280: 0 | P280: 0 | Q280: 2470000000 | R280: 0 | S280: 0
B281: =VLOOKUP(C281,T:U,2,) -> #N/A | C281: OBLIGASI | D281: Indonesia | E281: BANK HSBC INDONESIA | F281: Obligasi SBR 011 | G281: HSBC | H281: IDR | I281: CLOSE | J281: CLOSE | K281: CLOSE | L281: CLOSE | M281: CLOSE | O281: 0 | P281: 2000000000 | Q281: 2000000000 | R281: 0 | S281: 0
B282: =VLOOKUP(C282,T:U,2,) -> #N/A | C282: OBLIGASI | D282: Indonesia | E282: BANK HSBC INDONESIA | F282: ORI 023 | G282: HSBC | H282: IDR | I282: CLOSE | J282: CLOSE | K282: CLOSE | L282: CLOSE | M282: CLOSE | O282: 0 | P282: 3400000000 | Q282: 0 | R282: 0 | S282: 0
... B284: =VLOOKUP(C284,T:U,2,) -> #N/A | C284: OBLIGASI | D284: Indonesia | E284: BANK HSBC INDONESIA | F284: Obligasi USD INDON 30 USD $200.000 | G284: HSBC | H284: USD | I284: CLOSE | J284: CLOSE | K284: CLOSE | L284: CLOSE | M284: CLOSE | O284: 0 | P284: 3089000000 | Q284: 0 | R284: 0 | S284: 0
B285: =VLOOKUP(C285,T:U,2,) -> #N/A | C285: OBLIGASI | D285: Indonesia | E285: BANK HSBC INDONESIA | F285: Obligasi SR 011 | G285: HSBC | H285: IDR | I285: IDR | J285: 2025 | K285: CLOSE | L285: CLOSE | M285: CLOSE | O285: 0 | P285: 0 | Q285: 0 | R285: 3000000000 | S285: 3000000000
B286: =VLOOKUP(C286,T:U,2,) -> #N/A | C286: OBLIGASI | D286: Indonesia | E286: BANK HSBC INDONESIA | F286: Obligasi SBR10 | G286: HSBC | H286: IDR | I286: IDR | J286: 2025 | K286: CLOSE | L286: CLOSE | M286: CLOSE | O286: 0 | P286: 0 | Q286: 3000000000 | R286: 3000000000 | S286: 0
B287: =VLOOKUP(C287,T:U,2,) -> #N/A | C287: OBLIGASI | D287: Indonesia | E287: BANK HSBC INDONESIA | F287: Obligasi INDOIS 27 USD $200.000 | G287: HSBC | H287: USD | I287: IDR | J287: 2025 | K287: CLOSE | L287: CLOSE | M287: CLOSE | O287: 0 | P287: 0 | Q287: 3000800000 | R287: 2858800000 | S287: 2845600000
B288: =VLOOKUP(C288,T:U,2,) -> #N/A | C288: OBLIGASI | D288: Indonesia | E288: BANK HSBC INDONESIA | F288: Obligasi ORI 15 | G288: HSBC | H288: IDR | I288: IDR | J288: 2025 | K288: CLOSE | L288: CLOSE | M288: CLOSE | O288: 0 | P288: 0 | Q288: 0 | R288: 0 | S288: 3000000000
B289: =VLOOKUP(C289,T:U,2,) -> #N/A | C289: OBLIGASI | D289: Indonesia | E289: BANK HSBC INDONESIA | F289: Obligasi ORI 016 | G289: HSBC | H289: USD | I289: IDR | J289: 2025 | K289: CLOSE | L289: CLOSE | M289: CLOSE | O289: 0 | P289: 0 | Q289: 0 | R289: 0 | S289: 700000000
C290: OBLIGASI PEMERINTAH | D290: Indonesia | E290: BANK HSBC INDONESIA | F290: OBLIGASI USD INDON 50 $165.840 | G290: HSBC | H290: IDR | I290: CLOSE | J290: CLOSE | K290: CLOSE | L290: CLOSE | M290: CLOSE | O290: 2669194800 | P290: 0 | Q290: 0 | R290: 0 | S290: 0
C291: OBLIGASI PEMERINTAH | D291: Indonesia | E291: BANK HSBC INDONESIA | F291: OBLIGASI ORI025T6 | G291: HSBC | H291: IDR | I291: CLOSE | J291: CLOSE | K291: CLOSE | L291: CLOSE | M291: CLOSE | O291: 2041200000 | P291: 0 | Q291: 0 | R291: 0 | S291: 0
C292: OBLIGASI PEMERINTAH | D292: Indonesia | E292: BANK HSBC INDONESIA | F292: OBLIGASI ORI026T6 | G292: HSBC | H292: IDR | I292: CLOSE | J292: CLOSE | K292: CLOSE | L292: CLOSE | M292: CLOSE | O292: 1940000000 | P292: 0 | Q292: 0 | R292: 0 | S292: 0
C293: REKSADANA | D293: Indonesia | E293: SINARMAS ASSET MANAGEMENT | F293: Sinarmas Asset Mng. - Equity link note 111475 | G293: SMAS | H293: IDR | I293: CLOSE | J293: CLOSE | K293: CLOSE | L293: CLOSE | M293: CLOSE | O293: 0 | P293: 0 | Q293: 0 | R293: 1052659450 | S293: 1072392000
C294: REKSADANA | D294: Indonesia | E294: SINARMAS ASSET MANAGEMENT | F294: Sinarmas Asset Mng. - Credit Link note 110807 | G294: SMAS | H294: IDR | I294: CLOSE | J294: CLOSE | K294: CLOSE | L294: CLOSE | M294: CLOSE | O294: 0 | P294: 0 | Q294: 0 | R294: 908816730 | S294: 895007000
C295: REKSADANA | D295: Indonesia | E295: SINARMAS ASSET MANAGEMENT | F295: Sinarmas Sinarmas Saham | G295: SMAS | H295: IDR | I295: CLOSE | J295: CLOSE | K295: CLOSE | L295: CLOSE | M295: CLOSE | O295: 5450835 | P295: 0 | Q295: 0 | R295: 0 | S295: 0
C296: INVESTASI LAINNYA | D296: Indonesia | E296: BANK DBS INDONESIA | F296: Asuransi Jiwasraya RA 020101697 | G296: SSEK | H296: IDR | I296: CLOSE | J296: CLOSE | K296: CLOSE | L296: CLOSE | M296: CLOSE | O296: 0 | P296: 0 | Q296: 159446670 | R296: 159446670 | S296: 1539516000
C297: INVESTASI LAINNYA | D297: Indonesia | E297: BANK DBS INDONESIA | F297: Asuransi Jiwasraya RA 020105627 | G297: SSEK | H297: IDR | I297: CLOSE | J297: CLOSE | K297: CLOSE | L297: CLOSE | M297: CLOSE | O297: 0 | P297: 0 | Q297: 110528100 | R297: 110528100 | S297: 1070000000
...

Sheet Sheet3
